Workbook

Sheet Assumptions
A1: MODEL ASSUMPTIONS
A2: Blue = input | Green = linked value | Black = calculation | Yellow = verify
A3: GENERAL
A4: Analysis start year | B4: 2026 | C4: Fiscal Year 1 (October 2026 to September 2027)
A5: Season start date | B5: 46296
A6: Currency | B6: AED
A8: DEMAND ASSUMPTIONS
A9: FY1 event pipeline count | B9: =COUNTA('FY1 Event Pipeline'!A4:A15) -> 12 | C9: From 'FY1 Event Pipeline' sheet
A10: Target coverage of peak concurrency - Cabins | B10: 0.85 | C10: Percentile of probability-adjusted peak owned in fleet
A11: Target coverage of peak concurrency - Buggies | B11: 0.5
A12: Target coverage of peak concurrency - Barriers | B12: 0.85
A13: Target coverage of peak concurrency - Fencing | B13: 0.85
A14: Target coverage of peak concurrency - Terratrak | B14: 0.85
A15: Events % growth YoY | B15: 0.1 | C15: - 10% growth in annual events - conservative assumption for outdoor festivals, concerts, and public-events (projected 10-16% CAGR). - Growth rate drives peak concurrency (thus fleet growth) & cabin-days deployed
A17: REVENUE - RENTAL RATES (DAILY)
A18: Revenue per cabin per day | B18: 350 | C18: approx. 10,000/30 day event rate rounded up as peak daily rate
A19: Revenue per buggy per day | B19: 700 | C19: Daily rental rate from original model (ensure this isn't rented out in weekly slabs)
A20: Revenue per barrier per day | B20: =12/30 -> 0.4 | C20: AED 0.4/day rate per barrier - monthly-slab rental @ AED 12/barrier/month
A21: Revenue per fencing per day | B21: =55/30 -> 1.8333333 | C21: AED 1.83/day rate per fencing - monthly-slab rental @ AED 55/fence/month
A22: Revenue per flooring per day | B22: =900/30 -> 30 | C22: AED 30/day rate per flooring - monthly-slab rental @ AED 900/floor/month
C23: Rental Rate Growth?
A25: CAPEX
A26: Cabin useful life (years) | B26: 8 | C26: 8 years, straight-line
A27: Cabin residual value (% of CapEx) | B27: 0.2 | C27: 20% residual at end of useful life
A28: Cabin annual maintenance (% of CapEx p.a.) | B28: 0.025 | C28: 2.5% of gross capex
A29: Buggie cost per unit | B29: 40000 | C29: Avg. all-in cost
A30: Buggie useful life (years) | B30: 10 | C30: 10 years, straight-line
A31: Buggie residual value (% of CapEx) | B31: 0.3 | C31: 30% residual at end of useful life
A32: Buggie annual maintenance (% of CapEx p.a.) | B32: 0.025 | C32: 2.5% of gross capex
A33: Barrier cost per unit | B33: 300 | C33: Avg. all-in cost
A34: Fencing cost per unit | B34: 400 | C34: Avg. all-in cost
A35: Barriers & Fencing useful life (years) | B35: 10 | C35: 10 years, straight-line
A36: Barriers & Fencing residual value (% of CapEx) | B36: 0.4 | C36: 40% residual at end of useful life
A37: Barriers & Fencing annual maintenance (% of CapEx p.a.) | B37: 0.005 | C37: 0.5% of gross capex
... A42: Material cost inflation | B42: 0.02 | C42: 2.0% Y-o-Y unit price escalation
A44: OPEX / OVERHEAD
A45: Cabin Storage Yard Rental | B45: 20 | C45: Price (AED) per sqft per year
A46: % Circulation
A47: Hot desk rent / head / month | B47: 2000 | C47: Avg. cost of a fixed seat in a shared, coworking environment.
A48: Marketing budget per month | B48: 10000
A49: DEWA + utilities / month | B49: 1500 | C49: Buggie charging, lighting, cleaning, repairs, temperature moderation
A50: Insurance (fleet + liability) | B50: 22000 | C50: Verify
A51: Misc / contingency | B51: 50000 | C51: From original model
A52: Overhead escalation (% p.a.) | B52: 0.05 | C52: Utilities, insurance, office rent & contingency

Sheet FY1 Event Pipeline
A1: FINANCIAL YEAR 1 EVENT PIPELINE
A2: List of all the events in the FY 2026-2027 pipeline | Model assumes all assets are on hire upon delivery at mobilization start date until the demobilization end date | The events and asset demand form the basis for the demand distribution
A3: Event | B3: Venue | C3: Win Rate | D3: Live Open | E3: Live Close | F3: Days Live | G3: Days Mob | H3: Mob Start | I3: Days Demob | J3: Demob End | K3: Paid Hire Days | L3: Monthly-Slabs | M3: Weekly-Slabs | N3: Cabins | O3: Buggies | P3: Barriers | Q3: Fencing | R3: Terratrak | S3: Python Tuple Input
A4: Saadiyat Nights | B4: Saadiyat Island open-air | C4: 0.5 | D4: 46327 | E4: 46446 | F4: =E4-D4+1 -> 120 | G4: 30 | H4: =D4-G4 -> 46297 | I4: 7 | J4: =E4+I4 -> 46453 | K4: =J4-H4+1 -> 157 | L4: =_xlfn.CEILING.MATH(K4/30,1) -> 6 | M4: =_xlfn.CEILING.MATH(K4/7,1) -> 23 | N4: 10 | O4: 10 | P4: 0 | Q4: 0 | R4: 280 | S4: =_xlfn.CONCAT("('",,A4,"',",C4,",",H4-$B$17,",",J4-$B$17,",",N4,",",O4,",",P4,",",Q4,",",R4,"),") -> ('Saadiyat Nights',0.5,1,157,10,10,0,0,280),
A5: BRED X | B5: Yas Marina Circuit / TBC | C5: 0.5 | D5: 46332 | E5: 46336 | F5: =E5-D5+1 -> 5 | G5: 14 | H5: =D5-G5 -> 46318 | I5: 3 | J5: =E5+I5 -> 46339 | K5: =J5-H5+1 -> 22 | L5: =_xlfn.CEILING.MATH(K5/30,1) -> 1 | M5: =_xlfn.CEILING.MATH(K5/7,1) -> 4 | N5: 8 | O5: 0 | P5: 0 | Q5: 0 | R5: 0 | S5: =_xlfn.CONCAT("('",,A5,"',",C5,",",H5-$B$17,",",J5-$B$17,",",N5,",",O5,",",P5,",",Q5,",",R5,"),") -> ('BRED X',0.5,22,43,8,0,0,0,0),
A6: MOTN DHA | B6: Al Dhafra | C6: 0.5 | D6: 46344 | E6: 46349 | F6: =E6-D6+1 -> 6 | G6: 14 | H6: =D6-G6 -> 46330 | I6: 3 | J6: =E6+I6 -> 46352 | K6: =J6-H6+1 -> 23 | L6: =_xlfn.CEILING.MATH(K6/30,1) -> 1 | M6: =_xlfn.CEILING.MATH(K6/7,1) -> 4 | N6: 8 | O6: 6 | P6: 350 | Q6: 550 | R6: 0 | S6: =_xlfn.CONCAT("('",,A6,"',",C6,",",H6-$B$17,",",J6-$B$17,",",N6,",",O6,",",P6,",",Q6,",",R6,"),") -> ('MOTN DHA',0.5,34,56,8,6,350,550,0),
A7: No Art UAE | B7: Saadiyat Island / TBC | C7: 0.5 | D7: 46346 | E7: 46350 | F7: =E7-D7+1 -> 5 | G7: 14 | H7: =D7-G7 -> 46332 | I7: 3 | J7: =E7+I7 -> 46353 | K7: =J7-H7+1 -> 22 | L7: =_xlfn.CEILING.MATH(K7/30,1) -> 1 | M7: =_xlfn.CEILING.MATH(K7/7,1) -> 4 | N7: 24 | O7: 6 | P7: 0 | Q7: 0 | R7: 200 | S7: =_xlfn.CONCAT("('",,A7,"',",C7,",",H7-$B$17,",",J7-$B$17,",",N7,",",O7,",",P7,",",Q7,",",R7,"),") -> ('No Art UAE',0.5,36,57,24,6,0,0,200),
A8: Tanweer Festival | B8: Mleiha Desert, Sharjah | C8: 0.5 | D8: 46347 | E8: 46349 | F8: =E8-D8+1 -> 3 | G8: 7 | H8: =D8-G8 -> 46340 | I8: 3 | J8: =E8+I8 -> 46352 | K8: =J8-H8+1 -> 13 | L8: =_xlfn.CEILING.MATH(K8/30,1) -> 1 | M8: =_xlfn.CEILING.MATH(K8/7,1) -> 2 | N8: 0 | O8: 8 | P8: 900 | Q8: 50 | R8: 200 | S8: =_xlfn.CONCAT("('",,A8,"',",C8,",",H8-$B$17,",",J8-$B$17,",",N8,",",O8,",",P8,",",Q8,",",R8,"),") -> ('Tanweer Festival',0.5,44,56,0,8,900,50,200),
A9: MOTN AAN | B9: Al Ain | C9: 0.5 | D9: 46350 | E9: 46358 | F9: =E9-D9+1 -> 9 | G9: 14 | H9: =D9-G9 -> 46336 | I9: 4 | J9: =E9+I9 -> 46362 | K9: =J9-H9+1 -> 27 | L9: =_xlfn.CEILING.MATH(K9/30,1) -> 1 | M9: =_xlfn.CEILING.MATH(K9/7,1) -> 4 | N9: 18 | O9: 6 | P9: 350 | Q9: 550 | R9: 0 | S9: =_xlfn.CONCAT("('",,A9,"',",C9,",",H9-$B$17,",",J9-$B$17,",",N9,",",O9,",",P9,",",Q9,",",R9,"),") -> ('MOTN AAN',0.5,40,66,18,6,350,550,0),
A10: F1 Afterparty | B10: Yas Marina Circuit, Yas Island | C10: 0.5 | D10: 46360 | E10: 46362 | F10: =E10-D10+1 -> 3 | G10: 7 | H10: =D10-G10 -> 46353 | I10: 3 | J10: =E10+I10 -> 46365 | K10: =J10-H10+1 -> 13 | L10: =_xlfn.CEILING.MATH(K10/30,1) -> 1 | M10: =_xlfn.CEILING.MATH(K10/7,1) -> 2 | N10: 29 | O10: 8 | P10: 714 | Q10: 1180 | R10: 178 | S10: =_xlfn.CONCAT("('",,A10,"',",C10,",",H10-$B$17,",",J10-$B$17,",",N10,",",O10,",",P10,",",Q10,",",R10,"),") -> ('F1 Afterparty',0.5,57,69,29,8,714,1180,178),
A11: MOTN AUH | B11: Abu Dhabi Corniche | C11: 0.5 | D11: 46366 | E11: 46391 | F11: =E11-D11+1 -> 26 | G11: 20 | H11: =D11-G11 -> 46346 | I11: 7 | J11: =E11+I11 -> 46398 | K11: =J11-H11+1 -> 53 | L11: =_xlfn.CEILING.MATH(K11/30,1) -> 2 | M11: =_xlfn.CEILING.MATH(K11/7,1) -> 8 | N11: 20 | O11: 10 | P11: 700 | Q11: 1100 | R11: 200 | S11: =_xlfn.CONCAT("('",,A11,"',",C11,",",H11-$B$17,",",J11-$B$17,",",N11,",",O11,",",P11,",",Q11,",",R11,"),") -> ('MOTN AUH',0.5,50,102,20,10,700,1100,200),
A12: Yas Winterfest | B12: Yas Gateway Park, Yas Island | C12: 0.5 | D12: 46367 | E12: 46377 | F12: =E12-D12+1 -> 11 | G12: 15 | H12: =D12-G12 -> 46352 | I12: 7 | J12: =E12+I12 -> 46384 | K12: =J12-H12+1 -> 33 | L12: =_xlfn.CEILING.MATH(K12/30,1) -> 2 | M12: =_xlfn.CEILING.MATH(K12/7,1) -> 5 | N12: 6 | O12: 4 | P12: 644 | Q12: 760 | R12: 60 | S12: =_xlfn.CONCAT("('",,A12,"',",C12,",",H12-$B$17,",",J12-$B$17,",",N12,",",O12,",",P12,",",Q12,",",R12,"),") -> ('Yas Winterfest',0.5,56,88,6,4,644,760,60),
A13: Animenia | B13: Manarat Al Saadiyat | C13: 0.5 | D13: 46429 | E13: 46433 | F13: =E13-D13+1 -> 5 | G13: 15 | H13: =D13-G13 -> 46414 | I13: 3 | J13: =E13+I13 -> 46436 | K13: =J13-H13+1 -> 23 | L13: =_xlfn.CEILING.MATH(K13/30,1) -> 1 | M13: =_xlfn.CEILING.MATH(K13/7,1) -> 4 | N13: 8 | O13: 4 | P13: 288 | Q13: 192 | R13: 0 | S13: =_xlfn.CONCAT("('",,A13,"',",C13,",",H13-$B$17,",",J13-$B$17,",",N13,",",O13,",",P13,",",Q13,",",R13,"),") -> ('Animenia',0.5,118,140,8,4,288,192,0),
A14: DAZ | B14: Al Jahili Park, Al Ain | C14: 0.5 | D14: 46480 | E14: 46489 | F14: =E14-D14+1 -> 10 | G14: 14 | H14: =D14-G14 -> 46466 | I14: 7 | J14: =E14+I14 -> 46496 | K14: =J14-H14+1 -> 31 | L14: =_xlfn.CEILING.MATH(K14/30,1) -> 2 | M14: =_xlfn.CEILING.MATH(K14/7,1) -> 5 | N14: 15 | O14: 4 | P14: 775 | Q14: 225 | R14: 60 | S14: =_xlfn.CONCAT("('",,A14,"',",C14,",",H14-$B$17,",",J14-$B$17,",",N14,",",O14,",",P14,",",Q14,",",R14,"),") -> ('DAZ',0.5,170,200,15,4,775,225,60),
A15: BRED | B15: Yas Marina Circuit, Yas Island | C15: 0.5 | D15: 46499 | E15: 46503 | F15: =E15-D15+1 -> 5 | G15: 7 | H15: =D15-G15 -> 46492 | I15: 3 | J15: =E15+I15 -> 46506 | K15: =J15-H15+1 -> 15 | L15: =_xlfn.CEILING.MATH(K15/30,1) -> 1 | M15: =_xlfn.CEILING.MATH(K15/7,1) -> 3 | N15: 22 | O15: 6 | P15: 1500 | Q15: 500 | R15: 0 | S15: =_xlfn.CONCAT("('",,A15,"',",C15,",",H15-$B$17,",",J15-$B$17,",",N15,",",O15,",",P15,",",Q15,",",R15,"),") -> ('BRED',0.5,196,210,22,6,1500,500,0),
M16: Mean | N16: =AVERAGE(N4:N15) -> 14 | O16: =AVERAGE(O4:O15) -> 6 | P16: =AVERAGE(P4:P15) -> 518.41667 | Q16: =AVERAGE(Q4:Q15) -> 425.58333 | R16: =AVERAGE(R4:R15) -> 98.166667
A17: Calendar Start | B17: =Assumptions!B5 -> 46296 | M17: Median | N17: =MEDIAN(N4:N15) -> 12.5 | O17: =MEDIAN(O4:O15) -> 6 | P17: =MEDIAN(P4:P15) -> 497 | Q17: =MEDIAN(Q4:Q15) -> 362.5 | R17: =MEDIAN(R4:R15) -> 60
A19: FY1 (2026-2027) Concurrent Demand Curve

Sheet Human Resources
A1: HUMAN RESOURCES
A2: Personnel Count
A3: Position | D3: Year 1 | E3: Year 2 | F3: Year 3 | G3: Year 4 | H3: Year 5 | I3: Year 6 | J3: Year 7 | K3: Year 8
A4: General Manager (to hire) | D4: 1 | E4: 1 | F4: 1 | G4: 1 | H4: 1 | I4: 1 | J4: 1 | K4: 1
A5: Sales Manager | D5: 1 | E5: 1 | F5: 1 | G5: 1 | H5: 1 | I5: 1 | J5: 1 | K5: 1
A6: Accountant | D6: 1 | E6: 1 | F6: 1 | G6: 1 | H6: 1 | I6: 1 | J6: 1 | K6: 1
A7: Operations Manager | D7: 1 | E7: 1 | F7: 1 | G7: 1 | H7: 1 | I7: 1 | J7: 1 | K7: 1
A8: Plumber | D8: 1 | E8: 1 | F8: 2 | G8: 2 | H8: 3 | I8: 3 | J8: 4 | K8: 4
A9: Electrician | D9: 1 | E9: 1 | F9: 2 | G9: 2 | H9: 3 | I9: 3 | J9: 4 | K9: 4
A10: Admin | D10: 1 | E10: 1 | F10: 1 | G10: 1 | H10: 1 | I10: 2 | J10: 2 | K10: 2
A12: Salary/Personnel
A13: Position | B13: Monthly | C13: % Esc. | D13: Year 1 | E13: Year 2 | F13: Year 3 | G13: Year 4 | H13: Year 5 | I13: Year 6 | J13: Year 7 | K13: Year 8
A14: General Manager (to hire) | D14: 0 | E14: 0 | F14: 0 | G14: 0 | H14: 0 | I14: 0 | J14: 0 | K14: 0
A15: Sales Manager | B15: 12000 | C15: 0.1 | D15: =B15*12 -> 144000 | E15: =D15*(1+$C15) -> 158400 | F15: =E15*(1+$C15) -> 174240 | G15: =F15*(1+$C15) -> 191664 | H15: =G15*(1+$C15) -> 210830.4 | I15: =H15*(1+$C15) -> 231913.44 | J15: =I15*(1+$C15) -> 255104.78 | K15: =J15*(1+$C15) -> 280615.26
A16: Accountant | B16: 5000 | C16: 0.1 | D16: =B16*12 -> 60000 | E16: =D16*(1+$C16) -> 66000 | F16: =E16*(1+$C16) -> 72600 | G16: =F16*(1+$C16) -> 79860 | H16: =G16*(1+$C16) -> 87846 | I16: =H16*(1+$C16) -> 96630.6 | J16: =I16*(1+$C16) -> 106293.66 | K16: =J16*(1+$C16) -> 116923.03
A17: Operations Manager | B17: 12000 | C17: 0.1 | D17: =B17*12 -> 144000 | E17: =D17*(1+$C17) -> 158400 | F17: =E17*(1+$C17) -> 174240 | G17: =F17*(1+$C17) -> 191664 | H17: =G17*(1+$C17) -> 210830.4 | I17: =H17*(1+$C17) -> 231913.44 | J17: =I17*(1+$C17) -> 255104.78 | K17: =J17*(1+$C17) -> 280615.26
A18: Plumber | B18: 4000 | C18: 0.05 | D18: =B18*12 -> 48000 | E18: =D18*(1+$C18) -> 50400 | F18: =E18*(1+$C18) -> 52920 | G18: =F18*(1+$C18) -> 55566 | H18: =G18*(1+$C18) -> 58344.3 | I18: =H18*(1+$C18) -> 61261.515 | J18: =I18*(1+$C18) -> 64324.591 | K18: =J18*(1+$C18) -> 67540.82
A19: Electrician | B19: 4000 | C19: 0.05 | D19: =B19*12 -> 48000 | E19: =D19*(1+$C19) -> 50400 | F19: =E19*(1+$C19) -> 52920 | G19: =F19*(1+$C19) -> 55566 | H19: =G19*(1+$C19) -> 58344.3 | I19: =H19*(1+$C19) -> 61261.515 | J19: =I19*(1+$C19) -> 64324.591 | K19: =J19*(1+$C19) -> 67540.82
A20: Admin | B20: 4000 | C20: 0.05 | D20: =B20*12 -> 48000 | E20: =D20*(1+$C20) -> 50400 | F20: =E20*(1+$C20) -> 52920 | G20: =F20*(1+$C20) -> 55566 | H20: =G20*(1+$C20) -> 58344.3 | I20: =H20*(1+$C20) -> 61261.515 | J20: =I20*(1+$C20) -> 64324.591 | K20: =J20*(1+$C20) -> 67540.82
A22: Total Salary
A23: Position | D23: Year 1 | E23: Year 2 | F23: Year 3 | G23: Year 4 | H23: Year 5 | I23: Year 6 | J23: Year 7 | K23: Year 8
A24: General Manager (to hire) | D24: =D4*D14 -> 0 | E24: =E4*E14 -> 0 | F24: =F4*F14 -> 0 | G24: =G4*G14 -> 0 | H24: =H4*H14 -> 0 | I24: =I4*I14 -> 0 | J24: =J4*J14 -> 0 | K24: =K4*K14 -> 0
A25: Sales Manager | D25: =D5*D15 -> 144000 | E25: =E5*E15 -> 158400 | F25: =F5*F15 -> 174240 | G25: =G5*G15 -> 191664 | H25: =H5*H15 -> 210830.4 | I25: =I5*I15 -> 231913.44 | J25: =J5*J15 -> 255104.78 | K25: =K5*K15 -> 280615.26
A26: Accountant | D26: =D6*D16 -> 60000 | E26: =E6*E16 -> 66000 | F26: =F6*F16 -> 72600 | G26: =G6*G16 -> 79860 | H26: =H6*H16 -> 87846 | I26: =I6*I16 -> 96630.6 | J26: =J6*J16 -> 106293.66 | K26: =K6*K16 -> 116923.03
A27: Operations Manager | D27: =D7*D17 -> 144000 | E27: =E7*E17 -> 158400 | F27: =F7*F17 -> 174240 | G27: =G7*G17 -> 191664 | H27: =H7*H17 -> 210830.4 | I27: =I7*I17 -> 231913.44 | J27: =J7*J17 -> 255104.78 | K27: =K7*K17 -> 280615.26
A28: Plumber | D28: =D8*D18 -> 48000 | E28: =E8*E18 -> 50400 | F28: =F8*F18 -> 105840 | G28: =G8*G18 -> 111132 | H28: =H8*H18 -> 175032.9 | I28: =I8*I18 -> 183784.55 | J28: =J8*J18 -> 257298.36 | K28: =K8*K18 -> 270163.28
A29: Electrician | D29: =D9*D19 -> 48000 | E29: =E9*E19 -> 50400 | F29: =F9*F19 -> 105840 | G29: =G9*G19 -> 111132 | H29: =H9*H19 -> 175032.9 | I29: =I9*I19 -> 183784.55 | J29: =J9*J19 -> 257298.36 | K29: =K9*K19 -> 270163.28
A30: Admin | D30: =D10*D20 -> 48000 | E30: =E10*E20 -> 50400 | F30: =F10*F20 -> 52920 | G30: =G10*G20 -> 55566 | H30: =H10*H20 -> 58344.3 | I30: =I10*I20 -> 122523.03 | J30: =J10*J20 -> 128649.18 | K30: =K10*K20 -> 135081.64
A31: SUMMARY
A32: Annual Salary | D32: =SUM(D24:D30) -> 492000 | E32: =SUM(E24:E30) -> 534000 | F32: =SUM(F24:F30) -> 685680 | G32: =SUM(G24:G30) -> 741018 | H32: =SUM(H24:H30) -> 917916.9 | I32: =SUM(I24:I30) -> 1050549.6 | J32: =SUM(J24:J30) -> 1259749.1 | K32: =SUM(K24:K30) -> 1353561.8
A34: Office Desks
D35: Year 1 | E35: Year 2 | F35: Year 3 | G35: Year 4 | H35: Year 5 | I35: Year 6 | J35: Year 7 | K35: Year 8
A36: Desks needed | D36: =SUM(D4:D7,D10) -> 5 | E36: =SUM(E4:E7,E10) -> 5 | F36: =SUM(F4:F7,F10) -> 5 | G36: =SUM(G4:G7,G10) -> 5 | H36: =SUM(H4:H7,H10) -> 5 | I36: 6 | J36: 6 | K36: 6
A37: Annual rent per seat | D37: =Assumptions!B47*12 -> 24000 | E37: =D37*(1+Assumptions!$B$52) -> 25200 | F37: =E37*(1+Assumptions!$B$52) -> 26460 | G37: =F37*(1+Assumptions!$B$52) -> 27783 | H37: =G37*(1+Assumptions!$B$52) -> 29172.15 | I37: =H37*(1+Assumptions!$B$52) -> 30630.758 | J37: =I37*(1+Assumptions!$B$52) -> 32162.295 | K37: =J37*(1+Assumptions!$B$52) -> 33770.41
A38: Total rental cost | D38: =D37*D36 -> 120000 | E38: =E37*E36 -> 126000 | F38: =F37*F36 -> 132300 | G38: =G37*G36 -> 138915 | H38: =H37*H36 -> 145860.75 | I38: =I37*I36 -> 183784.55 | J38: =J37*J36 -> 192973.77 | K38: =K37*K36 -> 202622.46

Sheet CapEx & Storage
A1: CAPEX & STORAGE
E2: 0 | F2: =E2+1 -> 1 | G2: =F2+1 -> 2 | H2: =G2+1 -> 3 | I2: =H2+1 -> 4 | J2: =I2+1 -> 5 | K2: =J2+1 -> 6 | L2: =K2+1 -> 7
A3: SIMULATED ASSET REQUIREMENT
E4: Year 1 | F4: Year 2 | G4: Year 3 | H4: Year 4 | I4: Year 5 | J4: Year 6 | K4: Year 7 | L4: Year 8
A5: Cabins | E5: {=INDEX(Simulation!$D$2:$G$41,MATCH(1,(Simulation!$C$2:$C$41=$A5)*(Simulation!$A$2:$A$41=E$2+1),0),MATCH($D12,Simulation!$D$1:$G$1,0))} -> 80 | F5: {=INDEX(Simulation!$D$2:$G$41,MATCH(1,(Simulation!$C$2:$C$41=$A5)*(Simulation!$A$2:$A$41=F$2+1),0),MATCH($D12,Simulation!$D$1:$G$1,0))} -> 83 | G5: {=INDEX(Simulation!$D$2:$G$41,MATCH(1,(Simulation!$C$2:$C$41=$A5)*(Simulation!$A$2:$A$41=G$2+1),0),MATCH($D12,Simulation!$D$1:$G$1,0))} -> 90 | H5: {=INDEX(Simulation!$D$2:$G$41,MATCH(1,(Simulation!$C$2:$C$41=$A5)*(Simulation!$A$2:$A$41=H$2+1),0),MATCH($D12,Simulation!$D$1:$G$1,0))} -> 97 | I5: {=INDEX(Simulation!$D$2:$G$41,MATCH(1,(Simulation!$C$2:$C$41=$A5)*(Simulation!$A$2:$A$41=I$2+1),0),MATCH($D12,Simulation!$D$1:$G$1,0))} -> 100 | J5: {=INDEX(Simulation!$D$2:$G$41,MATCH(1,(Simulation!$C$2:$C$41=$A5)*(Simulation!$A$2:$A$41=J$2+1),0),MATCH($D12,Simulation!$D$1:$G$1,0))} -> 109 | K5: {=INDEX(Simulation!$D$2:$G$41,MATCH(1,(Simulation!$C$2:$C$41=$A5)*(Simulation!$A$2:$A$41=K$2+1),0),MATCH($D12,Simulation!$D$1:$G$1,0))} -> 120 | L5: {=INDEX(Simulation!$D$2:$G$41,MATCH(1,(Simulation!$C$2:$C$41=$A5)*(Simulation!$A$2:$A$41=L$2+1),0),MATCH($D12,Simulation!$D$1:$G$1,0))} -> 127
A6: Buggies | E6: {=INDEX(Simulation!$D$2:$G$41,MATCH(1,(Simulation!$C$2:$C$41=$A6)*(Simulation!$A$2:$A$41=E$2+1),0),MATCH($D13,Simulation!$D$1:$G$1,0))} -> 26 | F6: {=INDEX(Simulation!$D$2:$G$41,MATCH(1,(Simulation!$C$2:$C$41=$A6)*(Simulation!$A$2:$A$41=F$2+1),0),MATCH($D13,Simulation!$D$1:$G$1,0))} -> 28 | G6: {=INDEX(Simulation!$D$2:$G$41,MATCH(1,(Simulation!$C$2:$C$41=$A6)*(Simulation!$A$2:$A$41=G$2+1),0),MATCH($D13,Simulation!$D$1:$G$1,0))} -> 30 | H6: {=INDEX(Simulation!$D$2:$G$41,MATCH(1,(Simulation!$C$2:$C$41=$A6)*(Simulation!$A$2:$A$41=H$2+1),0),MATCH($D13,Simulation!$D$1:$G$1,0))} -> 34 | I6: {=INDEX(Simulation!$D$2:$G$41,MATCH(1,(Simulation!$C$2:$C$41=$A6)*(Simulation!$A$2:$A$41=I$2+1),0),MATCH($D13,Simulation!$D$1:$G$1,0))} -> 34 | J6: {=INDEX(Simulation!$D$2:$G$41,MATCH(1,(Simulation!$C$2:$C$41=$A6)*(Simulation!$A$2:$A$41=J$2+1),0),MATCH($D13,Simulation!$D$1:$G$1,0))} -> 38 | K6: {=INDEX(Simulation!$D$2:$G$41,MATCH(1,(Simulation!$C$2:$C$41=$A6)*(Simulation!$A$2:$A$41=K$2+1),0),MATCH($D13,Simulation!$D$1:$G$1,0))} -> 42 | L6: {=INDEX(Simulation!$D$2:$G$41,MATCH(1,(Simulation!$C$2:$C$41=$A6)*(Simulation!$A$2:$A$41=L$2+1),0),MATCH($D13,Simulation!$D$1:$G$1,0))} -> 46
A7: Barriers | E7: {=INDEX(Simulation!$D$2:$G$41,MATCH(1,(Simulation!$C$2:$C$41=$A7)*(Simulation!$A$2:$A$41=E$2+1),0),MATCH($D14,Simulation!$D$1:$G$1,0))} -> 2300 | F7: {=INDEX(Simulation!$D$2:$G$41,MATCH(1,(Simulation!$C$2:$C$41=$A7)*(Simulation!$A$2:$A$41=F$2+1),0),MATCH($D14,Simulation!$D$1:$G$1,0))} -> 2408 | G7: {=INDEX(Simulation!$D$2:$G$41,MATCH(1,(Simulation!$C$2:$C$41=$A7)*(Simulation!$A$2:$A$41=G$2+1),0),MATCH($D14,Simulation!$D$1:$G$1,0))} -> 2744 | H7: {=INDEX(Simulation!$D$2:$G$41,MATCH(1,(Simulation!$C$2:$C$41=$A7)*(Simulation!$A$2:$A$41=H$2+1),0),MATCH($D14,Simulation!$D$1:$G$1,0))} -> 2950 | I7: {=INDEX(Simulation!$D$2:$G$41,MATCH(1,(Simulation!$C$2:$C$41=$A7)*(Simulation!$A$2:$A$41=I$2+1),0),MATCH($D14,Simulation!$D$1:$G$1,0))} -> 3094 | J7: {=INDEX(Simulation!$D$2:$G$41,MATCH(1,(Simulation!$C$2:$C$41=$A7)*(Simulation!$A$2:$A$41=J$2+1),0),MATCH($D14,Simulation!$D$1:$G$1,0))} -> 3558 | K7: {=INDEX(Simulation!$D$2:$G$41,MATCH(1,(Simulation!$C$2:$C$41=$A7)*(Simulation!$A$2:$A$41=K$2+1),0),MATCH($D14,Simulation!$D$1:$G$1,0))} -> 3950 | L7: {=INDEX(Simulation!$D$2:$G$41,MATCH(1,(Simulation!$C$2:$C$41=$A7)*(Simulation!$A$2:$A$41=L$2+1),0),MATCH($D14,Simulation!$D$1:$G$1,0))} -> 4264
A8: Fencing | E8: {=INDEX(Simulation!$D$2:$G$41,MATCH(1,(Simulation!$C$2:$C$41=$A8)*(Simulation!$A$2:$A$41=E$2+1),0),MATCH($D15,Simulation!$D$1:$G$1,0))} -> 2960 | F8: {=INDEX(Simulation!$D$2:$G$41,MATCH(1,(Simulation!$C$2:$C$41=$A8)*(Simulation!$A$2:$A$41=F$2+1),0),MATCH($D15,Simulation!$D$1:$G$1,0))} -> 3010 | G8: {=INDEX(Simulation!$D$2:$G$41,MATCH(1,(Simulation!$C$2:$C$41=$A8)*(Simulation!$A$2:$A$41=G$2+1),0),MATCH($D15,Simulation!$D$1:$G$1,0))} -> 3230 | H8: {=INDEX(Simulation!$D$2:$G$41,MATCH(1,(Simulation!$C$2:$C$41=$A8)*(Simulation!$A$2:$A$41=H$2+1),0),MATCH($D15,Simulation!$D$1:$G$1,0))} -> 3440 | I8: {=INDEX(Simulation!$D$2:$G$41,MATCH(1,(Simulation!$C$2:$C$41=$A8)*(Simulation!$A$2:$A$41=I$2+1),0),MATCH($D15,Simulation!$D$1:$G$1,0))} -> 3590 | J8: {=INDEX(Simulation!$D$2:$G$41,MATCH(1,(Simulation!$C$2:$C$41=$A8)*(Simulation!$A$2:$A$41=J$2+1),0),MATCH($D15,Simulation!$D$1:$G$1,0))} -> 3880 | K8: {=INDEX(Simulation!$D$2:$G$41,MATCH(1,(Simulation!$C$2:$C$41=$A8)*(Simulation!$A$2:$A$41=K$2+1),0),MATCH($D15,Simulation!$D$1:$G$1,0))} -> 4340 | L8: {=INDEX(Simulation!$D$2:$G$41,MATCH(1,(Simulation!$C$2:$C$41=$A8)*(Simulation!$A$2:$A$41=L$2+1),0),MATCH($D15,Simulation!$D$1:$G$1,0))} -> 4490
A9: Flooring | E9: {=INDEX(Simulation!$D$2:$G$41,MATCH(1,(Simulation!$C$2:$C$41=$A9)*(Simulation!$A$2:$A$41=E$2+1),0),MATCH($D16,Simulation!$D$1:$G$1,0))} -> 740 | F9: {=INDEX(Simulation!$D$2:$G$41,MATCH(1,(Simulation!$C$2:$C$41=$A9)*(Simulation!$A$2:$A$41=F$2+1),0),MATCH($D16,Simulation!$D$1:$G$1,0))} -> 740 | G9: {=INDEX(Simulation!$D$2:$G$41,MATCH(1,(Simulation!$C$2:$C$41=$A9)*(Simulation!$A$2:$A$41=G$2+1),0),MATCH($D16,Simulation!$D$1:$G$1,0))} -> 840 | H9: {=INDEX(Simulation!$D$2:$G$41,MATCH(1,(Simulation!$C$2:$C$41=$A9)*(Simulation!$A$2:$A$41=H$2+1),0),MATCH($D16,Simulation!$D$1:$G$1,0))} -> 880 | I9: {=INDEX(Simulation!$D$2:$G$41,MATCH(1,(Simulation!$C$2:$C$41=$A9)*(Simulation!$A$2:$A$41=I$2+1),0),MATCH($D16,Simulation!$D$1:$G$1,0))} -> 918 | J9: {=INDEX(Simulation!$D$2:$G$41,MATCH(1,(Simulation!$C$2:$C$41=$A9)*(Simulation!$A$2:$A$41=J$2+1),0),MATCH($D16,Simulation!$D$1:$G$1,0))} -> 960 | K9: {=INDEX(Simulation!$D$2:$G$41,MATCH(1,(Simulation!$C$2:$C$41=$A9)*(Simulation!$A$2:$A$41=K$2+1),0),MATCH($D16,Simulation!$D$1:$G$1,0))} -> 1040 | L9: {=INDEX(Simulation!$D$2:$G$41,MATCH(1,(Simulation!$C$2:$C$41=$A9)*(Simulation!$A$2:$A$41=L$2+1),0),MATCH($D16,Simulation!$D$1:$G$1,0))} -> 1080
A10: ASSET PURCHASE: unit list & quantities by year
C11: Unit Price | D11: Coverage Pct. (Fleet Sizing) | E11: Year 1 | F11: Year 2 | G11: Year 3 | H11: Year 4 | I11: Year 5 | J11: Year 6 | K11: Year 7 | L11: Year 8 | M11: Cumulative Total Units | N11: Total CaPex
A12: Cabins | D12: 0.85 | E12: =E5 -> 80 | F12: =IF(F5>MAX($E$5:E5),F5-MAX($E$5:E5),0) -> 3 | G12: =IF(G5>MAX($E$5:F5),G5-MAX($E$5:F5),0) -> 7 | H12: =IF(H5>MAX($E$5:G5),H5-MAX($E$5:G5),0) -> 7 | I12: =IF(I5>MAX($E$5:H5),I5-MAX($E$5:H5),0) -> 3 | J12: =IF(J5>MAX($E$5:I5),J5-MAX($E$5:I5),0) -> 9 | K12: =IF(K5>MAX($E$5:J5),K5-MAX($E$5:J5),0) -> 11 | L12: =IF(L5>MAX($E$5:K5),L5-MAX($E$5:K5),0) -> 7 | M12: =SUM(E12:L12) -> 127 | N12: =SUM(E18:I18) -> 9971619
A13: Buggies | C13: =Assumptions!B29 -> 40000 | D13: =Assumptions!B11 -> 0.5 | E13: =E6 -> 26 | F13: =IF(F6>MAX($E$6:E6),F6-MAX($E$6:E6),0) -> 2 | G13: =IF(G6>MAX($E$6:F6),G6-MAX($E$6:F6),0) -> 2 | H13: =IF(H6>MAX($E$6:G6),H6-MAX($E$6:G6),0) -> 4 | I13: =IF(I6>MAX($E$6:H6),I6-MAX($E$6:H6),0) -> 0 | J13: =IF(J6>MAX($E$6:I6),J6-MAX($E$6:I6),0) -> 4 | K13: =IF(K6>MAX($E$6:J6),K6-MAX($E$6:J6),0) -> 4 | L13: =IF(L6>MAX($E$6:K6),L6-MAX($E$6:K6),0) -> 4 | M13: =SUM(E13:L13) -> 46 | N13: =SUM(E19:I19) -> 1374625.3
A14: Barriers | C14: =Assumptions!B33 -> 300 | D14: =Assumptions!B12 -> 0.85 | E14: =E7 -> 2300 | F14: =IF(F7>MAX($E$7:E7),F7-MAX($E$7:E7),0) -> 108 | G14: =IF(G7>MAX($E$7:F7),G7-MAX($E$7:F7),0) -> 336 | H14: =IF(H7>MAX($E$7:G7),H7-MAX($E$7:G7),0) -> 206 | I14: =IF(I7>MAX($E$7:H7),I7-MAX($E$7:H7),0) -> 144 | J14: =IF(J7>MAX($E$7:I7),J7-MAX($E$7:I7),0) -> 464 | K14: =IF(K7>MAX($E$7:J7),K7-MAX($E$7:J7),0) -> 392 | L14: =IF(L7>MAX($E$7:K7),L7-MAX($E$7:K7),0) -> 314 | M14: =SUM(E14:L14) -> 4264 | N14: =SUM(E20:I20) -> 940264.04
A15: Fencing | C15: =Assumptions!B34 -> 400 | D15: =Assumptions!B13 -> 0.85 | E15: =E8 -> 2960 | F15: =IF(F8>MAX($E$8:E8),F8-MAX($E$8:E8),0) -> 50 | G15: =IF(G8>MAX($E$8:F8),G8-MAX($E$8:F8),0) -> 220 | H15: =IF(H8>MAX($E$8:G8),H8-MAX($E$8:G8),0) -> 210 | I15: =IF(I8>MAX($E$8:H8),I8-MAX($E$8:H8),0) -> 150 | J15: =IF(J8>MAX($E$8:I8),J8-MAX($E$8:I8),0) -> 290 | K15: =IF(K8>MAX($E$8:J8),K8-MAX($E$8:J8),0) -> 460 | L15: =IF(L8>MAX($E$8:K8),L8-MAX($E$8:K8),0) -> 150 | M15: =SUM(E15:L15) -> 4490 | N15: =SUM(E21:I21) -> 1450042.6
A16: Flooring | C16: =Assumptions!B38 -> 500 | D16: =Assumptions!B14 -> 0.85 | E16: =E9 -> 740 | F16: =IF(F9>MAX($E$9:E9),F9-MAX($E$9:E9),0) -> 0 | G16: =IF(G9>MAX($E$9:F9),G9-MAX($E$9:F9),0) -> 100 | H16: =IF(H9>MAX($E$9:G9),H9-MAX($E$9:G9),0) -> 40 | I16: =IF(I9>MAX($E$9:H9),I9-MAX($E$9:H9),0) -> 38 | J16: =IF(J9>MAX($E$9:I9),J9-MAX($E$9:I9),0) -> 42 | K16: =IF(K9>MAX($E$9:J9),K9-MAX($E$9:J9),0) -> 80 | L16: =IF(L9>MAX($E$9:K9),L9-MAX($E$9:K9),0) -> 40 | M16: =SUM(E16:L16) -> 1080 | N16: =SUM(E22:I22) -> 463810.37
A17: SUMMARY
A18: Cabin CapEx | E18: =E48 -> 6658100 | F18: =F48 -> 764286 | G18: =G48 -> 708928.56 | H18: =H48 -> 884516.87 | I18: =I48 -> 955787.6 | J18: =J48 -> 0 | K18: =K48 -> 0 | L18: =L48 -> 0 | N18: =SUM(E18:I18) -> 9971619
A19: Buggies Yearly CapEx | E19: =E13*$C13*(1+Assumptions!$B$42)^'CapEx & Storage'!E$2 -> 1040000 | F19: =F13*$C13*(1+Assumptions!$B$42)^'CapEx & Storage'!F$2 -> 81600 | G19: =G13*$C13*(1+Assumptions!$B$42)^'CapEx & Storage'!G$2 -> 83232 | H19: =H13*$C13*(1+Assumptions!$B$42)^'CapEx & Storage'!H$2 -> 169793.28 | I19: =I13*$C13*(1+Assumptions!$B$42)^'CapEx & Storage'!I$2 -> 0 | J19: =J13*$C13*(1+Assumptions!$B$42)^'CapEx & Storage'!J$2 -> 176652.93 | K19: =K13*$C13*(1+Assumptions!$B$42)^'CapEx & Storage'!K$2 -> 180185.99 | L19: =L13*$C13*(1+Assumptions!$B$42)^'CapEx & Storage'!L$2 -> 183789.71 | N19: =SUM(E19:I19) -> 1374625.3
A20: Barriers CapEx | E20: =E14*$C14*(1+Assumptions!$B$42)^'CapEx & Storage'!E$2 -> 690000 | F20: =F14*$C14*(1+Assumptions!$B$42)^'CapEx & Storage'!F$2 -> 33048 | G20: =G14*$C14*(1+Assumptions!$B$42)^'CapEx & Storage'!G$2 -> 104872.32 | H20: =H14*$C14*(1+Assumptions!$B$42)^'CapEx & Storage'!H$2 -> 65582.654 | I20: =I14*$C14*(1+Assumptions!$B$42)^'CapEx & Storage'!I$2 -> 46761.069 | J20: =J14*$C14*(1+Assumptions!$B$42)^'CapEx & Storage'!J$2 -> 153688.05 | K20: =K14*$C14*(1+Assumptions!$B$42)^'CapEx & Storage'!K$2 -> 132436.7 | L20: =L14*$C14*(1+Assumptions!$B$42)^'CapEx & Storage'!L$2 -> 108206.19 | N20: =SUM(E20:I20) -> 940264.04
A21: Fencing CapEx | E21: =E15*$C15*(1+Assumptions!$B$42)^'CapEx & Storage'!E$2 -> 1184000 | F21: =F15*$C15*(1+Assumptions!$B$42)^'CapEx & Storage'!F$2 -> 20400 | G21: =G15*$C15*(1+Assumptions!$B$42)^'CapEx & Storage'!G$2 -> 91555.2 | H21: =H15*$C15*(1+Assumptions!$B$42)^'CapEx & Storage'!H$2 -> 89141.472 | I21: =I15*$C15*(1+Assumptions!$B$42)^'CapEx & Storage'!I$2 -> 64945.93 | J21: =J15*$C15*(1+Assumptions!$B$42)^'CapEx & Storage'!J$2 -> 128073.37 | K21: =K15*$C15*(1+Assumptions!$B$42)^'CapEx & Storage'!K$2 -> 207213.89 | L21: =L15*$C15*(1+Assumptions!$B$42)^'CapEx & Storage'!L$2 -> 68921.14 | N21: =SUM(E21:I21) -> 1450042.6
A22: Terratrak CapEx | E22: =E16*$C16*(1+Assumptions!$B$42)^'CapEx & Storage'!E$2 -> 370000 | F22: =F16*$C16*(1+Assumptions!$B$42)^'CapEx & Storage'!F$2 -> 0 | G22: =G16*$C16*(1+Assumptions!$B$42)^'CapEx & Storage'!G$2 -> 52020 | H22: =H16*$C16*(1+Assumptions!$B$42)^'CapEx & Storage'!H$2 -> 21224.16 | I22: =I16*$C16*(1+Assumptions!$B$42)^'CapEx & Storage'!I$2 -> 20566.211 | J22: =J16*$C16*(1+Assumptions!$B$42)^'CapEx & Storage'!J$2 -> 23185.697 | K22: =K16*$C16*(1+Assumptions!$B$42)^'CapEx & Storage'!K$2 -> 45046.497 | L22: =L16*$C16*(1+Assumptions!$B$42)^'CapEx & Storage'!L$2 -> 22973.713 | N22: =SUM(E22:I22) -> 463810.37
N23: =SUM(N18:N22) -> 14200361
A25: CABINS: unit list, quantities by year, and storage footprint
A26: Cabin Type | B26: Description | C26: Unit Price (AED) | D26: Floor Area (sqm) | E26: Year 1 | F26: Year 2 | G26: Year 3 | H26: Year 4 | I26: Year 5 | J26: Year 6 | K26: Year 7 | L26: Year 8 | M26: Cumulative Total Units | N26: Total CapEx
A27: 20 Ft Office | B27: Open Layout (1 Door) | C27: 26500 | D27: 15 | E27: 4 | F27: 1 | H27: 1 | M27: =SUM(E27:L27) -> 6 | N27: =IFERROR(E27*C27,0)+IFERROR(F27*C27*(1+Assumptions!$B$42)^1,0)+IFERROR(G27*C27*(1+Assumptions!$B$42)^2,0)+IFERROR(H27*C27*(1+Assumptions!$B$42)^3,0)+IFERROR(I27*C27*(1+Assumptions!$B$42)^4,0) -> 161152.01
A28: 20 Ft Office | B28: Open Layout (2 Doors) | C28: 28400 | D28: 15 | E28: 3 | F28: 1 | H28: 1 | I28: 1 | M28: =SUM(E28:L28) -> 6 | N28: =IFERROR(E28*C28,0)+IFERROR(F28*C28*(1+Assumptions!$B$42)^1,0)+IFERROR(G28*C28*(1+Assumptions!$B$42)^2,0)+IFERROR(H28*C28*(1+Assumptions!$B$42)^3,0)+IFERROR(I28*C28*(1+Assumptions!$B$42)^4,0) -> 175047.38
A29: 40 Ft Office | B29: Open Layout (2 Windows) | C29: 46200 | D29: 37 | E29: 5 | H29: 1 | I29: 2 | M29: =SUM(E29:L29) -> 8 | N29: =IFERROR(E29*C29,0)+IFERROR(F29*C29*(1+Assumptions!$B$42)^1,0)+IFERROR(G29*C29*(1+Assumptions!$B$42)^2,0)+IFERROR(H29*C29*(1+Assumptions!$B$42)^3,0)+IFERROR(I29*C29*(1+Assumptions!$B$42)^4,0) -> 380044.54
A30: 40 Ft Office | B30: Open Layout (Multi-window) | C30: 49700 | D30: 37 | E30: 6 | G30: 1 | H30: 1 | M30: =SUM(E30:L30) -> 8 | N30: =IFERROR(E30*C30,0)+IFERROR(F30*C30*(1+Assumptions!$B$42)^1,0)+IFERROR(G30*C30*(1+Assumptions!$B$42)^2,0)+IFERROR(H30*C30*(1+Assumptions!$B$42)^3,0)+IFERROR(I30*C30*(1+Assumptions!$B$42)^4,0) -> 402649.92
A31: 40 Ft Split | B31: 2 Offices | C31: 52700 | D31: 37 | E31: 5 | G31: 1 | H31: 1 | I31: 2 | M31: =SUM(E31:L31) -> 9 | N31: =IFERROR(E31*C31,0)+IFERROR(F31*C31*(1+Assumptions!$B$42)^1,0)+IFERROR(G31*C31*(1+Assumptions!$B$42)^2,0)+IFERROR(H31*C31*(1+Assumptions!$B$42)^3,0)+IFERROR(I31*C31*(1+Assumptions!$B$42)^4,0) -> 488343.09
A32: 40 Ft Split | B32: 2 Offices + Toilet + Pantry | C32: 109300 | D32: 37 | E32: 5 | H32: 1 | I32: 1 | M32: =SUM(E32:L32) -> 7 | N32: =IFERROR(E32*C32,0)+IFERROR(F32*C32*(1+Assumptions!$B$42)^1,0)+IFERROR(G32*C32*(1+Assumptions!$B$42)^2,0)+IFERROR(H32*C32*(1+Assumptions!$B$42)^3,0)+IFERROR(I32*C32*(1+Assumptions!$B$42)^4,0) -> 780799.87
A33: 20 Ft Ticketing | B33: Counter + 5 Windows | C33: 28700 | D33: 15 | E33: 4 | G33: 1 | M33: =SUM(E33:L33) -> 5 | N33: =IFERROR(E33*C33,0)+IFERROR(F33*C33*(1+Assumptions!$B$42)^1,0)+IFERROR(G33*C33*(1+Assumptions!$B$42)^2,0)+IFERROR(H33*C33*(1+Assumptions!$B$42)^3,0)+IFERROR(I33*C33*(1+Assumptions!$B$42)^4,0) -> 144659.48
A34: 40 Ft Ticketing | B34: Counter + 9 Windows | C34: 56400 | D34: 49 | E34: 4 | G34: 1 | M34: =SUM(E34:L34) -> 5 | N34: =IFERROR(E34*C34,0)+IFERROR(F34*C34*(1+Assumptions!$B$42)^1,0)+IFERROR(G34*C34*(1+Assumptions!$B$42)^2,0)+IFERROR(H34*C34*(1+Assumptions!$B$42)^3,0)+IFERROR(I34*C34*(1+Assumptions!$B$42)^4,0) -> 284278.56
A35: 40 Ft Toilet (Male) | B35: With Urinals + Baseframe + Stairs + Tanks | C35: 153900 | D35: 49 | E35: 5 | F35: 1 | M35: =SUM(E35:L35) -> 6 | N35: =IFERROR(E35*C35,0)+IFERROR(F35*C35*(1+Assumptions!$B$42)^1,0)+IFERROR(G35*C35*(1+Assumptions!$B$42)^2,0)+IFERROR(H35*C35*(1+Assumptions!$B$42)^3,0)+IFERROR(I35*C35*(1+Assumptions!$B$42)^4,0) -> 926478
A36: 40 Ft Toilet (Female) | B36: Baseframe + Stairs + Tanks | C36: 164100 | D36: 49 | E36: 5 | F36: 1 | M36: =SUM(E36:L36) -> 6 | N36: =IFERROR(E36*C36,0)+IFERROR(F36*C36*(1+Assumptions!$B$42)^1,0)+IFERROR(G36*C36*(1+Assumptions!$B$42)^2,0)+IFERROR(H36*C36*(1+Assumptions!$B$42)^3,0)+IFERROR(I36*C36*(1+Assumptions!$B$42)^4,0) -> 987882
A37: 40 Ft Toilet (Split) | B37: Half Male / Half Female + Baseframe + Stairs + Tanks | C37: 160000 | D37: 49 | E37: 5 | F37: 1 | G37: 2 | M37: =SUM(E37:L37) -> 8 | N37: =IFERROR(E37*C37,0)+IFERROR(F37*C37*(1+Assumptions!$B$42)^1,0)+IFERROR(G37*C37*(1+Assumptions!$B$42)^2,0)+IFERROR(H37*C37*(1+Assumptions!$B$42)^3,0)+IFERROR(I37*C37*(1+Assumptions!$B$42)^4,0) -> 1296128
A38: 20 Ft Toilet (Male) | B38: With Urinals + Baseframe + Stairs + Tanks | C38: 90100 | D38: 24 | E38: 5 | G38: 1 | M38: =SUM(E38:L38) -> 6 | N38: =IFERROR(E38*C38,0)+IFERROR(F38*C38*(1+Assumptions!$B$42)^1,0)+IFERROR(G38*C38*(1+Assumptions!$B$42)^2,0)+IFERROR(H38*C38*(1+Assumptions!$B$42)^3,0)+IFERROR(I38*C38*(1+Assumptions!$B$42)^4,0) -> 544240.04
A39: 20 Ft Toilet (Female) | B39: Baseframe + Stairs + Tanks | C39: 83800 | D39: 18 | E39: 5 | G39: 1 | M39: =SUM(E39:L39) -> 6 | N39: =IFERROR(E39*C39,0)+IFERROR(F39*C39*(1+Assumptions!$B$42)^1,0)+IFERROR(G39*C39*(1+Assumptions!$B$42)^2,0)+IFERROR(H39*C39*(1+Assumptions!$B$42)^3,0)+IFERROR(I39*C39*(1+Assumptions!$B$42)^4,0) -> 506185.52
A40: 20 Ft Shower Unit | B40: With Showers + Baseframe + Stairs + Tanks | C40: 82600 | D40: 18 | E40: 2 | H40: 1 | I40: 1 | M40: =SUM(E40:L40) -> 4 | N40: =IFERROR(E40*C40,0)+IFERROR(F40*C40*(1+Assumptions!$B$42)^1,0)+IFERROR(G40*C40*(1+Assumptions!$B$42)^2,0)+IFERROR(H40*C40*(1+Assumptions!$B$42)^3,0)+IFERROR(I40*C40*(1+Assumptions!$B$42)^4,0) -> 342264.68
A41: 8 Ft POD | B41: POD & Baby Changing | C41: 26800 | D41: 7 | E41: 4 | F41: 1 | I41: 1 | M41: =SUM(E41:L41) -> 6 | N41: =IFERROR(E41*C41,0)+IFERROR(F41*C41*(1+Assumptions!$B$42)^1,0)+IFERROR(G41*C41*(1+Assumptions!$B$42)^2,0)+IFERROR(H41*C41*(1+Assumptions!$B$42)^3,0)+IFERROR(I41*C41*(1+Assumptions!$B$42)^4,0) -> 163545.18
A42: 40 Ft Premium | B42: No Toilet & Pantry | C42: 189600 | D42: 49 | E42: 4 | F42: 1 | H42: 1 | I42: 1 | M42: =SUM(E42:L42) -> 7 | N42: =IFERROR(E42*C42,0)+IFERROR(F42*C42*(1+Assumptions!$B$42)^1,0)+IFERROR(G42*C42*(1+Assumptions!$B$42)^2,0)+IFERROR(H42*C42*(1+Assumptions!$B$42)^3,0)+IFERROR(I42*C42*(1+Assumptions!$B$42)^4,0) -> 1358226.2
A43: 40 Ft Premium | B43: With Toilet & Pantry + Baseframe + Stairs + Tanks | C43: 248500 | D43: 49 | E43: 2 | H43: 1 | I43: 1 | M43: =SUM(E43:L43) -> 4 | N43: =IFERROR(E43*C43,0)+IFERROR(F43*C43*(1+Assumptions!$B$42)^1,0)+IFERROR(G43*C43*(1+Assumptions!$B$42)^2,0)+IFERROR(H43*C43*(1+Assumptions!$B$42)^3,0)+IFERROR(I43*C43*(1+Assumptions!$B$42)^4,0) -> 1029694.6
A44: CABIN SUMMARY
A45: Cumulative fleet | B45: Running total of all units acquired | E45: =SUM(E27:E43) -> 73 | F45: =E45+SUM(F27:F43) -> 80 | G45: =F45+SUM(G27:G43) -> 88 | H45: =G45+SUM(H27:H43) -> 97 | I45: =H45+SUM(I27:I43) -> 107 | J45: =I45+SUM(J27:J43) -> 107 | K45: =J45+SUM(K27:K43) -> 107 | L45: =K45+SUM(L27:L43) -> 107 | M45: =SUM(M27:M43) -> 107 | N45: =SUM(N27:N43) -> 9971619
A46: Cumulative fleet - check | E46: =E5 -> 80 | F46: =E46+F12 -> 83 | G46: =F46+G12 -> 90 | H46: =G46+H12 -> 97 | I46: =H46+I12 -> 100 | J46: =I46+J12 -> 109 | K46: =J46+K12 -> 120 | L46: =K46+L12 -> 127
A47: Units Added | B47: YoY unit growth | E47: =SUM(E27:E43) -> 73 | F47: =SUM(F27:F43) -> 7 | G47: =SUM(G27:G43) -> 8 | H47: =SUM(H27:H43) -> 9 | I47: =SUM(I27:I43) -> 10 | J47: =SUM(J27:J43) -> 0 | K47: =SUM(K27:K43) -> 0 | L47: =SUM(L27:L43) -> 0
A48: Yearly CapEx (AED) | B48: Unit price inflation applied per year | E48: {=SUMPRODUCT($C$27:$C$43*(1+Assumptions!$B$42)^0,E27:E43)} -> 6658100 | F48: {=SUMPRODUCT($C$27:$C$43*(1+Assumptions!$B$42)^1,F27:F43)} -> 764286 | G48: {=SUMPRODUCT($C$27:$C$43*(1+Assumptions!$B$42)^2,G27:G43)} -> 708928.56 | H48: {=SUMPRODUCT($C$27:$C$43*(1+Assumptions!$B$42)^3,H27:H43)} -> 884516.87 | I48: {=SUMPRODUCT($C$27:$C$43*(1+Assumptions!$B$42)^4,I27:I43)} -> 955787.6 | J48: {=SUMPRODUCT($C$27:$C$43*(1+Assumptions!$B$42)^4,J27:J43)} -> 0 | K48: {=SUMPRODUCT($C$27:$C$43*(1+Assumptions!$B$42)^4,K27:K43)} -> 0 | L48: {=SUMPRODUCT($C$27:$C$43*(1+Assumptions!$B$42)^4,L27:L43)} -> 0
A51: COMBINED TOTAL CAPEX | E51: =SUM(E18:E22) -> 9942100 | F51: =SUM(F18:F22) -> 899334 | G51: =SUM(G18:G22) -> 1040608.1 | H51: =SUM(H18:H22) -> 1230258.4 | I51: =SUM(I18:I22) -> 1088060.8 | J51: =SUM(J18:J22) -> 481600.05 | K51: =SUM(K18:K22) -> 564883.07 | L51: =SUM(L18:L22) -> 383890.75 | N51: =SUM(N18:N22) -> 14200361
A52: → CapEx requiring funding | N52: =N51 -> 14200361
A55: STORAGE & YARD COST ANALYSIS
A56: Stacking factor | B56: 1 = no stack | 2 = double-stack | 3 = triple-stack | E56: 2 | F56: =E56 -> 2 | G56: =F56 -> 2 | H56: =G56 -> 2 | I56: =H56 -> 2 | J56: =I56 -> 2 | K56: =J56 -> 2 | L56: =K56 -> 2
A57: Yard rent (AED/sqft per year) | E57: 20 | F57: 20 | G57: 20 | H57: 20 | I57: 20 | J57: 21 | K57: 22 | L57: 23
A58: % Circulation | E58: 0.1 | F58: 0.1 | G58: 0.1 | H58: 0.1 | I58: 0.1 | J58: 1.1 | K58: 2.1 | L58: 3.1
A59: Cabin gross footprint (unstacked) + % Circulation (sqm) | E59: =SUMPRODUCT($D$27:$D$43,E27:E43)*(1+E58) -> 2685.1 | F59: =SUMPRODUCT($D$27:$D$43,F27:F43)*(1+F58)+E59 -> 2941.4 | G59: =SUMPRODUCT($D$27:$D$43,G27:G43)*(1+G58)+F59 -> 3247.2 | H59: =SUMPRODUCT($D$27:$D$43,H27:H43)*(1+H58)+G59 -> 3570.6 | I59: =SUMPRODUCT($D$27:$D$43,I27:I43)*(1+I58)+H59 -> 3925.9 | J59: =SUMPRODUCT($D$27:$D$43,J27:J43)*(1+J58)+I59 -> 3925.9 | K59: =SUMPRODUCT($D$27:$D$43,K27:K43)*(1+K58)+J59 -> 3925.9 | L59: =SUMPRODUCT($D$27:$D$43,L27:L43)*(1+L58)+K59 -> 3925.9
A60: Cabin gross footprint (unstacked) + % Circulation (sqft) | E60: =SUMPRODUCT($D$27:$D$43,E27:E43)*(1+E58)*10.76391 -> 28902.175 | F60: =SUMPRODUCT($D$27:$D$43,F27:F43)*(1+F58)*10.76391+E60 -> 31660.965 | G60: =SUMPRODUCT($D$27:$D$43,G27:G43)*(1+G58)*10.76391+F60 -> 34952.569 | H60: =SUMPRODUCT($D$27:$D$43,H27:H43)*(1+H58)*10.76391+G60 -> 38433.617 | I60: =SUMPRODUCT($D$27:$D$43,I27:I43)*(1+I58)*10.76391+H60 -> 42258.034 | J60: =SUMPRODUCT($D$27:$D$43,J27:J43)*(1+J58)*10.76391+I60 -> 42258.034 | K60: =SUMPRODUCT($D$27:$D$43,K27:K43)*(1+K58)*10.76391+J60 -> 42258.034 | L60: =SUMPRODUCT($D$27:$D$43,L27:L43)*(1+L58)*10.76391+K60 -> 42258.034
A61: Buggie gross footprint (sqft) | B61: Avg. Dim: 3m x 1.6m - 4.8m2 | E61: =SUM($E$6:E6)*4.8*10.76391 -> 1343.336 | F61: =SUM($E$6:F6)*4.8*10.76391 -> 2790.0055 | G61: =SUM($E$6:G6)*4.8*10.76391 -> 4340.0085 | H61: =SUM($E$6:H6)*4.8*10.76391 -> 6096.6786 | I61: =SUM($E$6:I6)*4.8*10.76391 -> 7853.3487 | J61: =SUM($E$6:J6)*4.8*10.76391 -> 9816.6859 | K61: =SUM($E$6:K6)*4.8*10.76391 -> 11986.69 | L61: =SUM($E$6:L6)*4.8*10.76391 -> 14363.362
A62: Effective storage footprint (after stacking) | E62: =E60/E56+E61 -> 15794.423 | F62: =F60/F56+F61 -> 18620.488 | G62: =G60/G56+G61 -> 21816.293 | H62: =H60/H56+H61 -> 25313.487 | I62: =I60/I56+I61 -> 28982.366 | J62: =J60/J56+J61 -> 30945.703 | K62: =K60/K56+K61 -> 33115.707 | L62: =L60/L56+L61 -> 35492.379
A63: Annual storage cost | E63: =E62*E57 -> 315888.47 | F63: =F62*F57 -> 372409.76 | G63: =G62*G57 -> 436325.86 | H63: =H62*H57 -> 506269.74 | I63: =I62*I57 -> 579647.32 | J63: =J62*J57 -> 649859.76 | K63: =K62*K57 -> 728545.56 | L63: =L62*L57 -> 816324.71
A65: Stacking scenario comparison | B65: Area | C65: Price/Year
A66: No stacking (worst case) | B66: =E60 -> 28902.175 | C66: =B66*$E$57 -> 578043.49
A67: Double-stacked (÷2) | B67: =B66/2 -> 14451.087 | C67: =B67*$E$57 -> 289021.75
A68: Triple-stacked (÷3) | B68: =B66/3 -> 9634.0582 | C68: =B68*$E$57 -> 192681.16

Sheet FY1 Event & Demand Timeline
A1: EVENT UTILISATION TIMELINE │ green = Mobilisation, red = Live event, blue = Demobilisation
D2: Year | E2: 2026 | CS2: 2027
D3: Month | E3: Oct | AJ3: Nov | BN3: Dec | CS3: Jan | DX3: Feb | EZ3: Mar | GE3: Apr
D4: Day | E4: 1 | F4: 2 | G4: 3 | H4: 4 | I4: 5 | J4: 6 | K4: 7 | L4: 8 | M4: 9 | N4: 10 | O4: 11 | P4: 12 | Q4: 13 | R4: 14 | S4: 15 | T4: 16 | U4: 17 | V4: 18 | W4: 19 | X4: 20 | Y4: 21 | Z4: 22 | AA4: 23 | AB4: 24 | AC4: 25 | AD4: 26 | AE4: 27 | AF4: 28 | AG4: 29 | AH4: 30 | AI4: 31 | AJ4: 1 | AK4: 2 | AL4: 3 | AM4: 4 | AN4: 5 | AO4: 6 | AP4: 7 | AQ4: 8 | AR4: 9 | AS4: 10 | AT4: 11 | AU4: 12 | AV4: 13 | AW4: 14 | AX4: 15 | AY4: 16 | AZ4: 17 | BA4: 18 | BB4: 19 | BC4: 20 | BD4: 21 | BE4: 22 | BF4: 23 | BG4: 24 | BH4: 25 | BI4: 26 | BJ4: 27 | BK4: 28 | BL4: 29 | BM4: 30 | BN4: 1 | BO4: 2 | BP4: 3 | BQ4: 4 | BR4: 5 | BS4: 6 | BT4: 7 | BU4: 8 | BV4: 9 | BW4: 10 | BX4: 11 | BY4: 12 | BZ4: 13 | CA4: 14 | CB4: 15 | CC4: 16 | CD4: 17 | CE4: 18 | CF4: 19 | CG4: 20 | CH4: 21 | CI4: 22 | CJ4: 23 | CK4: 24 | CL4: 25 | CM4: 26 | CN4: 27 | CO4: 28 | CP4: 29 | CQ4: 30 | CR4: 31 | CS4: 1 | CT4: 2 | CU4: 3 | CV4: 4 | CW4: 5 | CX4: 6 | CY4: 7 | CZ4: 8 | DA4: 9 | DB4: 10 | DC4: 11 | DD4: 12 | DE4: 13 | DF4: 14 | DG4: 15 | DH4: 16 | DI4: 17 | DJ4: 18 | DK4: 19 | DL4: 20 | DM4: 21 | DN4: 22 | DO4: 23 | DP4: 24 | DQ4: 25 | DR4: 26 | DS4: 27 | DT4: 28 | DU4: 29 | DV4: 30 | DW4: 31 | DX4: 1 | DY4: 2 | DZ4: 3 | EA4: 4 | EB4: 5 | EC4: 6 | ED4: 7 | EE4: 8 | EF4: 9 | EG4: 10 | EH4: 11 | EI4: 12 | EJ4: 13 | EK4: 14 | EL4: 15 | EM4: 16 | EN4: 17 | EO4: 18 | EP4: 19 | EQ4: 20 | ER4: 21 | ES4: 22 | ET4: 23 | EU4: 24 | EV4: 25 | EW4: 26 | EX4: 27 | EY4: 28 | EZ4: 1 | FA4: 2 | FB4: 3 | FC4: 4 | FD4: 5 | FE4: 6 | FF4: 7 | FG4: 8 | FH4: 9 | FI4: 10 | FJ4: 11 | FK4: 12 | FL4: 13 | FM4: 14 | FN4: 15 | FO4: 16 | FP4: 17 | FQ4: 18 | FR4: 19 | FS4: 20 | FT4: 21 | FU4: 22 | FV4: 23 | FW4: 24 | FX4: 25 | FY4: 26 | FZ4: 27 | GA4: 28 | GB4: 29 | GC4: 30 | GD4: 31 | GE4: 1 | GF4: 2 | GG4: 3 | GH4: 4 | GI4: 5 | GJ4: 6 | GK4: 7 | GL4: 8 | GM4: 9 | GN4: 10 | GO4: 11 | GP4: 12 | GQ4: 13 | GR4: 14 | GS4: 15 | GT4: 16 | GU4: 17 | GV4: 18 | GW4: 19 | GX4: 20 | GY4: 21 | GZ4: 22 | HA4: 23 | HB4: 24 | HC4: 25 | HD4: 26 | HE4: 27 | HF4: 28 | HG4: 29 | HH4: 30
D5: Date | E5: =DATE(2026,10,1) -> 46296 | F5: =E5+1 -> 46297 | G5: =F5+1 -> 46298 | H5: =G5+1 -> 46299 | I5: =H5+1 -> 46300 | J5: =I5+1 -> 46301 | K5: =J5+1 -> 46302 | L5: =K5+1 -> 46303 | M5: =L5+1 -> 46304 | ... HH5: =HG5+1 -> 46507
A6: CABINS | B6: Start | C6: End | D6: Count
A7: ='FY1 Event Pipeline'!A4 -> Saadiyat Nights | B7: =_xlfn.XLOOKUP(A7,'FY1 Event Pipeline'!$A$4:$A$15,'FY1 Event Pipeline'!$H$4:$H$15) -> 46297 | C7: =_xlfn.XLOOKUP(A7,'FY1 Event Pipeline'!$A$4:$A$15,'FY1 Event Pipeline'!$J$4:$J$15) -> 46453 | D7: =_xlfn.XLOOKUP(A7,'FY1 Event Pipeline'!$A$4:$A$15,'FY1 Event Pipeline'!$N$4:$N$15) -> 10 | E7: =IF(AND(E$5>=$B7,E$5<=$C7),$D7,"") | F7: =IF(AND(F$5>=$B7,F$5<=$C7),$D7,"") -> 10 | G7: =IF(AND(G$5>=$B7,G$5<=$C7),$D7,"") -> 10 | H7: =IF(AND(H$5>=$B7,H$5<=$C7),$D7,"") -> 10 | I7: =IF(AND(I$5>=$B7,I$5<=$C7),$D7,"") -> 10 | J7: =IF(AND(J$5>=$B7,J$5<=$C7),$D7,"") -> 10 | K7: =IF(AND(K$5>=$B7,K$5<=$C7),$D7,"") -> 10 | L7: =IF(AND(L$5>=$B7,L$5<=$C7),$D7,"") -> 10 | ... HH7: =IF(AND(HH$5>=$B7,HH$5<=$C7),$D7,"")
A8: ='FY1 Event Pipeline'!A5 -> BRED X | B8: =_xlfn.XLOOKUP(A8,'FY1 Event Pipeline'!$A$4:$A$15,'FY1 Event Pipeline'!$H$4:$H$15) -> 46318 | C8: =_xlfn.XLOOKUP(A8,'FY1 Event Pipeline'!$A$4:$A$15,'FY1 Event Pipeline'!$J$4:$J$15) -> 46339 | D8: =_xlfn.XLOOKUP(A8,'FY1 Event Pipeline'!$A$4:$A$15,'FY1 Event Pipeline'!$N$4:$N$15) -> 8 | E8: =IF(AND(E$5>=$B8,E$5<=$C8),$D8,"") | F8: =IF(AND(F$5>=$B8,F$5<=$C8),$D8,"") | G8: =IF(AND(G$5>=$B8,G$5<=$C8),$D8,"") | H8: =IF(AND(H$5>=$B8,H$5<=$C8),$D8,"") | I8: =IF(AND(I$5>=$B8,I$5<=$C8),$D8,"") | J8: =IF(AND(J$5>=$B8,J$5<=$C8),$D8,"") | K8: =IF(AND(K$5>=$B8,K$5<=$C8),$D8,"") | L8: =IF(AND(L$5>=$B8,L$5<=$C8),$D8,"") | ... HH8: =IF(AND(HH$5>=$B8,HH$5<=$C8),$D8,"")
A9: ='FY1 Event Pipeline'!A6 -> MOTN DHA | B9: =_xlfn.XLOOKUP(A9,'FY1 Event Pipeline'!$A$4:$A$15,'FY1 Event Pipeline'!$H$4:$H$15) -> 46330 | C9: =_xlfn.XLOOKUP(A9,'FY1 Event Pipeline'!$A$4:$A$15,'FY1 Event Pipeline'!$J$4:$J$15) -> 46352 | D9: =_xlfn.XLOOKUP(A9,'FY1 Event Pipeline'!$A$4:$A$15,'FY1 Event Pipeline'!$N$4:$N$15) -> 8 | E9: =IF(AND(E$5>=$B9,E$5<=$C9),$D9,"") | F9: =IF(AND(F$5>=$B9,F$5<=$C9),$D9,"") | G9: =IF(AND(G$5>=$B9,G$5<=$C9),$D9,"") | H9: =IF(AND(H$5>=$B9,H$5<=$C9),$D9,"") | I9: =IF(AND(I$5>=$B9,I$5<=$C9),$D9,"") | J9: =IF(AND(J$5>=$B9,J$5<=$C9),$D9,"") | K9: =IF(AND(K$5>=$B9,K$5<=$C9),$D9,"") | L9: =IF(AND(L$5>=$B9,L$5<=$C9),$D9,"") | ... HH9: =IF(AND(HH$5>=$B9,HH$5<=$C9),$D9,"")
A10: ='FY1 Event Pipeline'!A7 -> No Art UAE | B10: =_xlfn.XLOOKUP(A10,'FY1 Event Pipeline'!$A$4:$A$15,'FY1 Event Pipeline'!$H$4:$H$15) -> 46332 | C10: =_xlfn.XLOOKUP(A10,'FY1 Event Pipeline'!$A$4:$A$15,'FY1 Event Pipeline'!$J$4:$J$15) -> 46353 | D10: =_xlfn.XLOOKUP(A10,'FY1 Event Pipeline'!$A$4:$A$15,'FY1 Event Pipeline'!$N$4:$N$15) -> 24 | E10: =IF(AND(E$5>=$B10,E$5<=$C10),$D10,"") | F10: =IF(AND(F$5>=$B10,F$5<=$C10),$D10,"") | G10: =IF(AND(G$5>=$B10,G$5<=$C10),$D10,"") | H10: =IF(AND(H$5>=$B10,H$5<=$C10),$D10,"") | I10: =IF(AND(I$5>=$B10,I$5<=$C10),$D10,"") | J10: =IF(AND(J$5>=$B10,J$5<=$C10),$D10,"") | K10: =IF(AND(K$5>=$B10,K$5<=$C10),$D10,"") | L10: =IF(AND(L$5>=$B10,L$5<=$C10),$D10,"") | ... HH10: =IF(AND(HH$5>=$B10,HH$5<=$C10),$D10,"")
A11: ='FY1 Event Pipeline'!A8 -> Tanweer Festival | B11: =_xlfn.XLOOKUP(A11,'FY1 Event Pipeline'!$A$4:$A$15,'FY1 Event Pipeline'!$H$4:$H$15) -> 46340 | C11: =_xlfn.XLOOKUP(A11,'FY1 Event Pipeline'!$A$4:$A$15,'FY1 Event Pipeline'!$J$4:$J$15) -> 46352 | D11: =_xlfn.XLOOKUP(A11,'FY1 Event Pipeline'!$A$4:$A$15,'FY1 Event Pipeline'!$N$4:$N$15) -> 0 | E11: =IF(AND(E$5>=$B11,E$5<=$C11),$D11,"") | F11: =IF(AND(F$5>=$B11,F$5<=$C11),$D11,"") | G11: =IF(AND(G$5>=$B11,G$5<=$C11),$D11,"") | H11: =IF(AND(H$5>=$B11,H$5<=$C11),$D11,"") | I11: =IF(AND(I$5>=$B11,I$5<=$C11),$D11,"") | J11: =IF(AND(J$5>=$B11,J$5<=$C11),$D11,"") | K11: =IF(AND(K$5>=$B11,K$5<=$C11),$D11,"") | L11: =IF(AND(L$5>=$B11,L$5<=$C11),$D11,"") | ... HH11: =IF(AND(HH$5>=$B11,HH$5<=$C11),$D11,"")
A12: ='FY1 Event Pipeline'!A9 -> MOTN AAN | B12: =_xlfn.XLOOKUP(A12,'FY1 Event Pipeline'!$A$4:$A$15,'FY1 Event Pipeline'!$H$4:$H$15) -> 46336 | C12: =_xlfn.XLOOKUP(A12,'FY1 Event Pipeline'!$A$4:$A$15,'FY1 Event Pipeline'!$J$4:$J$15) -> 46362 | D12: =_xlfn.XLOOKUP(A12,'FY1 Event Pipeline'!$A$4:$A$15,'FY1 Event Pipeline'!$N$4:$N$15) -> 18 | E12: =IF(AND(E$5>=$B12,E$5<=$C12),$D12,"") | F12: =IF(AND(F$5>=$B12,F$5<=$C12),$D12,"") | G12: =IF(AND(G$5>=$B12,G$5<=$C12),$D12,"") | H12: =IF(AND(H$5>=$B12,H$5<=$C12),$D12,"") | I12: =IF(AND(I$5>=$B12,I$5<=$C12),$D12,"") | J12: =IF(AND(J$5>=$B12,J$5<=$C12),$D12,"") | K12: =IF(AND(K$5>=$B12,K$5<=$C12),$D12,"") | L12: =IF(AND(L$5>=$B12,L$5<=$C12),$D12,"") | ... HH12: =IF(AND(HH$5>=$B12,HH$5<=$C12),$D12,"")
A13: ='FY1 Event Pipeline'!A10 -> F1 Afterparty | B13: =_xlfn.XLOOKUP(A13,'FY1 Event Pipeline'!$A$4:$A$15,'FY1 Event Pipeline'!$H$4:$H$15) -> 46353 | C13: =_xlfn.XLOOKUP(A13,'FY1 Event Pipeline'!$A$4:$A$15,'FY1 Event Pipeline'!$J$4:$J$15) -> 46365 | D13: =_xlfn.XLOOKUP(A13,'FY1 Event Pipeline'!$A$4:$A$15,'FY1 Event Pipeline'!$N$4:$N$15) -> 29 | E13: =IF(AND(E$5>=$B13,E$5<=$C13),$D13,"") | F13: =IF(AND(F$5>=$B13,F$5<=$C13),$D13,"") | G13: =IF(AND(G$5>=$B13,G$5<=$C13),$D13,"") | H13: =IF(AND(H$5>=$B13,H$5<=$C13),$D13,"") | I13: =IF(AND(I$5>=$B13,I$5<=$C13),$D13,"") | J13: =IF(AND(J$5>=$B13,J$5<=$C13),$D13,"") | K13: =IF(AND(K$5>=$B13,K$5<=$C13),$D13,"") | L13: =IF(AND(L$5>=$B13,L$5<=$C13),$D13,"") | ... HH13: =IF(AND(HH$5>=$B13,HH$5<=$C13),$D13,"")
A14: ='FY1 Event Pipeline'!A11 -> MOTN AUH | B14: =_xlfn.XLOOKUP(A14,'FY1 Event Pipeline'!$A$4:$A$15,'FY1 Event Pipeline'!$H$4:$H$15) -> 46346 | C14: =_xlfn.XLOOKUP(A14,'FY1 Event Pipeline'!$A$4:$A$15,'FY1 Event Pipeline'!$J$4:$J$15) -> 46398 | D14: =_xlfn.XLOOKUP(A14,'FY1 Event Pipeline'!$A$4:$A$15,'FY1 Event Pipeline'!$N$4:$N$15) -> 20 | E14: =IF(AND(E$5>=$B14,E$5<=$C14),$D14,"") | F14: =IF(AND(F$5>=$B14,F$5<=$C14),$D14,"") | G14: =IF(AND(G$5>=$B14,G$5<=$C14),$D14,"") | H14: =IF(AND(H$5>=$B14,H$5<=$C14),$D14,"") | I14: =IF(AND(I$5>=$B14,I$5<=$C14),$D14,"") | J14: =IF(AND(J$5>=$B14,J$5<=$C14),$D14,"") | K14: =IF(AND(K$5>=$B14,K$5<=$C14),$D14,"") | L14: =IF(AND(L$5>=$B14,L$5<=$C14),$D14,"") | ... HH14: =IF(AND(HH$5>=$B14,HH$5<=$C14),$D14,"")
A15: ='FY1 Event Pipeline'!A12 -> Yas Winterfest | B15: =_xlfn.XLOOKUP(A15,'FY1 Event Pipeline'!$A$4:$A$15,'FY1 Event Pipeline'!$H$4:$H$15) -> 46352 | C15: =_xlfn.XLOOKUP(A15,'FY1 Event Pipeline'!$A$4:$A$15,'FY1 Event Pipeline'!$J$4:$J$15) -> 46384 | D15: =_xlfn.XLOOKUP(A15,'FY1 Event Pipeline'!$A$4:$A$15,'FY1 Event Pipeline'!$N$4:$N$15) -> 6 | E15: =IF(AND(E$5>=$B15,E$5<=$C15),$D15,"") | F15: =IF(AND(F$5>=$B15,F$5<=$C15),$D15,"") | G15: =IF(AND(G$5>=$B15,G$5<=$C15),$D15,"") | H15: =IF(AND(H$5>=$B15,H$5<=$C15),$D15,"") | I15: =IF(AND(I$5>=$B15,I$5<=$C15),$D15,"") | J15: =IF(AND(J$5>=$B15,J$5<=$C15),$D15,"") | K15: =IF(AND(K$5>=$B15,K$5<=$C15),$D15,"") | L15: =IF(AND(L$5>=$B15,L$5<=$C15),$D15,"") | ... HH15: =IF(AND(HH$5>=$B15,HH$5<=$C15),$D15,"")
A16: ='FY1 Event Pipeline'!A13 -> Animenia | B16: =_xlfn.XLOOKUP(A16,'FY1 Event Pipeline'!$A$4:$A$15,'FY1 Event Pipeline'!$H$4:$H$15) -> 46414 | C16: =_xlfn.XLOOKUP(A16,'FY1 Event Pipeline'!$A$4:$A$15,'FY1 Event Pipeline'!$J$4:$J$15) -> 46436 | D16: =_xlfn.XLOOKUP(A16,'FY1 Event Pipeline'!$A$4:$A$15,'FY1 Event Pipeline'!$N$4:$N$15) -> 8 | E16: =IF(AND(E$5>=$B16,E$5<=$C16),$D16,"") | F16: =IF(AND(F$5>=$B16,F$5<=$C16),$D16,"") | G16: =IF(AND(G$5>=$B16,G$5<=$C16),$D16,"") | H16: =IF(AND(H$5>=$B16,H$5<=$C16),$D16,"") | I16: =IF(AND(I$5>=$B16,I$5<=$C16),$D16,"") | J16: =IF(AND(J$5>=$B16,J$5<=$C16),$D16,"") | K16: =IF(AND(K$5>=$B16,K$5<=$C16),$D16,"") | L16: =IF(AND(L$5>=$B16,L$5<=$C16),$D16,"") | ... HH16: =IF(AND(HH$5>=$B16,HH$5<=$C16),$D16,"")
A17: ='FY1 Event Pipeline'!A14 -> DAZ | B17: =_xlfn.XLOOKUP(A17,'FY1 Event Pipeline'!$A$4:$A$15,'FY1 Event Pipeline'!$H$4:$H$15) -> 46466 | C17: =_xlfn.XLOOKUP(A17,'FY1 Event Pipeline'!$A$4:$A$15,'FY1 Event Pipeline'!$J$4:$J$15) -> 46496 | D17: =_xlfn.XLOOKUP(A17,'FY1 Event Pipeline'!$A$4:$A$15,'FY1 Event Pipeline'!$N$4:$N$15) -> 15 | E17: =IF(AND(E$5>=$B17,E$5<=$C17),$D17,"") | F17: =IF(AND(F$5>=$B17,F$5<=$C17),$D17,"") | G17: =IF(AND(G$5>=$B17,G$5<=$C17),$D17,"") | H17: =IF(AND(H$5>=$B17,H$5<=$C17),$D17,"") | I17: =IF(AND(I$5>=$B17,I$5<=$C17),$D17,"") | J17: =IF(AND(J$5>=$B17,J$5<=$C17),$D17,"") | K17: =IF(AND(K$5>=$B17,K$5<=$C17),$D17,"") | L17: =IF(AND(L$5>=$B17,L$5<=$C17),$D17,"") | ... HH17: =IF(AND(HH$5>=$B17,HH$5<=$C17),$D17,"")
A18: ='FY1 Event Pipeline'!A15 -> BRED | B18: =_xlfn.XLOOKUP(A18,'FY1 Event Pipeline'!$A$4:$A$15,'FY1 Event Pipeline'!$H$4:$H$15) -> 46492 | C18: =_xlfn.XLOOKUP(A18,'FY1 Event Pipeline'!$A$4:$A$15,'FY1 Event Pipeline'!$J$4:$J$15) -> 46506 | D18: =_xlfn.XLOOKUP(A18,'FY1 Event Pipeline'!$A$4:$A$15,'FY1 Event Pipeline'!$N$4:$N$15) -> 22 | E18: =IF(AND(E$5>=$B18,E$5<=$C18),$D18,"") | F18: =IF(AND(F$5>=$B18,F$5<=$C18),$D18,"") | G18: =IF(AND(G$5>=$B18,G$5<=$C18),$D18,"") | H18: =IF(AND(H$5>=$B18,H$5<=$C18),$D18,"") | I18: =IF(AND(I$5>=$B18,I$5<=$C18),$D18,"") | J18: =IF(AND(J$5>=$B18,J$5<=$C18),$D18,"") | K18: =IF(AND(K$5>=$B18,K$5<=$C18),$D18,"") | L18: =IF(AND(L$5>=$B18,L$5<=$C18),$D18,"") | ... HH18: =IF(AND(HH$5>=$B18,HH$5<=$C18),$D18,"")
A19: MAX CABINS ON-HIRE | D19: =MAX(F19:HH19) -> 107 | E19: =SUM(E7:E18) -> 0 | F19: =SUM(F7:F18) -> 10 | G19: =SUM(G7:G18) -> 10 | H19: =SUM(H7:H18) -> 10 | I19: =SUM(I7:I18) -> 10 | J19: =SUM(J7:J18) -> 10 | K19: =SUM(K7:K18) -> 10 | L19: =SUM(L7:L18) -> 10 | ... HH19: =SUM(HH7:HH18) -> 0
A20: BUGGIES
A21: ='FY1 Event Pipeline'!A4 -> Saadiyat Nights | B21: =_xlfn.XLOOKUP(A21,'FY1 Event Pipeline'!$A$4:$A$15,'FY1 Event Pipeline'!$H$4:$H$15) -> 46297 | C21: =_xlfn.XLOOKUP(A21,'FY1 Event Pipeline'!$A$4:$A$15,'FY1 Event Pipeline'!$J$4:$J$15) -> 46453 | D21: =_xlfn.XLOOKUP(A21,'FY1 Event Pipeline'!$A$4:$A$15,'FY1 Event Pipeline'!$O$4:$O$15) -> 10 | E21: =IF(AND(E$5>=$B21,E$5<=$C21),$D21,"") | F21: =IF(AND(F$5>=$B21,F$5<=$C21),$D21,"") -> 10 | G21: =IF(AND(G$5>=$B21,G$5<=$C21),$D21,"") -> 10 | H21: =IF(AND(H$5>=$B21,H$5<=$C21),$D21,"") -> 10 | I21: =IF(AND(I$5>=$B21,I$5<=$C21),$D21,"") -> 10 | J21: =IF(AND(J$5>=$B21,J$5<=$C21),$D21,"") -> 10 | K21: =IF(AND(K$5>=$B21,K$5<=$C21),$D21,"") -> 10 | L21: =IF(AND(L$5>=$B21,L$5<=$C21),$D21,"") -> 10 | ... HH21: =IF(AND(HH$5>=$B21,HH$5<=$C21),$D21,"")
A22: ='FY1 Event Pipeline'!A5 -> BRED X | B22: =_xlfn.XLOOKUP(A22,'FY1 Event Pipeline'!$A$4:$A$15,'FY1 Event Pipeline'!$H$4:$H$15) -> 46318 | C22: =_xlfn.XLOOKUP(A22,'FY1 Event Pipeline'!$A$4:$A$15,'FY1 Event Pipeline'!$J$4:$J$15) -> 46339 | D22: =_xlfn.XLOOKUP(A22,'FY1 Event Pipeline'!$A$4:$A$15,'FY1 Event Pipeline'!$O$4:$O$15) -> 0 | E22: =IF(AND(E$5>=$B22,E$5<=$C22),$D22,"") | F22: =IF(AND(F$5>=$B22,F$5<=$C22),$D22,"") | G22: =IF(AND(G$5>=$B22,G$5<=$C22),$D22,"") | H22: =IF(AND(H$5>=$B22,H$5<=$C22),$D22,"") | I22: =IF(AND(I$5>=$B22,I$5<=$C22),$D22,"") | J22: =IF(AND(J$5>=$B22,J$5<=$C22),$D22,"") | K22: =IF(AND(K$5>=$B22,K$5<=$C22),$D22,"") | L22: =IF(AND(L$5>=$B22,L$5<=$C22),$D22,"") | ... HH22: =IF(AND(HH$5>=$B22,HH$5<=$C22),$D22,"")
A23: ='FY1 Event Pipeline'!A6 -> MOTN DHA | B23: =_xlfn.XLOOKUP(A23,'FY1 Event Pipeline'!$A$4:$A$15,'FY1 Event Pipeline'!$H$4:$H$15) -> 46330 | C23: =_xlfn.XLOOKUP(A23,'FY1 Event Pipeline'!$A$4:$A$15,'FY1 Event Pipeline'!$J$4:$J$15) -> 46352 | D23: =_xlfn.XLOOKUP(A23,'FY1 Event Pipeline'!$A$4:$A$15,'FY1 Event Pipeline'!$O$4:$O$15) -> 6 | E23: =IF(AND(E$5>=$B23,E$5<=$C23),$D23,"") | F23: =IF(AND(F$5>=$B23,F$5<=$C23),$D23,"") | G23: =IF(AND(G$5>=$B23,G$5<=$C23),$D23,"") | H23: =IF(AND(H$5>=$B23,H$5<=$C23),$D23,"") | I23: =IF(AND(I$5>=$B23,I$5<=$C23),$D23,"") | J23: =IF(AND(J$5>=$B23,J$5<=$C23),$D23,"") | K23: =IF(AND(K$5>=$B23,K$5<=$C23),$D23,"") | L23: =IF(AND(L$5>=$B23,L$5<=$C23),$D23,"") | ... HH23: =IF(AND(HH$5>=$B23,HH$5<=$C23),$D23,"")
A24: ='FY1 Event Pipeline'!A7 -> No Art UAE | B24: =_xlfn.XLOOKUP(A24,'FY1 Event Pipeline'!$A$4:$A$15,'FY1 Event Pipeline'!$H$4:$H$15) -> 46332 | C24: =_xlfn.XLOOKUP(A24,'FY1 Event Pipeline'!$A$4:$A$15,'FY1 Event Pipeline'!$J$4:$J$15) -> 46353 | D24: =_xlfn.XLOOKUP(A24,'FY1 Event Pipeline'!$A$4:$A$15,'FY1 Event Pipeline'!$O$4:$O$15) -> 6 | E24: =IF(AND(E$5>=$B24,E$5<=$C24),$D24,"") | F24: =IF(AND(F$5>=$B24,F$5<=$C24),$D24,"") | G24: =IF(AND(G$5>=$B24,G$5<=$C24),$D24,"") | H24: =IF(AND(H$5>=$B24,H$5<=$C24),$D24,"") | I24: =IF(AND(I$5>=$B24,I$5<=$C24),$D24,"") | J24: =IF(AND(J$5>=$B24,J$5<=$C24),$D24,"") | K24: =IF(AND(K$5>=$B24,K$5<=$C24),$D24,"") | L24: =IF(AND(L$5>=$B24,L$5<=$C24),$D24,"") | ... HH24: =IF(AND(HH$5>=$B24,HH$5<=$C24),$D24,"")
A25: ='FY1 Event Pipeline'!A8 -> Tanweer Festival | B25: =_xlfn.XLOOKUP(A25,'FY1 Event Pipeline'!$A$4:$A$15,'FY1 Event Pipeline'!$H$4:$H$15) -> 46340 | C25: =_xlfn.XLOOKUP(A25,'FY1 Event Pipeline'!$A$4:$A$15,'FY1 Event Pipeline'!$J$4:$J$15) -> 46352 | D25: =_xlfn.XLOOKUP(A25,'FY1 Event Pipeline'!$A$4:$A$15,'FY1 Event Pipeline'!$O$4:$O$15) -> 8 | E25: =IF(AND(E$5>=$B25,E$5<=$C25),$D25,"") | F25: =IF(AND(F$5>=$B25,F$5<=$C25),$D25,"") | G25: =IF(AND(G$5>=$B25,G$5<=$C25),$D25,"") | H25: =IF(AND(H$5>=$B25,H$5<=$C25),$D25,"") | I25: =IF(AND(I$5>=$B25,I$5<=$C25),$D25,"") | J25: =IF(AND(J$5>=$B25,J$5<=$C25),$D25,"") | K25: =IF(AND(K$5>=$B25,K$5<=$C25),$D25,"") | L25: =IF(AND(L$5>=$B25,L$5<=$C25),$D25,"") | ... HH25: =IF(AND(HH$5>=$B25,HH$5<=$C25),$D25,"")
A26: ='FY1 Event Pipeline'!A9 -> MOTN AAN | B26: =_xlfn.XLOOKUP(A26,'FY1 Event Pipeline'!$A$4:$A$15,'FY1 Event Pipeline'!$H$4:$H$15) -> 46336 | C26: =_xlfn.XLOOKUP(A26,'FY1 Event Pipeline'!$A$4:$A$15,'FY1 Event Pipeline'!$J$4:$J$15) -> 46362 | D26: =_xlfn.XLOOKUP(A26,'FY1 Event Pipeline'!$A$4:$A$15,'FY1 Event Pipeline'!$O$4:$O$15) -> 6 | E26: =IF(AND(E$5>=$B26,E$5<=$C26),$D26,"") | F26: =IF(AND(F$5>=$B26,F$5<=$C26),$D26,"") | G26: =IF(AND(G$5>=$B26,G$5<=$C26),$D26,"") | H26: =IF(AND(H$5>=$B26,H$5<=$C26),$D26,"") | I26: =IF(AND(I$5>=$B26,I$5<=$C26),$D26,"") | J26: =IF(AND(J$5>=$B26,J$5<=$C26),$D26,"") | K26: =IF(AND(K$5>=$B26,K$5<=$C26),$D26,"") | L26: =IF(AND(L$5>=$B26,L$5<=$C26),$D26,"") | ... HH26: =IF(AND(HH$5>=$B26,HH$5<=$C26),$D26,"")
A27: ='FY1 Event Pipeline'!A10 -> F1 Afterparty | B27: =_xlfn.XLOOKUP(A27,'FY1 Event Pipeline'!$A$4:$A$15,'FY1 Event Pipeline'!$H$4:$H$15) -> 46353 | C27: =_xlfn.XLOOKUP(A27,'FY1 Event Pipeline'!$A$4:$A$15,'FY1 Event Pipeline'!$J$4:$J$15) -> 46365 | D27: =_xlfn.XLOOKUP(A27,'FY1 Event Pipeline'!$A$4:$A$15,'FY1 Event Pipeline'!$O$4:$O$15) -> 8 | E27: =IF(AND(E$5>=$B27,E$5<=$C27),$D27,"") | F27: =IF(AND(F$5>=$B27,F$5<=$C27),$D27,"") | G27: =IF(AND(G$5>=$B27,G$5<=$C27),$D27,"") | H27: =IF(AND(H$5>=$B27,H$5<=$C27),$D27,"") | I27: =IF(AND(I$5>=$B27,I$5<=$C27),$D27,"") | J27: =IF(AND(J$5>=$B27,J$5<=$C27),$D27,"") | K27: =IF(AND(K$5>=$B27,K$5<=$C27),$D27,"") | L27: =IF(AND(L$5>=$B27,L$5<=$C27),$D27,"") | ... HH27: =IF(AND(HH$5>=$B27,HH$5<=$C27),$D27,"")
A28: ='FY1 Event Pipeline'!A11 -> MOTN AUH | B28: =_xlfn.XLOOKUP(A28,'FY1 Event Pipeline'!$A$4:$A$15,'FY1 Event Pipeline'!$H$4:$H$15) -> 46346 | C28: =_xlfn.XLOOKUP(A28,'FY1 Event Pipeline'!$A$4:$A$15,'FY1 Event Pipeline'!$J$4:$J$15) -> 46398 | D28: =_xlfn.XLOOKUP(A28,'FY1 Event Pipeline'!$A$4:$A$15,'FY1 Event Pipeline'!$O$4:$O$15) -> 10 | E28: =IF(AND(E$5>=$B28,E$5<=$C28),$D28,"") | F28: =IF(AND(F$5>=$B28,F$5<=$C28),$D28,"") | G28: =IF(AND(G$5>=$B28,G$5<=$C28),$D28,"") | H28: =IF(AND(H$5>=$B28,H$5<=$C28),$D28,"") | I28: =IF(AND(I$5>=$B28,I$5<=$C28),$D28,"") | J28: =IF(AND(J$5>=$B28,J$5<=$C28),$D28,"") | K28: =IF(AND(K$5>=$B28,K$5<=$C28),$D28,"") | L28: =IF(AND(L$5>=$B28,L$5<=$C28),$D28,"") | ... HH28: =IF(AND(HH$5>=$B28,HH$5<=$C28),$D28,"")
A29: ='FY1 Event Pipeline'!A12 -> Yas Winterfest | B29: =_xlfn.XLOOKUP(A29,'FY1 Event Pipeline'!$A$4:$A$15,'FY1 Event Pipeline'!$H$4:$H$15) -> 46352 | C29: =_xlfn.XLOOKUP(A29,'FY1 Event Pipeline'!$A$4:$A$15,'FY1 Event Pipeline'!$J$4:$J$15) -> 46384 | D29: =_xlfn.XLOOKUP(A29,'FY1 Event Pipeline'!$A$4:$A$15,'FY1 Event Pipeline'!$O$4:$O$15) -> 4 | E29: =IF(AND(E$5>=$B29,E$5<=$C29),$D29,"") | F29: =IF(AND(F$5>=$B29,F$5<=$C29),$D29,"") | G29: =IF(AND(G$5>=$B29,G$5<=$C29),$D29,"") | H29: =IF(AND(H$5>=$B29,H$5<=$C29),$D29,"") | I29: =IF(AND(I$5>=$B29,I$5<=$C29),$D29,"") | J29: =IF(AND(J$5>=$B29,J$5<=$C29),$D29,"") | K29: =IF(AND(K$5>=$B29,K$5<=$C29),$D29,"") | L29: =IF(AND(L$5>=$B29,L$5<=$C29),$D29,"") | ... HH29: =IF(AND(HH$5>=$B29,HH$5<=$C29),$D29,"")
A30: ='FY1 Event Pipeline'!A13 -> Animenia | B30: =_xlfn.XLOOKUP(A30,'FY1 Event Pipeline'!$A$4:$A$15,'FY1 Event Pipeline'!$H$4:$H$15) -> 46414 | C30: =_xlfn.XLOOKUP(A30,'FY1 Event Pipeline'!$A$4:$A$15,'FY1 Event Pipeline'!$J$4:$J$15) -> 46436 | D30: =_xlfn.XLOOKUP(A30,'FY1 Event Pipeline'!$A$4:$A$15,'FY1 Event Pipeline'!$O$4:$O$15) -> 4 | E30: =IF(AND(E$5>=$B30,E$5<=$C30),$D30,"") | F30: =IF(AND(F$5>=$B30,F$5<=$C30),$D30,"") | G30: =IF(AND(G$5>=$B30,G$5<=$C30),$D30,"") | H30: =IF(AND(H$5>=$B30,H$5<=$C30),$D30,"") | I30: =IF(AND(I$5>=$B30,I$5<=$C30),$D30,"") | J30: =IF(AND(J$5>=$B30,J$5<=$C30),$D30,"") | K30: =IF(AND(K$5>=$B30,K$5<=$C30),$D30,"") | L30: =IF(AND(L$5>=$B30,L$5<=$C30),$D30,"") | ... HH30: =IF(AND(HH$5>=$B30,HH$5<=$C30),$D30,"")
A31: ='FY1 Event Pipeline'!A14 -> DAZ | B31: =_xlfn.XLOOKUP(A31,'FY1 Event Pipeline'!$A$4:$A$15,'FY1 Event Pipeline'!$H$4:$H$15) -> 46466 | C31: =_xlfn.XLOOKUP(A31,'FY1 Event Pipeline'!$A$4:$A$15,'FY1 Event Pipeline'!$J$4:$J$15) -> 46496 | D31: =_xlfn.XLOOKUP(A31,'FY1 Event Pipeline'!$A$4:$A$15,'FY1 Event Pipeline'!$O$4:$O$15) -> 4 | E31: =IF(AND(E$5>=$B31,E$5<=$C31),$D31,"") | F31: =IF(AND(F$5>=$B31,F$5<=$C31),$D31,"") | G31: =IF(AND(G$5>=$B31,G$5<=$C31),$D31,"") | H31: =IF(AND(H$5>=$B31,H$5<=$C31),$D31,"") | I31: =IF(AND(I$5>=$B31,I$5<=$C31),$D31,"") | J31: =IF(AND(J$5>=$B31,J$5<=$C31),$D31,"") | K31: =IF(AND(K$5>=$B31,K$5<=$C31),$D31,"") | L31: =IF(AND(L$5>=$B31,L$5<=$C31),$D31,"") | ... HH31: =IF(AND(HH$5>=$B31,HH$5<=$C31),$D31,"")
A32: ='FY1 Event Pipeline'!A15 -> BRED | B32: =_xlfn.XLOOKUP(A32,'FY1 Event Pipeline'!$A$4:$A$15,'FY1 Event Pipeline'!$H$4:$H$15) -> 46492 | C32: =_xlfn.XLOOKUP(A32,'FY1 Event Pipeline'!$A$4:$A$15,'FY1 Event Pipeline'!$J$4:$J$15) -> 46506 | D32: =_xlfn.XLOOKUP(A32,'FY1 Event Pipeline'!$A$4:$A$15,'FY1 Event Pipeline'!$O$4:$O$15) -> 6 | E32: =IF(AND(E$5>=$B32,E$5<=$C32),$D32,"") | F32: =IF(AND(F$5>=$B32,F$5<=$C32),$D32,"") | G32: =IF(AND(G$5>=$B32,G$5<=$C32),$D32,"") | H32: =IF(AND(H$5>=$B32,H$5<=$C32),$D32,"") | I32: =IF(AND(I$5>=$B32,I$5<=$C32),$D32,"") | J32: =IF(AND(J$5>=$B32,J$5<=$C32),$D32,"") | K32: =IF(AND(K$5>=$B32,K$5<=$C32),$D32,"") | L32: =IF(AND(L$5>=$B32,L$5<=$C32),$D32,"") | ... HH32: =IF(AND(HH$5>=$B32,HH$5<=$C32),$D32,"")
A33: MAX BUGGIES ON-HIRE | D33: =MAX(F33:HH33) -> 50 | E33: =SUM(E21:E32) -> 0 | F33: =SUM(F21:F32) -> 10 | G33: =SUM(G21:G32) -> 10 | H33: =SUM(H21:H32) -> 10 | I33: =SUM(I21:I32) -> 10 | J33: =SUM(J21:J32) -> 10 | K33: =SUM(K21:K32) -> 10 | L33: =SUM(L21:L32) -> 10 | ... HH33: =SUM(HH21:HH32) -> 0
A34: BARRIERS
A35: ='FY1 Event Pipeline'!A4 -> Saadiyat Nights | B35: =_xlfn.XLOOKUP(A35,'FY1 Event Pipeline'!$A$4:$A$15,'FY1 Event Pipeline'!$H$4:$H$15) -> 46297 | C35: =_xlfn.XLOOKUP(A35,'FY1 Event Pipeline'!$A$4:$A$15,'FY1 Event Pipeline'!$J$4:$J$15) -> 46453 | D35: =_xlfn.XLOOKUP(A35,'FY1 Event Pipeline'!$A$4:$A$15,'FY1 Event Pipeline'!$P$4:$P$15) -> 0 | E35: =IF(AND(E$5>=$B35,E$5<=$C35),$D35,"") | F35: =IF(AND(F$5>=$B35,F$5<=$C35),$D35,"") -> 0 | G35: =IF(AND(G$5>=$B35,G$5<=$C35),$D35,"") -> 0 | H35: =IF(AND(H$5>=$B35,H$5<=$C35),$D35,"") -> 0 | I35: =IF(AND(I$5>=$B35,I$5<=$C35),$D35,"") -> 0 | J35: =IF(AND(J$5>=$B35,J$5<=$C35),$D35,"") -> 0 | K35: =IF(AND(K$5>=$B35,K$5<=$C35),$D35,"") -> 0 | L35: =IF(AND(L$5>=$B35,L$5<=$C35),$D35,"") -> 0 | ... HH35: =IF(AND(HH$5>=$B35,HH$5<=$C35),$D35,"")
A36: ='FY1 Event Pipeline'!A5 -> BRED X | B36: =_xlfn.XLOOKUP(A36,'FY1 Event Pipeline'!$A$4:$A$15,'FY1 Event Pipeline'!$H$4:$H$15) -> 46318 | C36: =_xlfn.XLOOKUP(A36,'FY1 Event Pipeline'!$A$4:$A$15,'FY1 Event Pipeline'!$J$4:$J$15) -> 46339 | D36: =_xlfn.XLOOKUP(A36,'FY1 Event Pipeline'!$A$4:$A$15,'FY1 Event Pipeline'!$P$4:$P$15) -> 0 | E36: =IF(AND(E$5>=$B36,E$5<=$C36),$D36,"") | F36: =IF(AND(F$5>=$B36,F$5<=$C36),$D36,"") | G36: =IF(AND(G$5>=$B36,G$5<=$C36),$D36,"") | H36: =IF(AND(H$5>=$B36,H$5<=$C36),$D36,"") | I36: =IF(AND(I$5>=$B36,I$5<=$C36),$D36,"") | J36: =IF(AND(J$5>=$B36,J$5<=$C36),$D36,"") | K36: =IF(AND(K$5>=$B36,K$5<=$C36),$D36,"") | L36: =IF(AND(L$5>=$B36,L$5<=$C36),$D36,"") | ... HH36: =IF(AND(HH$5>=$B36,HH$5<=$C36),$D36,"")
A37: ='FY1 Event Pipeline'!A6 -> MOTN DHA | B37: =_xlfn.XLOOKUP(A37,'FY1 Event Pipeline'!$A$4:$A$15,'FY1 Event Pipeline'!$H$4:$H$15) -> 46330 | C37: =_xlfn.XLOOKUP(A37,'FY1 Event Pipeline'!$A$4:$A$15,'FY1 Event Pipeline'!$J$4:$J$15) -> 46352 | D37: =_xlfn.XLOOKUP(A37,'FY1 Event Pipeline'!$A$4:$A$15,'FY1 Event Pipeline'!$P$4:$P$15) -> 350 | E37: =IF(AND(E$5>=$B37,E$5<=$C37),$D37,"") | F37: =IF(AND(F$5>=$B37,F$5<=$C37),$D37,"") | G37: =IF(AND(G$5>=$B37,G$5<=$C37),$D37,"") | H37: =IF(AND(H$5>=$B37,H$5<=$C37),$D37,"") | I37: =IF(AND(I$5>=$B37,I$5<=$C37),$D37,"") | J37: =IF(AND(J$5>=$B37,J$5<=$C37),$D37,"") | K37: =IF(AND(K$5>=$B37,K$5<=$C37),$D37,"") | L37: =IF(AND(L$5>=$B37,L$5<=$C37),$D37,"") | ... HH37: =IF(AND(HH$5>=$B37,HH$5<=$C37),$D37,"")
A38: ='FY1 Event Pipeline'!A7 -> No Art UAE | B38: =_xlfn.XLOOKUP(A38,'FY1 Event Pipeline'!$A$4:$A$15,'FY1 Event Pipeline'!$H$4:$H$15) -> 46332 | C38: =_xlfn.XLOOKUP(A38,'FY1 Event Pipeline'!$A$4:$A$15,'FY1 Event Pipeline'!$J$4:$J$15) -> 46353 | D38: =_xlfn.XLOOKUP(A38,'FY1 Event Pipeline'!$A$4:$A$15,'FY1 Event Pipeline'!$P$4:$P$15) -> 0 | E38: =IF(AND(E$5>=$B38,E$5<=$C38),$D38,"") | F38: =IF(AND(F$5>=$B38,F$5<=$C38),$D38,"") | G38: =IF(AND(G$5>=$B38,G$5<=$C38),$D38,"") | H38: =IF(AND(H$5>=$B38,H$5<=$C38),$D38,"") | I38: =IF(AND(I$5>=$B38,I$5<=$C38),$D38,"") | J38: =IF(AND(J$5>=$B38,J$5<=$C38),$D38,"") | K38: =IF(AND(K$5>=$B38,K$5<=$C38),$D38,"") | L38: =IF(AND(L$5>=$B38,L$5<=$C38),$D38,"") | ... HH38: =IF(AND(HH$5>=$B38,HH$5<=$C38),$D38,"")
A39: ='FY1 Event Pipeline'!A8 -> Tanweer Festival | B39: =_xlfn.XLOOKUP(A39,'FY1 Event Pipeline'!$A$4:$A$15,'FY1 Event Pipeline'!$H$4:$H$15) -> 46340 | C39: =_xlfn.XLOOKUP(A39,'FY1 Event Pipeline'!$A$4:$A$15,'FY1 Event Pipeline'!$J$4:$J$15) -> 46352 | D39: =_xlfn.XLOOKUP(A39,'FY1 Event Pipeline'!$A$4:$A$15,'FY1 Event Pipeline'!$P$4:$P$15) -> 900 | E39: =IF(AND(E$5>=$B39,E$5<=$C39),$D39,"") | F39: =IF(AND(F$5>=$B39,F$5<=$C39),$D39,"") | G39: =IF(AND(G$5>=$B39,G$5<=$C39),$D39,"") | H39: =IF(AND(H$5>=$B39,H$5<=$C39),$D39,"") | I39: =IF(AND(I$5>=$B39,I$5<=$C39),$D39,"") | J39: =IF(AND(J$5>=$B39,J$5<=$C39),$D39,"") | K39: =IF(AND(K$5>=$B39,K$5<=$C39),$D39,"") | L39: =IF(AND(L$5>=$B39,L$5<=$C39),$D39,"") | ... HH39: =IF(AND(HH$5>=$B39,HH$5<=$C39),$D39,"")
A40: ='FY1 Event Pipeline'!A9 -> MOTN AAN | B40: =_xlfn.XLOOKUP(A40,'FY1 Event Pipeline'!$A$4:$A$15,'FY1 Event Pipeline'!$H$4:$H$15) -> 46336 | C40: =_xlfn.XLOOKUP(A40,'FY1 Event Pipeline'!$A$4:$A$15,'FY1 Event Pipeline'!$J$4:$J$15) -> 46362 | D40: =_xlfn.XLOOKUP(A40,'FY1 Event Pipeline'!$A$4:$A$15,'FY1 Event Pipeline'!$P$4:$P$15) -> 350 | E40: =IF(AND(E$5>=$B40,E$5<=$C40),$D40,"") | F40: =IF(AND(F$5>=$B40,F$5<=$C40),$D40,"") | G40: =IF(AND(G$5>=$B40,G$5<=$C40),$D40,"") | H40: =IF(AND(H$5>=$B40,H$5<=$C40),$D40,"") | I40: =IF(AND(I$5>=$B40,I$5<=$C40),$D40,"") | J40: =IF(AND(J$5>=$B40,J$5<=$C40),$D40,"") | K40: =IF(AND(K$5>=$B40,K$5<=$C40),$D40,"") | L40: =IF(AND(L$5>=$B40,L$5<=$C40),$D40,"") | ... HH40: =IF(AND(HH$5>=$B40,HH$5<=$C40),$D40,"")
A41: ='FY1 Event Pipeline'!A10 -> F1 Afterparty | B41: =_xlfn.XLOOKUP(A41,'FY1 Event Pipeline'!$A$4:$A$15,'FY1 Event Pipeline'!$H$4:$H$15) -> 46353 | C41: =_xlfn.XLOOKUP(A41,'FY1 Event Pipeline'!$A$4:$A$15,'FY1 Event Pipeline'!$J$4:$J$15) -> 46365 | D41: =_xlfn.XLOOKUP(A41,'FY1 Event Pipeline'!$A$4:$A$15,'FY1 Event Pipeline'!$P$4:$P$15) -> 714 | E41: =IF(AND(E$5>=$B41,E$5<=$C41),$D41,"") | F41: =IF(AND(F$5>=$B41,F$5<=$C41),$D41,"") | G41: =IF(AND(G$5>=$B41,G$5<=$C41),$D41,"") | H41: =IF(AND(H$5>=$B41,H$5<=$C41),$D41,"") | I41: =IF(AND(I$5>=$B41,I$5<=$C41),$D41,"") | J41: =IF(AND(J$5>=$B41,J$5<=$C41),$D41,"") | K41: =IF(AND(K$5>=$B41,K$5<=$C41),$D41,"") | L41: =IF(AND(L$5>=$B41,L$5<=$C41),$D41,"") | ... HH41: =IF(AND(HH$5>=$B41,HH$5<=$C41),$D41,"")
A42: ='FY1 Event Pipeline'!A11 -> MOTN AUH | B42: =_xlfn.XLOOKUP(A42,'FY1 Event Pipeline'!$A$4:$A$15,'FY1 Event Pipeline'!$H$4:$H$15) -> 46346 | C42: =_xlfn.XLOOKUP(A42,'FY1 Event Pipeline'!$A$4:$A$15,'FY1 Event Pipeline'!$J$4:$J$15) -> 46398 | D42: =_xlfn.XLOOKUP(A42,'FY1 Event Pipeline'!$A$4:$A$15,'FY1 Event Pipeline'!$P$4:$P$15) -> 700 | E42: =IF(AND(E$5>=$B42,E$5<=$C42),$D42,"") | F42: =IF(AND(F$5>=$B42,F$5<=$C42),$D42,"") | G42: =IF(AND(G$5>=$B42,G$5<=$C42),$D42,"") | H42: =IF(AND(H$5>=$B42,H$5<=$C42),$D42,"") | I42: =IF(AND(I$5>=$B42,I$5<=$C42),$D42,"") | J42: =IF(AND(J$5>=$B42,J$5<=$C42),$D42,"") | K42: =IF(AND(K$5>=$B42,K$5<=$C42),$D42,"") | L42: =IF(AND(L$5>=$B42,L$5<=$C42),$D42,"") | ... HH42: =IF(AND(HH$5>=$B42,HH$5<=$C42),$D42,"")
A43: ='FY1 Event Pipeline'!A12 -> Yas Winterfest | B43: =_xlfn.XLOOKUP(A43,'FY1 Event Pipeline'!$A$4:$A$15,'FY1 Event Pipeline'!$H$4:$H$15) -> 46352 | C43: =_xlfn.XLOOKUP(A43,'FY1 Event Pipeline'!$A$4:$A$15,'FY1 Event Pipeline'!$J$4:$J$15) -> 46384 | D43: =_xlfn.XLOOKUP(A43,'FY1 Event Pipeline'!$A$4:$A$15,'FY1 Event Pipeline'!$P$4:$P$15) -> 644 | E43: =IF(AND(E$5>=$B43,E$5<=$C43),$D43,"") | F43: =IF(AND(F$5>=$B43,F$5<=$C43),$D43,"") | G43: =IF(AND(G$5>=$B43,G$5<=$C43),$D43,"") | H43: =IF(AND(H$5>=$B43,H$5<=$C43),$D43,"") | I43: =IF(AND(I$5>=$B43,I$5<=$C43),$D43,"") | J43: =IF(AND(J$5>=$B43,J$5<=$C43),$D43,"") | K43: =IF(AND(K$5>=$B43,K$5<=$C43),$D43,"") | L43: =IF(AND(L$5>=$B43,L$5<=$C43),$D43,"") | ... HH43: =IF(AND(HH$5>=$B43,HH$5<=$C43),$D43,"")
A44: ='FY1 Event Pipeline'!A13 -> Animenia | B44: =_xlfn.XLOOKUP(A44,'FY1 Event Pipeline'!$A$4:$A$15,'FY1 Event Pipeline'!$H$4:$H$15) -> 46414 | C44: =_xlfn.XLOOKUP(A44,'FY1 Event Pipeline'!$A$4:$A$15,'FY1 Event Pipeline'!$J$4:$J$15) -> 46436 | D44: =_xlfn.XLOOKUP(A44,'FY1 Event Pipeline'!$A$4:$A$15,'FY1 Event Pipeline'!$P$4:$P$15) -> 288 | E44: =IF(AND(E$5>=$B44,E$5<=$C44),$D44,"") | F44: =IF(AND(F$5>=$B44,F$5<=$C44),$D44,"") | G44: =IF(AND(G$5>=$B44,G$5<=$C44),$D44,"") | H44: =IF(AND(H$5>=$B44,H$5<=$C44),$D44,"") | I44: =IF(AND(I$5>=$B44,I$5<=$C44),$D44,"") | J44: =IF(AND(J$5>=$B44,J$5<=$C44),$D44,"") | K44: =IF(AND(K$5>=$B44,K$5<=$C44),$D44,"") | L44: =IF(AND(L$5>=$B44,L$5<=$C44),$D44,"") | ... HH44: =IF(AND(HH$5>=$B44,HH$5<=$C44),$D44,"")
A45: ='FY1 Event Pipeline'!A14 -> DAZ | B45: =_xlfn.XLOOKUP(A45,'FY1 Event Pipeline'!$A$4:$A$15,'FY1 Event Pipeline'!$H$4:$H$15) -> 46466 | C45: =_xlfn.XLOOKUP(A45,'FY1 Event Pipeline'!$A$4:$A$15,'FY1 Event Pipeline'!$J$4:$J$15) -> 46496 | D45: =_xlfn.XLOOKUP(A45,'FY1 Event Pipeline'!$A$4:$A$15,'FY1 Event Pipeline'!$P$4:$P$15) -> 775 | E45: =IF(AND(E$5>=$B45,E$5<=$C45),$D45,"") | F45: =IF(AND(F$5>=$B45,F$5<=$C45),$D45,"") | G45: =IF(AND(G$5>=$B45,G$5<=$C45),$D45,"") | H45: =IF(AND(H$5>=$B45,H$5<=$C45),$D45,"") | I45: =IF(AND(I$5>=$B45,I$5<=$C45),$D45,"") | J45: =IF(AND(J$5>=$B45,J$5<=$C45),$D45,"") | K45: =IF(AND(K$5>=$B45,K$5<=$C45),$D45,"") | L45: =IF(AND(L$5>=$B45,L$5<=$C45),$D45,"") | ... HH45: =IF(AND(HH$5>=$B45,HH$5<=$C45),$D45,"")
A46: ='FY1 Event Pipeline'!A15 -> BRED | B46: =_xlfn.XLOOKUP(A46,'FY1 Event Pipeline'!$A$4:$A$15,'FY1 Event Pipeline'!$H$4:$H$15) -> 46492 | C46: =_xlfn.XLOOKUP(A46,'FY1 Event Pipeline'!$A$4:$A$15,'FY1 Event Pipeline'!$J$4:$J$15) -> 46506 | D46: =_xlfn.XLOOKUP(A46,'FY1 Event Pipeline'!$A$4:$A$15,'FY1 Event Pipeline'!$P$4:$P$15) -> 1500 | E46: =IF(AND(E$5>=$B46,E$5<=$C46),$D46,"") | F46: =IF(AND(F$5>=$B46,F$5<=$C46),$D46,"") | G46: =IF(AND(G$5>=$B46,G$5<=$C46),$D46,"") | H46: =IF(AND(H$5>=$B46,H$5<=$C46),$D46,"") | I46: =IF(AND(I$5>=$B46,I$5<=$C46),$D46,"") | J46: =IF(AND(J$5>=$B46,J$5<=$C46),$D46,"") | K46: =IF(AND(K$5>=$B46,K$5<=$C46),$D46,"") | L46: =IF(AND(L$5>=$B46,L$5<=$C46),$D46,"") | ... HH46: =IF(AND(HH$5>=$B46,HH$5<=$C46),$D46,"")
A47: MAX BARRIERS ON-HIRE | D47: =MAX(F47:HH47) -> 2944 | E47: =SUM(E35:E46) -> 0 | F47: =SUM(F35:F46) -> 0 | G47: =SUM(G35:G46) -> 0 | H47: =SUM(H35:H46) -> 0 | I47: =SUM(I35:I46) -> 0 | J47: =SUM(J35:J46) -> 0 | K47: =SUM(K35:K46) -> 0 | L47: =SUM(L35:L46) -> 0 | ... HH47: =SUM(HH35:HH46) -> 0
A48: FENCING
A49: ='FY1 Event Pipeline'!A4 -> Saadiyat Nights | B49: =_xlfn.XLOOKUP(A49,'FY1 Event Pipeline'!$A$4:$A$15,'FY1 Event Pipeline'!$H$4:$H$15) -> 46297 | C49: =_xlfn.XLOOKUP(A49,'FY1 Event Pipeline'!$A$4:$A$15,'FY1 Event Pipeline'!$J$4:$J$15) -> 46453 | D49: =_xlfn.XLOOKUP(A49,'FY1 Event Pipeline'!$A$4:$A$15,'FY1 Event Pipeline'!$Q$4:$Q$15) -> 0 | E49: =IF(AND(E$5>=$B49,E$5<=$C49),$D49,"") | F49: =IF(AND(F$5>=$B49,F$5<=$C49),$D49,"") -> 0 | G49: =IF(AND(G$5>=$B49,G$5<=$C49),$D49,"") -> 0 | H49: =IF(AND(H$5>=$B49,H$5<=$C49),$D49,"") -> 0 | I49: =IF(AND(I$5>=$B49,I$5<=$C49),$D49,"") -> 0 | J49: =IF(AND(J$5>=$B49,J$5<=$C49),$D49,"") -> 0 | K49: =IF(AND(K$5>=$B49,K$5<=$C49),$D49,"") -> 0 | L49: =IF(AND(L$5>=$B49,L$5<=$C49),$D49,"") -> 0 | ... HH49: =IF(AND(HH$5>=$B49,HH$5<=$C49),$D49,"")
A50: ='FY1 Event Pipeline'!A5 -> BRED X | B50: =_xlfn.XLOOKUP(A50,'FY1 Event Pipeline'!$A$4:$A$15,'FY1 Event Pipeline'!$H$4:$H$15) -> 46318 | C50: =_xlfn.XLOOKUP(A50,'FY1 Event Pipeline'!$A$4:$A$15,'FY1 Event Pipeline'!$J$4:$J$15) -> 46339 | D50: =_xlfn.XLOOKUP(A50,'FY1 Event Pipeline'!$A$4:$A$15,'FY1 Event Pipeline'!$Q$4:$Q$15) -> 0 | E50: =IF(AND(E$5>=$B50,E$5<=$C50),$D50,"") | F50: =IF(AND(F$5>=$B50,F$5<=$C50),$D50,"") | G50: =IF(AND(G$5>=$B50,G$5<=$C50),$D50,"") | H50: =IF(AND(H$5>=$B50,H$5<=$C50),$D50,"") | I50: =IF(AND(I$5>=$B50,I$5<=$C50),$D50,"") | J50: =IF(AND(J$5>=$B50,J$5<=$C50),$D50,"") | K50: =IF(AND(K$5>=$B50,K$5<=$C50),$D50,"") | L50: =IF(AND(L$5>=$B50,L$5<=$C50),$D50,"") | ... HH50: =IF(AND(HH$5>=$B50,HH$5<=$C50),$D50,"")
A51: ='FY1 Event Pipeline'!A6 -> MOTN DHA | B51: =_xlfn.XLOOKUP(A51,'FY1 Event Pipeline'!$A$4:$A$15,'FY1 Event Pipeline'!$H$4:$H$15) -> 46330 | C51: =_xlfn.XLOOKUP(A51,'FY1 Event Pipeline'!$A$4:$A$15,'FY1 Event Pipeline'!$J$4:$J$15) -> 46352 | D51: =_xlfn.XLOOKUP(A51,'FY1 Event Pipeline'!$A$4:$A$15,'FY1 Event Pipeline'!$Q$4:$Q$15) -> 550 | E51: =IF(AND(E$5>=$B51,E$5<=$C51),$D51,"") | F51: =IF(AND(F$5>=$B51,F$5<=$C51),$D51,"") | G51: =IF(AND(G$5>=$B51,G$5<=$C51),$D51,"") | H51: =IF(AND(H$5>=$B51,H$5<=$C51),$D51,"") | I51: =IF(AND(I$5>=$B51,I$5<=$C51),$D51,"") | J51: =IF(AND(J$5>=$B51,J$5<=$C51),$D51,"") | K51: =IF(AND(K$5>=$B51,K$5<=$C51),$D51,"") | L51: =IF(AND(L$5>=$B51,L$5<=$C51),$D51,"") | ... HH51: =IF(AND(HH$5>=$B51,HH$5<=$C51),$D51,"")
A52: ='FY1 Event Pipeline'!A7 -> No Art UAE | B52: =_xlfn.XLOOKUP(A52,'FY1 Event Pipeline'!$A$4:$A$15,'FY1 Event Pipeline'!$H$4:$H$15) -> 46332 | C52: =_xlfn.XLOOKUP(A52,'FY1 Event Pipeline'!$A$4:$A$15,'FY1 Event Pipeline'!$J$4:$J$15) -> 46353 | D52: =_xlfn.XLOOKUP(A52,'FY1 Event Pipeline'!$A$4:$A$15,'FY1 Event Pipeline'!$Q$4:$Q$15) -> 0 | E52: =IF(AND(E$5>=$B52,E$5<=$C52),$D52,"") | F52: =IF(AND(F$5>=$B52,F$5<=$C52),$D52,"") | G52: =IF(AND(G$5>=$B52,G$5<=$C52),$D52,"") | H52: =IF(AND(H$5>=$B52,H$5<=$C52),$D52,"") | I52: =IF(AND(I$5>=$B52,I$5<=$C52),$D52,"") | J52: =IF(AND(J$5>=$B52,J$5<=$C52),$D52,"") | K52: =IF(AND(K$5>=$B52,K$5<=$C52),$D52,"") | L52: =IF(AND(L$5>=$B52,L$5<=$C52),$D52,"") | ... HH52: =IF(AND(HH$5>=$B52,HH$5<=$C52),$D52,"")
A53: ='FY1 Event Pipeline'!A8 -> Tanweer Festival | B53: =_xlfn.XLOOKUP(A53,'FY1 Event Pipeline'!$A$4:$A$15,'FY1 Event Pipeline'!$H$4:$H$15) -> 46340 | C53: =_xlfn.XLOOKUP(A53,'FY1 Event Pipeline'!$A$4:$A$15,'FY1 Event Pipeline'!$J$4:$J$15) -> 46352 | D53: =_xlfn.XLOOKUP(A53,'FY1 Event Pipeline'!$A$4:$A$15,'FY1 Event Pipeline'!$Q$4:$Q$15) -> 50 | E53: =IF(AND(E$5>=$B53,E$5<=$C53),$D53,"") | F53: =IF(AND(F$5>=$B53,F$5<=$C53),$D53,"") | G53: =IF(AND(G$5>=$B53,G$5<=$C53),$D53,"") | H53: =IF(AND(H$5>=$B53,H$5<=$C53),$D53,"") | I53: =IF(AND(I$5>=$B53,I$5<=$C53),$D53,"") | J53: =IF(AND(J$5>=$B53,J$5<=$C53),$D53,"") | K53: =IF(AND(K$5>=$B53,K$5<=$C53),$D53,"") | L53: =IF(AND(L$5>=$B53,L$5<=$C53),$D53,"") | ... HH53: =IF(AND(HH$5>=$B53,HH$5<=$C53),$D53,"")
A54: ='FY1 Event Pipeline'!A9 -> MOTN AAN | B54: =_xlfn.XLOOKUP(A54,'FY1 Event Pipeline'!$A$4:$A$15,'FY1 Event Pipeline'!$H$4:$H$15) -> 46336 | C54: =_xlfn.XLOOKUP(A54,'FY1 Event Pipeline'!$A$4:$A$15,'FY1 Event Pipeline'!$J$4:$J$15) -> 46362 | D54: =_xlfn.XLOOKUP(A54,'FY1 Event Pipeline'!$A$4:$A$15,'FY1 Event Pipeline'!$Q$4:$Q$15) -> 550 | E54: =IF(AND(E$5>=$B54,E$5<=$C54),$D54,"") | F54: =IF(AND(F$5>=$B54,F$5<=$C54),$D54,"") | G54: =IF(AND(G$5>=$B54,G$5<=$C54),$D54,"") | H54: =IF(AND(H$5>=$B54,H$5<=$C54),$D54,"") | I54: =IF(AND(I$5>=$B54,I$5<=$C54),$D54,"") | J54: =IF(AND(J$5>=$B54,J$5<=$C54),$D54,"") | K54: =IF(AND(K$5>=$B54,K$5<=$C54),$D54,"") | L54: =IF(AND(L$5>=$B54,L$5<=$C54),$D54,"") | ... HH54: =IF(AND(HH$5>=$B54,HH$5<=$C54),$D54,"")
A55: ='FY1 Event Pipeline'!A10 -> F1 Afterparty | B55: =_xlfn.XLOOKUP(A55,'FY1 Event Pipeline'!$A$4:$A$15,'FY1 Event Pipeline'!$H$4:$H$15) -> 46353 | C55: =_xlfn.XLOOKUP(A55,'FY1 Event Pipeline'!$A$4:$A$15,'FY1 Event Pipeline'!$J$4:$J$15) -> 46365 | D55: =_xlfn.XLOOKUP(A55,'FY1 Event Pipeline'!$A$4:$A$15,'FY1 Event Pipeline'!$Q$4:$Q$15) -> 1180 | E55: =IF(AND(E$5>=$B55,E$5<=$C55),$D55,"") | F55: =IF(AND(F$5>=$B55,F$5<=$C55),$D55,"") | G55: =IF(AND(G$5>=$B55,G$5<=$C55),$D55,"") | H55: =IF(AND(H$5>=$B55,H$5<=$C55),$D55,"") | I55: =IF(AND(I$5>=$B55,I$5<=$C55),$D55,"") | J55: =IF(AND(J$5>=$B55,J$5<=$C55),$D55,"") | K55: =IF(AND(K$5>=$B55,K$5<=$C55),$D55,"") | L55: =IF(AND(L$5>=$B55,L$5<=$C55),$D55,"") | ... HH55: =IF(AND(HH$5>=$B55,HH$5<=$C55),$D55,"")
A56: ='FY1 Event Pipeline'!A11 -> MOTN AUH | B56: =_xlfn.XLOOKUP(A56,'FY1 Event Pipeline'!$A$4:$A$15,'FY1 Event Pipeline'!$H$4:$H$15) -> 46346 | C56: =_xlfn.XLOOKUP(A56,'FY1 Event Pipeline'!$A$4:$A$15,'FY1 Event Pipeline'!$J$4:$J$15) -> 46398 | D56: =_xlfn.XLOOKUP(A56,'FY1 Event Pipeline'!$A$4:$A$15,'FY1 Event Pipeline'!$Q$4:$Q$15) -> 1100 | E56: =IF(AND(E$5>=$B56,E$5<=$C56),$D56,"") | F56: =IF(AND(F$5>=$B56,F$5<=$C56),$D56,"") | G56: =IF(AND(G$5>=$B56,G$5<=$C56),$D56,"") | H56: =IF(AND(H$5>=$B56,H$5<=$C56),$D56,"") | I56: =IF(AND(I$5>=$B56,I$5<=$C56),$D56,"") | J56: =IF(AND(J$5>=$B56,J$5<=$C56),$D56,"") | K56: =IF(AND(K$5>=$B56,K$5<=$C56),$D56,"") | L56: =IF(AND(L$5>=$B56,L$5<=$C56),$D56,"") | ... HH56: =IF(AND(HH$5>=$B56,HH$5<=$C56),$D56,"")
A57: ='FY1 Event Pipeline'!A12 -> Yas Winterfest | B57: =_xlfn.XLOOKUP(A57,'FY1 Event Pipeline'!$A$4:$A$15,'FY1 Event Pipeline'!$H$4:$H$15) -> 46352 | C57: =_xlfn.XLOOKUP(A57,'FY1 Event Pipeline'!$A$4:$A$15,'FY1 Event Pipeline'!$J$4:$J$15) -> 46384 | D57: =_xlfn.XLOOKUP(A57,'FY1 Event Pipeline'!$A$4:$A$15,'FY1 Event Pipeline'!$Q$4:$Q$15) -> 760 | E57: =IF(AND(E$5>=$B57,E$5<=$C57),$D57,"") | F57: =IF(AND(F$5>=$B57,F$5<=$C57),$D57,"") | G57: =IF(AND(G$5>=$B57,G$5<=$C57),$D57,"") | H57: =IF(AND(H$5>=$B57,H$5<=$C57),$D57,"") | I57: =IF(AND(I$5>=$B57,I$5<=$C57),$D57,"") | J57: =IF(AND(J$5>=$B57,J$5<=$C57),$D57,"") | K57: =IF(AND(K$5>=$B57,K$5<=$C57),$D57,"") | L57: =IF(AND(L$5>=$B57,L$5<=$C57),$D57,"") | ... HH57: =IF(AND(HH$5>=$B57,HH$5<=$C57),$D57,"")
A58: ='FY1 Event Pipeline'!A13 -> Animenia | B58: =_xlfn.XLOOKUP(A58,'FY1 Event Pipeline'!$A$4:$A$15,'FY1 Event Pipeline'!$H$4:$H$15) -> 46414 | C58: =_xlfn.XLOOKUP(A58,'FY1 Event Pipeline'!$A$4:$A$15,'FY1 Event Pipeline'!$J$4:$J$15) -> 46436 | D58: =_xlfn.XLOOKUP(A58,'FY1 Event Pipeline'!$A$4:$A$15,'FY1 Event Pipeline'!$Q$4:$Q$15) -> 192 | E58: =IF(AND(E$5>=$B58,E$5<=$C58),$D58,"") | F58: =IF(AND(F$5>=$B58,F$5<=$C58),$D58,"") | G58: =IF(AND(G$5>=$B58,G$5<=$C58),$D58,"") | H58: =IF(AND(H$5>=$B58,H$5<=$C58),$D58,"") | I58: =IF(AND(I$5>=$B58,I$5<=$C58),$D58,"") | J58: =IF(AND(J$5>=$B58,J$5<=$C58),$D58,"") | K58: =IF(AND(K$5>=$B58,K$5<=$C58),$D58,"") | L58: =IF(AND(L$5>=$B58,L$5<=$C58),$D58,"") | ... HH58: =IF(AND(HH$5>=$B58,HH$5<=$C58),$D58,"")
A59: ='FY1 Event Pipeline'!A14 -> DAZ | B59: =_xlfn.XLOOKUP(A59,'FY1 Event Pipeline'!$A$4:$A$15,'FY1 Event Pipeline'!$H$4:$H$15) -> 46466 | C59: =_xlfn.XLOOKUP(A59,'FY1 Event Pipeline'!$A$4:$A$15,'FY1 Event Pipeline'!$J$4:$J$15) -> 46496 | D59: =_xlfn.XLOOKUP(A59,'FY1 Event Pipeline'!$A$4:$A$15,'FY1 Event Pipeline'!$Q$4:$Q$15) -> 225 | E59: =IF(AND(E$5>=$B59,E$5<=$C59),$D59,"") | F59: =IF(AND(F$5>=$B59,F$5<=$C59),$D59,"") | G59: =IF(AND(G$5>=$B59,G$5<=$C59),$D59,"") | H59: =IF(AND(H$5>=$B59,H$5<=$C59),$D59,"") | I59: =IF(AND(I$5>=$B59,I$5<=$C59),$D59,"") | J59: =IF(AND(J$5>=$B59,J$5<=$C59),$D59,"") | K59: =IF(AND(K$5>=$B59,K$5<=$C59),$D59,"") | L59: =IF(AND(L$5>=$B59,L$5<=$C59),$D59,"") | ... HH59: =IF(AND(HH$5>=$B59,HH$5<=$C59),$D59,"")
A60: ='FY1 Event Pipeline'!A15 -> BRED | B60: =_xlfn.XLOOKUP(A60,'FY1 Event Pipeline'!$A$4:$A$15,'FY1 Event Pipeline'!$H$4:$H$15) -> 46492 | C60: =_xlfn.XLOOKUP(A60,'FY1 Event Pipeline'!$A$4:$A$15,'FY1 Event Pipeline'!$J$4:$J$15) -> 46506 | D60: =_xlfn.XLOOKUP(A60,'FY1 Event Pipeline'!$A$4:$A$15,'FY1 Event Pipeline'!$Q$4:$Q$15) -> 500 | E60: =IF(AND(E$5>=$B60,E$5<=$C60),$D60,"") | F60: =IF(AND(F$5>=$B60,F$5<=$C60),$D60,"") | G60: =IF(AND(G$5>=$B60,G$5<=$C60),$D60,"") | H60: =IF(AND(H$5>=$B60,H$5<=$C60),$D60,"") | I60: =IF(AND(I$5>=$B60,I$5<=$C60),$D60,"") | J60: =IF(AND(J$5>=$B60,J$5<=$C60),$D60,"") | K60: =IF(AND(K$5>=$B60,K$5<=$C60),$D60,"") | L60: =IF(AND(L$5>=$B60,L$5<=$C60),$D60,"") | ... HH60: =IF(AND(HH$5>=$B60,HH$5<=$C60),$D60,"")
A61: MAX FENCING ON-HIRE | D61: =MAX(E61:HH61) -> 3590 | E61: =SUM(E49:E60) -> 0 | F61: =SUM(F49:F60) -> 0 | G61: =SUM(G49:G60) -> 0 | H61: =SUM(H49:H60) -> 0 | I61: =SUM(I49:I60) -> 0 | J61: =SUM(J49:J60) -> 0 | K61: =SUM(K49:K60) -> 0 | L61: =SUM(L49:L60) -> 0 | ... HH61: =SUM(HH49:HH60) -> 0
A62: TERRATRAK
A63: ='FY1 Event Pipeline'!A4 -> Saadiyat Nights | B63: =_xlfn.XLOOKUP(A63,'FY1 Event Pipeline'!$A$4:$A$15,'FY1 Event Pipeline'!$H$4:$H$15) -> 46297 | C63: =_xlfn.XLOOKUP(A63,'FY1 Event Pipeline'!$A$4:$A$15,'FY1 Event Pipeline'!$J$4:$J$15) -> 46453 | D63: =_xlfn.XLOOKUP(A63,'FY1 Event Pipeline'!$A$4:$A$15,'FY1 Event Pipeline'!$R$4:$R$15) -> 280 | E63: =IF(AND(E$5>=$B63,E$5<=$C63),$D63,"") | F63: =IF(AND(F$5>=$B63,F$5<=$C63),$D63,"") -> 280 | G63: =IF(AND(G$5>=$B63,G$5<=$C63),$D63,"") -> 280 | H63: =IF(AND(H$5>=$B63,H$5<=$C63),$D63,"") -> 280 | I63: =IF(AND(I$5>=$B63,I$5<=$C63),$D63,"") -> 280 | J63: =IF(AND(J$5>=$B63,J$5<=$C63),$D63,"") -> 280 | K63: =IF(AND(K$5>=$B63,K$5<=$C63),$D63,"") -> 280 | L63: =IF(AND(L$5>=$B63,L$5<=$C63),$D63,"") -> 280 | ... HH63: =IF(AND(HH$5>=$B63,HH$5<=$C63),$D63,"")
A64: ='FY1 Event Pipeline'!A5 -> BRED X | B64: =_xlfn.XLOOKUP(A64,'FY1 Event Pipeline'!$A$4:$A$15,'FY1 Event Pipeline'!$H$4:$H$15) -> 46318 | C64: =_xlfn.XLOOKUP(A64,'FY1 Event Pipeline'!$A$4:$A$15,'FY1 Event Pipeline'!$J$4:$J$15) -> 46339 | D64: =_xlfn.XLOOKUP(A64,'FY1 Event Pipeline'!$A$4:$A$15,'FY1 Event Pipeline'!$R$4:$R$15) -> 0 | E64: =IF(AND(E$5>=$B64,E$5<=$C64),$D64,"") | F64: =IF(AND(F$5>=$B64,F$5<=$C64),$D64,"") | G64: =IF(AND(G$5>=$B64,G$5<=$C64),$D64,"") | H64: =IF(AND(H$5>=$B64,H$5<=$C64),$D64,"") | I64: =IF(AND(I$5>=$B64,I$5<=$C64),$D64,"") | J64: =IF(AND(J$5>=$B64,J$5<=$C64),$D64,"") | K64: =IF(AND(K$5>=$B64,K$5<=$C64),$D64,"") | L64: =IF(AND(L$5>=$B64,L$5<=$C64),$D64,"") | ... HH64: =IF(AND(HH$5>=$B64,HH$5<=$C64),$D64,"")
A65: ='FY1 Event Pipeline'!A6 -> MOTN DHA | B65: =_xlfn.XLOOKUP(A65,'FY1 Event Pipeline'!$A$4:$A$15,'FY1 Event Pipeline'!$H$4:$H$15) -> 46330 | C65: =_xlfn.XLOOKUP(A65,'FY1 Event Pipeline'!$A$4:$A$15,'FY1 Event Pipeline'!$J$4:$J$15) -> 46352 | D65: =_xlfn.XLOOKUP(A65,'FY1 Event Pipeline'!$A$4:$A$15,'FY1 Event Pipeline'!$R$4:$R$15) -> 0 | E65: =IF(AND(E$5>=$B65,E$5<=$C65),$D65,"") | F65: =IF(AND(F$5>=$B65,F$5<=$C65),$D65,"") | G65: =IF(AND(G$5>=$B65,G$5<=$C65),$D65,"") | H65: =IF(AND(H$5>=$B65,H$5<=$C65),$D65,"") | I65: =IF(AND(I$5>=$B65,I$5<=$C65),$D65,"") | J65: =IF(AND(J$5>=$B65,J$5<=$C65),$D65,"") | K65: =IF(AND(K$5>=$B65,K$5<=$C65),$D65,"") | L65: =IF(AND(L$5>=$B65,L$5<=$C65),$D65,"") | ... HH65: =IF(AND(HH$5>=$B65,HH$5<=$C65),$D65,"")
A66: ='FY1 Event Pipeline'!A7 -> No Art UAE | B66: =_xlfn.XLOOKUP(A66,'FY1 Event Pipeline'!$A$4:$A$15,'FY1 Event Pipeline'!$H$4:$H$15) -> 46332 | C66: =_xlfn.XLOOKUP(A66,'FY1 Event Pipeline'!$A$4:$A$15,'FY1 Event Pipeline'!$J$4:$J$15) -> 46353 | D66: =_xlfn.XLOOKUP(A66,'FY1 Event Pipeline'!$A$4:$A$15,'FY1 Event Pipeline'!$R$4:$R$15) -> 200 | E66: =IF(AND(E$5>=$B66,E$5<=$C66),$D66,"") | F66: =IF(AND(F$5>=$B66,F$5<=$C66),$D66,"") | G66: =IF(AND(G$5>=$B66,G$5<=$C66),$D66,"") | H66: =IF(AND(H$5>=$B66,H$5<=$C66),$D66,"") | I66: =IF(AND(I$5>=$B66,I$5<=$C66),$D66,"") | J66: =IF(AND(J$5>=$B66,J$5<=$C66),$D66,"") | K66: =IF(AND(K$5>=$B66,K$5<=$C66),$D66,"") | L66: =IF(AND(L$5>=$B66,L$5<=$C66),$D66,"") | ... HH66: =IF(AND(HH$5>=$B66,HH$5<=$C66),$D66,"")
A67: ='FY1 Event Pipeline'!A8 -> Tanweer Festival | B67: =_xlfn.XLOOKUP(A67,'FY1 Event Pipeline'!$A$4:$A$15,'FY1 Event Pipeline'!$H$4:$H$15) -> 46340 | C67: =_xlfn.XLOOKUP(A67,'FY1 Event Pipeline'!$A$4:$A$15,'FY1 Event Pipeline'!$J$4:$J$15) -> 46352 | D67: =_xlfn.XLOOKUP(A67,'FY1 Event Pipeline'!$A$4:$A$15,'FY1 Event Pipeline'!$R$4:$R$15) -> 200 | E67: =IF(AND(E$5>=$B67,E$5<=$C67),$D67,"") | F67: =IF(AND(F$5>=$B67,F$5<=$C67),$D67,"") | G67: =IF(AND(G$5>=$B67,G$5<=$C67),$D67,"") | H67: =IF(AND(H$5>=$B67,H$5<=$C67),$D67,"") | I67: =IF(AND(I$5>=$B67,I$5<=$C67),$D67,"") | J67: =IF(AND(J$5>=$B67,J$5<=$C67),$D67,"") | K67: =IF(AND(K$5>=$B67,K$5<=$C67),$D67,"") | L67: =IF(AND(L$5>=$B67,L$5<=$C67),$D67,"") | ... HH67: =IF(AND(HH$5>=$B67,HH$5<=$C67),$D67,"")
A68: ='FY1 Event Pipeline'!A9 -> MOTN AAN | B68: =_xlfn.XLOOKUP(A68,'FY1 Event Pipeline'!$A$4:$A$15,'FY1 Event Pipeline'!$H$4:$H$15) -> 46336 | C68: =_xlfn.XLOOKUP(A68,'FY1 Event Pipeline'!$A$4:$A$15,'FY1 Event Pipeline'!$J$4:$J$15) -> 46362 | D68: =_xlfn.XLOOKUP(A68,'FY1 Event Pipeline'!$A$4:$A$15,'FY1 Event Pipeline'!$R$4:$R$15) -> 0 | E68: =IF(AND(E$5>=$B68,E$5<=$C68),$D68,"") | F68: =IF(AND(F$5>=$B68,F$5<=$C68),$D68,"") | G68: =IF(AND(G$5>=$B68,G$5<=$C68),$D68,"") | H68: =IF(AND(H$5>=$B68,H$5<=$C68),$D68,"") | I68: =IF(AND(I$5>=$B68,I$5<=$C68),$D68,"") | J68: =IF(AND(J$5>=$B68,J$5<=$C68),$D68,"") | K68: =IF(AND(K$5>=$B68,K$5<=$C68),$D68,"") | L68: =IF(AND(L$5>=$B68,L$5<=$C68),$D68,"") | ... HH68: =IF(AND(HH$5>=$B68,HH$5<=$C68),$D68,"")
A69: ='FY1 Event Pipeline'!A10 -> F1 Afterparty | B69: =_xlfn.XLOOKUP(A69,'FY1 Event Pipeline'!$A$4:$A$15,'FY1 Event Pipeline'!$H$4:$H$15) -> 46353 | C69: =_xlfn.XLOOKUP(A69,'FY1 Event Pipeline'!$A$4:$A$15,'FY1 Event Pipeline'!$J$4:$J$15) -> 46365 | D69: =_xlfn.XLOOKUP(A69,'FY1 Event Pipeline'!$A$4:$A$15,'FY1 Event Pipeline'!$R$4:$R$15) -> 178 | E69: =IF(AND(E$5>=$B69,E$5<=$C69),$D69,"") | F69: =IF(AND(F$5>=$B69,F$5<=$C69),$D69,"") | G69: =IF(AND(G$5>=$B69,G$5<=$C69),$D69,"") | H69: =IF(AND(H$5>=$B69,H$5<=$C69),$D69,"") | I69: =IF(AND(I$5>=$B69,I$5<=$C69),$D69,"") | J69: =IF(AND(J$5>=$B69,J$5<=$C69),$D69,"") | K69: =IF(AND(K$5>=$B69,K$5<=$C69),$D69,"") | L69: =IF(AND(L$5>=$B69,L$5<=$C69),$D69,"") | ... HH69: =IF(AND(HH$5>=$B69,HH$5<=$C69),$D69,"")
A70: ='FY1 Event Pipeline'!A11 -> MOTN AUH | B70: =_xlfn.XLOOKUP(A70,'FY1 Event Pipeline'!$A$4:$A$15,'FY1 Event Pipeline'!$H$4:$H$15) -> 46346 | C70: =_xlfn.XLOOKUP(A70,'FY1 Event Pipeline'!$A$4:$A$15,'FY1 Event Pipeline'!$J$4:$J$15) -> 46398 | D70: =_xlfn.XLOOKUP(A70,'FY1 Event Pipeline'!$A$4:$A$15,'FY1 Event Pipeline'!$R$4:$R$15) -> 200 | E70: =IF(AND(E$5>=$B70,E$5<=$C70),$D70,"") | F70: =IF(AND(F$5>=$B70,F$5<=$C70),$D70,"") | G70: =IF(AND(G$5>=$B70,G$5<=$C70),$D70,"") | H70: =IF(AND(H$5>=$B70,H$5<=$C70),$D70,"") | I70: =IF(AND(I$5>=$B70,I$5<=$C70),$D70,"") | J70: =IF(AND(J$5>=$B70,J$5<=$C70),$D70,"") | K70: =IF(AND(K$5>=$B70,K$5<=$C70),$D70,"") | L70: =IF(AND(L$5>=$B70,L$5<=$C70),$D70,"") | ... HH70: =IF(AND(HH$5>=$B70,HH$5<=$C70),$D70,"")
A71: ='FY1 Event Pipeline'!A12 -> Yas Winterfest | B71: =_xlfn.XLOOKUP(A71,'FY1 Event Pipeline'!$A$4:$A$15,'FY1 Event Pipeline'!$H$4:$H$15) -> 46352 | C71: =_xlfn.XLOOKUP(A71,'FY1 Event Pipeline'!$A$4:$A$15,'FY1 Event Pipeline'!$J$4:$J$15) -> 46384 | D71: =_xlfn.XLOOKUP(A71,'FY1 Event Pipeline'!$A$4:$A$15,'FY1 Event Pipeline'!$R$4:$R$15) -> 60 | E71: =IF(AND(E$5>=$B71,E$5<=$C71),$D71,"") | F71: =IF(AND(F$5>=$B71,F$5<=$C71),$D71,"") | G71: =IF(AND(G$5>=$B71,G$5<=$C71),$D71,"") | H71: =IF(AND(H$5>=$B71,H$5<=$C71),$D71,"") | I71: =IF(AND(I$5>=$B71,I$5<=$C71),$D71,"") | J71: =IF(AND(J$5>=$B71,J$5<=$C71),$D71,"") | K71: =IF(AND(K$5>=$B71,K$5<=$C71),$D71,"") | L71: =IF(AND(L$5>=$B71,L$5<=$C71),$D71,"") | ... HH71: =IF(AND(HH$5>=$B71,HH$5<=$C71),$D71,"")
A72: ='FY1 Event Pipeline'!A13 -> Animenia | B72: =_xlfn.XLOOKUP(A72,'FY1 Event Pipeline'!$A$4:$A$15,'FY1 Event Pipeline'!$H$4:$H$15) -> 46414 | C72: =_xlfn.XLOOKUP(A72,'FY1 Event Pipeline'!$A$4:$A$15,'FY1 Event Pipeline'!$J$4:$J$15) -> 46436 | D72: =_xlfn.XLOOKUP(A72,'FY1 Event Pipeline'!$A$4:$A$15,'FY1 Event Pipeline'!$R$4:$R$15) -> 0 | E72: =IF(AND(E$5>=$B72,E$5<=$C72),$D72,"") | F72: =IF(AND(F$5>=$B72,F$5<=$C72),$D72,"") | G72: =IF(AND(G$5>=$B72,G$5<=$C72),$D72,"") | H72: =IF(AND(H$5>=$B72,H$5<=$C72),$D72,"") | I72: =IF(AND(I$5>=$B72,I$5<=$C72),$D72,"") | J72: =IF(AND(J$5>=$B72,J$5<=$C72),$D72,"") | K72: =IF(AND(K$5>=$B72,K$5<=$C72),$D72,"") | L72: =IF(AND(L$5>=$B72,L$5<=$C72),$D72,"") | ... HH72: =IF(AND(HH$5>=$B72,HH$5<=$C72),$D72,"")
A73: ='FY1 Event Pipeline'!A14 -> DAZ | B73: =_xlfn.XLOOKUP(A73,'FY1 Event Pipeline'!$A$4:$A$15,'FY1 Event Pipeline'!$H$4:$H$15) -> 46466 | C73: =_xlfn.XLOOKUP(A73,'FY1 Event Pipeline'!$A$4:$A$15,'FY1 Event Pipeline'!$J$4:$J$15) -> 46496 | D73: =_xlfn.XLOOKUP(A73,'FY1 Event Pipeline'!$A$4:$A$15,'FY1 Event Pipeline'!$R$4:$R$15) -> 60 | E73: =IF(AND(E$5>=$B73,E$5<=$C73),$D73,"") | F73: =IF(AND(F$5>=$B73,F$5<=$C73),$D73,"") | G73: =IF(AND(G$5>=$B73,G$5<=$C73),$D73,"") | H73: =IF(AND(H$5>=$B73,H$5<=$C73),$D73,"") | I73: =IF(AND(I$5>=$B73,I$5<=$C73),$D73,"") | J73: =IF(AND(J$5>=$B73,J$5<=$C73),$D73,"") | K73: =IF(AND(K$5>=$B73,K$5<=$C73),$D73,"") | L73: =IF(AND(L$5>=$B73,L$5<=$C73),$D73,"") | ... HH73: =IF(AND(HH$5>=$B73,HH$5<=$C73),$D73,"")
A74: ='FY1 Event Pipeline'!A15 -> BRED | B74: =_xlfn.XLOOKUP(A74,'FY1 Event Pipeline'!$A$4:$A$15,'FY1 Event Pipeline'!$H$4:$H$15) -> 46492 | C74: =_xlfn.XLOOKUP(A74,'FY1 Event Pipeline'!$A$4:$A$15,'FY1 Event Pipeline'!$J$4:$J$15) -> 46506 | D74: =_xlfn.XLOOKUP(A74,'FY1 Event Pipeline'!$A$4:$A$15,'FY1 Event Pipeline'!$R$4:$R$15) -> 0 | E74: =IF(AND(E$5>=$B74,E$5<=$C74),$D74,"") | F74: =IF(AND(F$5>=$B74,F$5<=$C74),$D74,"") | G74: =IF(AND(G$5>=$B74,G$5<=$C74),$D74,"") | H74: =IF(AND(H$5>=$B74,H$5<=$C74),$D74,"") | I74: =IF(AND(I$5>=$B74,I$5<=$C74),$D74,"") | J74: =IF(AND(J$5>=$B74,J$5<=$C74),$D74,"") | K74: =IF(AND(K$5>=$B74,K$5<=$C74),$D74,"") | L74: =IF(AND(L$5>=$B74,L$5<=$C74),$D74,"") | ... HH74: =IF(AND(HH$5>=$B74,HH$5<=$C74),$D74,"")
A75: MAX TERRATRAK ON-HIRE | D75: =MAX(E75:HH75) -> 940 | E75: =SUM(E63:E74) -> 0 | F75: =SUM(F63:F74) -> 280 | G75: =SUM(G63:G74) -> 280 | H75: =SUM(H63:H74) -> 280 | I75: =SUM(I63:I74) -> 280 | J75: =SUM(J63:J74) -> 280 | K75: =SUM(K63:K74) -> 280 | L75: =SUM(L63:L74) -> 280 | ... HH75: =SUM(HH63:HH74) -> 0

Sheet Depreciation Schedule
A1: STRAIGHT-LINE DEPRECIATION SCHEDULE
A2: Each capex tranche depreciated independently from acquisition year. CapEx pulled from CapEx & Storage sheet.
A3: Asset Group | B3: CapEx (AED) | C3: Acquisition Year | D3: Life (yrs) | E3: Residual % | F3: Depreciable Base | G3: Annual Dep'n | H3: Year 1 | I3: Year 2 | J3: Year 3 | K3: Year 4 | L3: Year 5 | M3: Year 6 | N3: Year 7 | O3: Year 8
H4: 1 | I4: 2 | J4: 3 | K4: 4 | L4: 5 | M4: 6 | N4: 7 | O4: 8
A5: Cabins - Y1 fleet | B5: {=TRANSPOSE('CapEx & Storage'!E18:L18)} -> 6658100 | C5: =Assumptions!$B$4 -> 2026 | D5: =Assumptions!$B$26 -> 8 | E5: =Assumptions!$B$27 -> 0.2 | F5: =B5*(1-E5) -> 5326480 | G5: =F5/D5 -> 665810 | H5: =IF(AND(($C5-Assumptions!$B$4+1)<=H$4,H$4<=($C5-Assumptions!$B$4+$D5)),$G5,0) -> 665810 | I5: =IF(AND(($C5-Assumptions!$B$4+1)<=I$4,I$4<=($C5-Assumptions!$B$4+$D5)),$G5,0) -> 665810 | J5: =IF(AND(($C5-Assumptions!$B$4+1)<=J$4,J$4<=($C5-Assumptions!$B$4+$D5)),$G5,0) -> 665810 | K5: =IF(AND(($C5-Assumptions!$B$4+1)<=K$4,K$4<=($C5-Assumptions!$B$4+$D5)),$G5,0) -> 665810 | L5: =IF(AND(($C5-Assumptions!$B$4+1)<=L$4,L$4<=($C5-Assumptions!$B$4+$D5)),$G5,0) -> 665810 | M5: =IF(AND(($C5-Assumptions!$B$4+1)<=M$4,M$4<=($C5-Assumptions!$B$4+$D5)),$G5,0) -> 665810 | N5: =IF(AND(($C5-Assumptions!$B$4+1)<=N$4,N$4<=($C5-Assumptions!$B$4+$D5)),$G5,0) -> 665810 | O5: =IF(AND(($C5-Assumptions!$B$4+1)<=O$4,O$4<=($C5-Assumptions!$B$4+$D5)),$G5,0) -> 665810
A6: Cabins - Y2 additions | B6: 764286 | C6: =C5+1 -> 2027 | D6: =Assumptions!$B$26 -> 8 | E6: =Assumptions!$B$27 -> 0.2 | F6: =B6*(1-E6) -> 611428.8 | G6: =F6/D6 -> 76428.6 | H6: =IF(AND(($C6-Assumptions!$B$4+1)<=H$4,H$4<=($C6-Assumptions!$B$4+$D6)),$G6,0) -> 0 | I6: =IF(AND(($C6-Assumptions!$B$4+1)<=I$4,I$4<=($C6-Assumptions!$B$4+$D6)),$G6,0) -> 76428.6 | J6: =IF(AND(($C6-Assumptions!$B$4+1)<=J$4,J$4<=($C6-Assumptions!$B$4+$D6)),$G6,0) -> 76428.6 | K6: =IF(AND(($C6-Assumptions!$B$4+1)<=K$4,K$4<=($C6-Assumptions!$B$4+$D6)),$G6,0) -> 76428.6 | L6: =IF(AND(($C6-Assumptions!$B$4+1)<=L$4,L$4<=($C6-Assumptions!$B$4+$D6)),$G6,0) -> 76428.6 | M6: =IF(AND(($C6-Assumptions!$B$4+1)<=M$4,M$4<=($C6-Assumptions!$B$4+$D6)),$G6,0) -> 76428.6 | N6: =IF(AND(($C6-Assumptions!$B$4+1)<=N$4,N$4<=($C6-Assumptions!$B$4+$D6)),$G6,0) -> 76428.6 | O6: =IF(AND(($C6-Assumptions!$B$4+1)<=O$4,O$4<=($C6-Assumptions!$B$4+$D6)),$G6,0) -> 76428.6
A7: Cabins - Y3 additions | B7: 708928.56 | C7: =C6+1 -> 2028 | D7: =Assumptions!$B$26 -> 8 | E7: =Assumptions!$B$27 -> 0.2 | F7: =B7*(1-E7) -> 567142.85 | G7: =F7/D7 -> 70892.856 | H7: =IF(AND(($C7-Assumptions!$B$4+1)<=H$4,H$4<=($C7-Assumptions!$B$4+$D7)),$G7,0) -> 0 | I7: =IF(AND(($C7-Assumptions!$B$4+1)<=I$4,I$4<=($C7-Assumptions!$B$4+$D7)),$G7,0) -> 0 | J7: =IF(AND(($C7-Assumptions!$B$4+1)<=J$4,J$4<=($C7-Assumptions!$B$4+$D7)),$G7,0) -> 70892.856 | K7: =IF(AND(($C7-Assumptions!$B$4+1)<=K$4,K$4<=($C7-Assumptions!$B$4+$D7)),$G7,0) -> 70892.856 | L7: =IF(AND(($C7-Assumptions!$B$4+1)<=L$4,L$4<=($C7-Assumptions!$B$4+$D7)),$G7,0) -> 70892.856 | M7: =IF(AND(($C7-Assumptions!$B$4+1)<=M$4,M$4<=($C7-Assumptions!$B$4+$D7)),$G7,0) -> 70892.856 | N7: =IF(AND(($C7-Assumptions!$B$4+1)<=N$4,N$4<=($C7-Assumptions!$B$4+$D7)),$G7,0) -> 70892.856 | O7: =IF(AND(($C7-Assumptions!$B$4+1)<=O$4,O$4<=($C7-Assumptions!$B$4+$D7)),$G7,0) -> 70892.856
A8: Cabins - Y4 additions | B8: 884516.87 | C8: =C7+1 -> 2029 | D8: =Assumptions!$B$26 -> 8 | E8: =Assumptions!$B$27 -> 0.2 | F8: =B8*(1-E8) -> 707613.49 | G8: =F8/D8 -> 88451.687 | H8: =IF(AND(($C8-Assumptions!$B$4+1)<=H$4,H$4<=($C8-Assumptions!$B$4+$D8)),$G8,0) -> 0 | I8: =IF(AND(($C8-Assumptions!$B$4+1)<=I$4,I$4<=($C8-Assumptions!$B$4+$D8)),$G8,0) -> 0 | J8: =IF(AND(($C8-Assumptions!$B$4+1)<=J$4,J$4<=($C8-Assumptions!$B$4+$D8)),$G8,0) -> 0 | K8: =IF(AND(($C8-Assumptions!$B$4+1)<=K$4,K$4<=($C8-Assumptions!$B$4+$D8)),$G8,0) -> 88451.687 | L8: =IF(AND(($C8-Assumptions!$B$4+1)<=L$4,L$4<=($C8-Assumptions!$B$4+$D8)),$G8,0) -> 88451.687 | M8: =IF(AND(($C8-Assumptions!$B$4+1)<=M$4,M$4<=($C8-Assumptions!$B$4+$D8)),$G8,0) -> 88451.687 | N8: =IF(AND(($C8-Assumptions!$B$4+1)<=N$4,N$4<=($C8-Assumptions!$B$4+$D8)),$G8,0) -> 88451.687 | O8: =IF(AND(($C8-Assumptions!$B$4+1)<=O$4,O$4<=($C8-Assumptions!$B$4+$D8)),$G8,0) -> 88451.687
A9: Cabins - Y5 additions | B9: 955787.6 | C9: =C8+1 -> 2030 | D9: =Assumptions!$B$26 -> 8 | E9: =Assumptions!$B$27 -> 0.2 | F9: =B9*(1-E9) -> 764630.08 | G9: =F9/D9 -> 95578.76 | H9: =IF(AND(($C9-Assumptions!$B$4+1)<=H$4,H$4<=($C9-Assumptions!$B$4+$D9)),$G9,0) -> 0 | I9: =IF(AND(($C9-Assumptions!$B$4+1)<=I$4,I$4<=($C9-Assumptions!$B$4+$D9)),$G9,0) -> 0 | J9: =IF(AND(($C9-Assumptions!$B$4+1)<=J$4,J$4<=($C9-Assumptions!$B$4+$D9)),$G9,0) -> 0 | K9: =IF(AND(($C9-Assumptions!$B$4+1)<=K$4,K$4<=($C9-Assumptions!$B$4+$D9)),$G9,0) -> 0 | L9: =IF(AND(($C9-Assumptions!$B$4+1)<=L$4,L$4<=($C9-Assumptions!$B$4+$D9)),$G9,0) -> 95578.76 | M9: =IF(AND(($C9-Assumptions!$B$4+1)<=M$4,M$4<=($C9-Assumptions!$B$4+$D9)),$G9,0) -> 95578.76 | N9: =IF(AND(($C9-Assumptions!$B$4+1)<=N$4,N$4<=($C9-Assumptions!$B$4+$D9)),$G9,0) -> 95578.76 | O9: =IF(AND(($C9-Assumptions!$B$4+1)<=O$4,O$4<=($C9-Assumptions!$B$4+$D9)),$G9,0) -> 95578.76
A10: Cabins - Y6 additions | B10: 0 | C10: =C9+1 -> 2031 | D10: =Assumptions!$B$26 -> 8 | E10: =Assumptions!$B$27 -> 0.2 | F10: =B10*(1-E10) -> 0 | G10: =F10/D10 -> 0 | L10: =IF(AND(($C10-Assumptions!$B$4+1)<=L$4,L$4<=($C10-Assumptions!$B$4+$D10)),$G10,0) -> 0 | M10: =IF(AND(($C10-Assumptions!$B$4+1)<=M$4,M$4<=($C10-Assumptions!$B$4+$D10)),$G10,0) -> 0 | N10: =IF(AND(($C10-Assumptions!$B$4+1)<=N$4,N$4<=($C10-Assumptions!$B$4+$D10)),$G10,0) -> 0 | O10: =IF(AND(($C10-Assumptions!$B$4+1)<=O$4,O$4<=($C10-Assumptions!$B$4+$D10)),$G10,0) -> 0
A11: Cabins - Y7 additions | B11: 0 | C11: =C10+1 -> 2032 | D11: =Assumptions!$B$26 -> 8 | E11: =Assumptions!$B$27 -> 0.2 | F11: =B11*(1-E11) -> 0 | G11: =F11/D11 -> 0 | L11: =IF(AND(($C11-Assumptions!$B$4+1)<=L$4,L$4<=($C11-Assumptions!$B$4+$D11)),$G11,0) -> 0 | M11: =IF(AND(($C11-Assumptions!$B$4+1)<=M$4,M$4<=($C11-Assumptions!$B$4+$D11)),$G11,0) -> 0 | N11: =IF(AND(($C11-Assumptions!$B$4+1)<=N$4,N$4<=($C11-Assumptions!$B$4+$D11)),$G11,0) -> 0 | O11: =IF(AND(($C11-Assumptions!$B$4+1)<=O$4,O$4<=($C11-Assumptions!$B$4+$D11)),$G11,0) -> 0
A12: Cabins - Y8 additions | B12: 0 | C12: =C11+1 -> 2033 | D12: =Assumptions!$B$26 -> 8 | E12: =Assumptions!$B$27 -> 0.2 | F12: =B12*(1-E12) -> 0 | G12: =F12/D12 -> 0 | L12: =IF(AND(($C12-Assumptions!$B$4+1)<=L$4,L$4<=($C12-Assumptions!$B$4+$D12)),$G12,0) -> 0 | M12: =IF(AND(($C12-Assumptions!$B$4+1)<=M$4,M$4<=($C12-Assumptions!$B$4+$D12)),$G12,0) -> 0 | N12: =IF(AND(($C12-Assumptions!$B$4+1)<=N$4,N$4<=($C12-Assumptions!$B$4+$D12)),$G12,0) -> 0 | O12: =IF(AND(($C12-Assumptions!$B$4+1)<=O$4,O$4<=($C12-Assumptions!$B$4+$D12)),$G12,0) -> 0
A13: Buggies - Y1 fleet | B13: {=TRANSPOSE('CapEx & Storage'!E19:L19)} -> 1040000 | C13: =Assumptions!$B$4 -> 2026 | D13: =Assumptions!$B$30 -> 10 | E13: =Assumptions!$B$31 -> 0.3 | F13: =B13*(1-E13) -> 728000 | G13: =F13/D13 -> 72800 | H13: =IF(AND(($C13-Assumptions!$B$4+1)<=H$4,H$4<=($C13-Assumptions!$B$4+$D13)),$G13,0) -> 72800 | I13: =IF(AND(($C13-Assumptions!$B$4+1)<=I$4,I$4<=($C13-Assumptions!$B$4+$D13)),$G13,0) -> 72800 | J13: =IF(AND(($C13-Assumptions!$B$4+1)<=J$4,J$4<=($C13-Assumptions!$B$4+$D13)),$G13,0) -> 72800 | K13: =IF(AND(($C13-Assumptions!$B$4+1)<=K$4,K$4<=($C13-Assumptions!$B$4+$D13)),$G13,0) -> 72800 | L13: =IF(AND(($C13-Assumptions!$B$4+1)<=L$4,L$4<=($C13-Assumptions!$B$4+$D13)),$G13,0) -> 72800 | M13: =IF(AND(($C13-Assumptions!$B$4+1)<=M$4,M$4<=($C13-Assumptions!$B$4+$D13)),$G13,0) -> 72800 | N13: =IF(AND(($C13-Assumptions!$B$4+1)<=N$4,N$4<=($C13-Assumptions!$B$4+$D13)),$G13,0) -> 72800 | O13: =IF(AND(($C13-Assumptions!$B$4+1)<=O$4,O$4<=($C13-Assumptions!$B$4+$D13)),$G13,0) -> 72800
A14: Buggies - Y2 additions | B14: 81600 | C14: =C13+1 -> 2027 | D14: =Assumptions!$B$30 -> 10 | E14: =Assumptions!$B$31 -> 0.3 | F14: =B14*(1-E14) -> 57120 | G14: =F14/D14 -> 5712 | H14: =IF(AND(($C14-Assumptions!$B$4+1)<=H$4,H$4<=($C14-Assumptions!$B$4+$D14)),$G14,0) -> 0 | I14: =IF(AND(($C14-Assumptions!$B$4+1)<=I$4,I$4<=($C14-Assumptions!$B$4+$D14)),$G14,0) -> 5712 | J14: =IF(AND(($C14-Assumptions!$B$4+1)<=J$4,J$4<=($C14-Assumptions!$B$4+$D14)),$G14,0) -> 5712 | K14: =IF(AND(($C14-Assumptions!$B$4+1)<=K$4,K$4<=($C14-Assumptions!$B$4+$D14)),$G14,0) -> 5712 | L14: =IF(AND(($C14-Assumptions!$B$4+1)<=L$4,L$4<=($C14-Assumptions!$B$4+$D14)),$G14,0) -> 5712 | M14: =IF(AND(($C14-Assumptions!$B$4+1)<=M$4,M$4<=($C14-Assumptions!$B$4+$D14)),$G14,0) -> 5712 | N14: =IF(AND(($C14-Assumptions!$B$4+1)<=N$4,N$4<=($C14-Assumptions!$B$4+$D14)),$G14,0) -> 5712 | O14: =IF(AND(($C14-Assumptions!$B$4+1)<=O$4,O$4<=($C14-Assumptions!$B$4+$D14)),$G14,0) -> 5712
A15: Buggies - Y3 additions | B15: 83232 | C15: =C14+1 -> 2028 | D15: =Assumptions!$B$30 -> 10 | E15: =Assumptions!$B$31 -> 0.3 | F15: =B15*(1-E15) -> 58262.4 | G15: =F15/D15 -> 5826.24 | H15: =IF(AND(($C15-Assumptions!$B$4+1)<=H$4,H$4<=($C15-Assumptions!$B$4+$D15)),$G15,0) -> 0 | I15: =IF(AND(($C15-Assumptions!$B$4+1)<=I$4,I$4<=($C15-Assumptions!$B$4+$D15)),$G15,0) -> 0 | J15: =IF(AND(($C15-Assumptions!$B$4+1)<=J$4,J$4<=($C15-Assumptions!$B$4+$D15)),$G15,0) -> 5826.24 | K15: =IF(AND(($C15-Assumptions!$B$4+1)<=K$4,K$4<=($C15-Assumptions!$B$4+$D15)),$G15,0) -> 5826.24 | L15: =IF(AND(($C15-Assumptions!$B$4+1)<=L$4,L$4<=($C15-Assumptions!$B$4+$D15)),$G15,0) -> 5826.24 | M15: =IF(AND(($C15-Assumptions!$B$4+1)<=M$4,M$4<=($C15-Assumptions!$B$4+$D15)),$G15,0) -> 5826.24 | N15: =IF(AND(($C15-Assumptions!$B$4+1)<=N$4,N$4<=($C15-Assumptions!$B$4+$D15)),$G15,0) -> 5826.24 | O15: =IF(AND(($C15-Assumptions!$B$4+1)<=O$4,O$4<=($C15-Assumptions!$B$4+$D15)),$G15,0) -> 5826.24
A16: Buggies - Y4 additions | B16: 169793.28 | C16: =C15+1 -> 2029 | D16: =Assumptions!$B$30 -> 10 | E16: =Assumptions!$B$31 -> 0.3 | F16: =B16*(1-E16) -> 118855.3 | G16: =F16/D16 -> 11885.53 | H16: =IF(AND(($C16-Assumptions!$B$4+1)<=H$4,H$4<=($C16-Assumptions!$B$4+$D16)),$G16,0) -> 0 | I16: =IF(AND(($C16-Assumptions!$B$4+1)<=I$4,I$4<=($C16-Assumptions!$B$4+$D16)),$G16,0) -> 0 | J16: =IF(AND(($C16-Assumptions!$B$4+1)<=J$4,J$4<=($C16-Assumptions!$B$4+$D16)),$G16,0) -> 0 | K16: =IF(AND(($C16-Assumptions!$B$4+1)<=K$4,K$4<=($C16-Assumptions!$B$4+$D16)),$G16,0) -> 11885.53 | L16: =IF(AND(($C16-Assumptions!$B$4+1)<=L$4,L$4<=($C16-Assumptions!$B$4+$D16)),$G16,0) -> 11885.53 | M16: =IF(AND(($C16-Assumptions!$B$4+1)<=M$4,M$4<=($C16-Assumptions!$B$4+$D16)),$G16,0) -> 11885.53 | N16: =IF(AND(($C16-Assumptions!$B$4+1)<=N$4,N$4<=($C16-Assumptions!$B$4+$D16)),$G16,0) -> 11885.53 | O16: =IF(AND(($C16-Assumptions!$B$4+1)<=O$4,O$4<=($C16-Assumptions!$B$4+$D16)),$G16,0) -> 11885.53
A17: Buggies - Y5 additions | B17: 0 | C17: =C16+1 -> 2030 | D17: =Assumptions!$B$30 -> 10 | E17: =Assumptions!$B$31 -> 0.3 | F17: =B17*(1-E17) -> 0 | G17: =F17/D17 -> 0 | H17: =IF(AND(($C17-Assumptions!$B$4+1)<=H$4,H$4<=($C17-Assumptions!$B$4+$D17)),$G17,0) -> 0 | I17: =IF(AND(($C17-Assumptions!$B$4+1)<=I$4,I$4<=($C17-Assumptions!$B$4+$D17)),$G17,0) -> 0 | J17: =IF(AND(($C17-Assumptions!$B$4+1)<=J$4,J$4<=($C17-Assumptions!$B$4+$D17)),$G17,0) -> 0 | K17: =IF(AND(($C17-Assumptions!$B$4+1)<=K$4,K$4<=($C17-Assumptions!$B$4+$D17)),$G17,0) -> 0 | L17: =IF(AND(($C17-Assumptions!$B$4+1)<=L$4,L$4<=($C17-Assumptions!$B$4+$D17)),$G17,0) -> 0 | M17: =IF(AND(($C17-Assumptions!$B$4+1)<=M$4,M$4<=($C17-Assumptions!$B$4+$D17)),$G17,0) -> 0 | N17: =IF(AND(($C17-Assumptions!$B$4+1)<=N$4,N$4<=($C17-Assumptions!$B$4+$D17)),$G17,0) -> 0 | O17: =IF(AND(($C17-Assumptions!$B$4+1)<=O$4,O$4<=($C17-Assumptions!$B$4+$D17)),$G17,0) -> 0
A18: Buggies - Y6 additions | B18: 176652.93 | C18: =C17+1 -> 2031 | D18: =Assumptions!$B$30 -> 10 | E18: =Assumptions!$B$31 -> 0.3 | F18: =B18*(1-E18) -> 123657.05 | G18: =F18/D18 -> 12365.705 | L18: =IF(AND(($C18-Assumptions!$B$4+1)<=L$4,L$4<=($C18-Assumptions!$B$4+$D18)),$G18,0) -> 0 | M18: =IF(AND(($C18-Assumptions!$B$4+1)<=M$4,M$4<=($C18-Assumptions!$B$4+$D18)),$G18,0) -> 12365.705 | N18: =IF(AND(($C18-Assumptions!$B$4+1)<=N$4,N$4<=($C18-Assumptions!$B$4+$D18)),$G18,0) -> 12365.705 | O18: =IF(AND(($C18-Assumptions!$B$4+1)<=O$4,O$4<=($C18-Assumptions!$B$4+$D18)),$G18,0) -> 12365.705
A19: Buggies - Y7 additions | B19: 180185.99 | C19: =C18+1 -> 2032 | D19: =Assumptions!$B$30 -> 10 | E19: =Assumptions!$B$31 -> 0.3 | F19: =B19*(1-E19) -> 126130.19 | G19: =F19/D19 -> 12613.019 | L19: =IF(AND(($C19-Assumptions!$B$4+1)<=L$4,L$4<=($C19-Assumptions!$B$4+$D19)),$G19,0) -> 0 | M19: =IF(AND(($C19-Assumptions!$B$4+1)<=M$4,M$4<=($C19-Assumptions!$B$4+$D19)),$G19,0) -> 0 | N19: =IF(AND(($C19-Assumptions!$B$4+1)<=N$4,N$4<=($C19-Assumptions!$B$4+$D19)),$G19,0) -> 12613.019 | O19: =IF(AND(($C19-Assumptions!$B$4+1)<=O$4,O$4<=($C19-Assumptions!$B$4+$D19)),$G19,0) -> 12613.019
A20: Buggies - Y8 additions | B20: 183789.71 | C20: =C19+1 -> 2033 | D20: =Assumptions!$B$30 -> 10 | E20: =Assumptions!$B$31 -> 0.3 | F20: =B20*(1-E20) -> 128652.79 | G20: =F20/D20 -> 12865.279 | L20: =IF(AND(($C20-Assumptions!$B$4+1)<=L$4,L$4<=($C20-Assumptions!$B$4+$D20)),$G20,0) -> 0 | M20: =IF(AND(($C20-Assumptions!$B$4+1)<=M$4,M$4<=($C20-Assumptions!$B$4+$D20)),$G20,0) -> 0 | N20: =IF(AND(($C20-Assumptions!$B$4+1)<=N$4,N$4<=($C20-Assumptions!$B$4+$D20)),$G20,0) -> 0 | O20: =IF(AND(($C20-Assumptions!$B$4+1)<=O$4,O$4<=($C20-Assumptions!$B$4+$D20)),$G20,0) -> 12865.279
A21: Barriers - Y1 fleet | B21: {=TRANSPOSE('CapEx & Storage'!E20:L20)} -> 690000 | C21: =Assumptions!$B$4 -> 2026 | D21: =Assumptions!$B$35 -> 10 | E21: =Assumptions!$B$36 -> 0.4 | F21: =B21*(1-E21) -> 414000 | G21: =F21/D21 -> 41400 | H21: =IF(AND(($C21-Assumptions!$B$4+1)<=H$4,H$4<=($C21-Assumptions!$B$4+$D21)),$G21,0) -> 41400 | I21: =IF(AND(($C21-Assumptions!$B$4+1)<=I$4,I$4<=($C21-Assumptions!$B$4+$D21)),$G21,0) -> 41400 | J21: =IF(AND(($C21-Assumptions!$B$4+1)<=J$4,J$4<=($C21-Assumptions!$B$4+$D21)),$G21,0) -> 41400 | K21: =IF(AND(($C21-Assumptions!$B$4+1)<=K$4,K$4<=($C21-Assumptions!$B$4+$D21)),$G21,0) -> 41400 | L21: =IF(AND(($C21-Assumptions!$B$4+1)<=L$4,L$4<=($C21-Assumptions!$B$4+$D21)),$G21,0) -> 41400 | M21: =IF(AND(($C21-Assumptions!$B$4+1)<=M$4,M$4<=($C21-Assumptions!$B$4+$D21)),$G21,0) -> 41400 | N21: =IF(AND(($C21-Assumptions!$B$4+1)<=N$4,N$4<=($C21-Assumptions!$B$4+$D21)),$G21,0) -> 41400 | O21: =IF(AND(($C21-Assumptions!$B$4+1)<=O$4,O$4<=($C21-Assumptions!$B$4+$D21)),$G21,0) -> 41400
A22: Barriers - Y2 additions | B22: 33048 | C22: =C21+1 -> 2027 | D22: =Assumptions!$B$35 -> 10 | E22: =Assumptions!$B$36 -> 0.4 | F22: =B22*(1-E22) -> 19828.8 | G22: =F22/D22 -> 1982.88 | H22: =IF(AND(($C22-Assumptions!$B$4+1)<=H$4,H$4<=($C22-Assumptions!$B$4+$D22)),$G22,0) -> 0 | I22: =IF(AND(($C22-Assumptions!$B$4+1)<=I$4,I$4<=($C22-Assumptions!$B$4+$D22)),$G22,0) -> 1982.88 | J22: =IF(AND(($C22-Assumptions!$B$4+1)<=J$4,J$4<=($C22-Assumptions!$B$4+$D22)),$G22,0) -> 1982.88 | K22: =IF(AND(($C22-Assumptions!$B$4+1)<=K$4,K$4<=($C22-Assumptions!$B$4+$D22)),$G22,0) -> 1982.88 | L22: =IF(AND(($C22-Assumptions!$B$4+1)<=L$4,L$4<=($C22-Assumptions!$B$4+$D22)),$G22,0) -> 1982.88 | M22: =IF(AND(($C22-Assumptions!$B$4+1)<=M$4,M$4<=($C22-Assumptions!$B$4+$D22)),$G22,0) -> 1982.88 | N22: =IF(AND(($C22-Assumptions!$B$4+1)<=N$4,N$4<=($C22-Assumptions!$B$4+$D22)),$G22,0) -> 1982.88 | O22: =IF(AND(($C22-Assumptions!$B$4+1)<=O$4,O$4<=($C22-Assumptions!$B$4+$D22)),$G22,0) -> 1982.88
A23: Barriers - Y3 additions | B23: 104872.32 | C23: =C22+1 -> 2028 | D23: =Assumptions!$B$35 -> 10 | E23: =Assumptions!$B$36 -> 0.4 | F23: =B23*(1-E23) -> 62923.392 | G23: =F23/D23 -> 6292.3392 | H23: =IF(AND(($C23-Assumptions!$B$4+1)<=H$4,H$4<=($C23-Assumptions!$B$4+$D23)),$G23,0) -> 0 | I23: =IF(AND(($C23-Assumptions!$B$4+1)<=I$4,I$4<=($C23-Assumptions!$B$4+$D23)),$G23,0) -> 0 | J23: =IF(AND(($C23-Assumptions!$B$4+1)<=J$4,J$4<=($C23-Assumptions!$B$4+$D23)),$G23,0) -> 6292.3392 | K23: =IF(AND(($C23-Assumptions!$B$4+1)<=K$4,K$4<=($C23-Assumptions!$B$4+$D23)),$G23,0) -> 6292.3392 | L23: =IF(AND(($C23-Assumptions!$B$4+1)<=L$4,L$4<=($C23-Assumptions!$B$4+$D23)),$G23,0) -> 6292.3392 | M23: =IF(AND(($C23-Assumptions!$B$4+1)<=M$4,M$4<=($C23-Assumptions!$B$4+$D23)),$G23,0) -> 6292.3392 | N23: =IF(AND(($C23-Assumptions!$B$4+1)<=N$4,N$4<=($C23-Assumptions!$B$4+$D23)),$G23,0) -> 6292.3392 | O23: =IF(AND(($C23-Assumptions!$B$4+1)<=O$4,O$4<=($C23-Assumptions!$B$4+$D23)),$G23,0) -> 6292.3392
A24: Barriers - Y4 additions | B24: 65582.654 | C24: =C23+1 -> 2029 | D24: =Assumptions!$B$35 -> 10 | E24: =Assumptions!$B$36 -> 0.4 | F24: =B24*(1-E24) -> 39349.593 | G24: =F24/D24 -> 3934.9593 | H24: =IF(AND(($C24-Assumptions!$B$4+1)<=H$4,H$4<=($C24-Assumptions!$B$4+$D24)),$G24,0) -> 0 | I24: =IF(AND(($C24-Assumptions!$B$4+1)<=I$4,I$4<=($C24-Assumptions!$B$4+$D24)),$G24,0) -> 0 | J24: =IF(AND(($C24-Assumptions!$B$4+1)<=J$4,J$4<=($C24-Assumptions!$B$4+$D24)),$G24,0) -> 0 | K24: =IF(AND(($C24-Assumptions!$B$4+1)<=K$4,K$4<=($C24-Assumptions!$B$4+$D24)),$G24,0) -> 3934.9593 | L24: =IF(AND(($C24-Assumptions!$B$4+1)<=L$4,L$4<=($C24-Assumptions!$B$4+$D24)),$G24,0) -> 3934.9593 | M24: =IF(AND(($C24-Assumptions!$B$4+1)<=M$4,M$4<=($C24-Assumptions!$B$4+$D24)),$G24,0) -> 3934.9593 | N24: =IF(AND(($C24-Assumptions!$B$4+1)<=N$4,N$4<=($C24-Assumptions!$B$4+$D24)),$G24,0) -> 3934.9593 | O24: =IF(AND(($C24-Assumptions!$B$4+1)<=O$4,O$4<=($C24-Assumptions!$B$4+$D24)),$G24,0) -> 3934.9593
A25: Barriers - Y5 additions | B25: 46761.069 | C25: =C24+1 -> 2030 | D25: =Assumptions!$B$35 -> 10 | E25: =Assumptions!$B$36 -> 0.4 | F25: =B25*(1-E25) -> 28056.642 | G25: =F25/D25 -> 2805.6642 | H25: =IF(AND(($C25-Assumptions!$B$4+1)<=H$4,H$4<=($C25-Assumptions!$B$4+$D25)),$G25,0) -> 0 | I25: =IF(AND(($C25-Assumptions!$B$4+1)<=I$4,I$4<=($C25-Assumptions!$B$4+$D25)),$G25,0) -> 0 | J25: =IF(AND(($C25-Assumptions!$B$4+1)<=J$4,J$4<=($C25-Assumptions!$B$4+$D25)),$G25,0) -> 0 | K25: =IF(AND(($C25-Assumptions!$B$4+1)<=K$4,K$4<=($C25-Assumptions!$B$4+$D25)),$G25,0) -> 0 | L25: =IF(AND(($C25-Assumptions!$B$4+1)<=L$4,L$4<=($C25-Assumptions!$B$4+$D25)),$G25,0) -> 2805.6642 | M25: =IF(AND(($C25-Assumptions!$B$4+1)<=M$4,M$4<=($C25-Assumptions!$B$4+$D25)),$G25,0) -> 2805.6642 | N25: =IF(AND(($C25-Assumptions!$B$4+1)<=N$4,N$4<=($C25-Assumptions!$B$4+$D25)),$G25,0) -> 2805.6642 | O25: =IF(AND(($C25-Assumptions!$B$4+1)<=O$4,O$4<=($C25-Assumptions!$B$4+$D25)),$G25,0) -> 2805.6642
A26: Barriers - Y6 additions | B26: 153688.05 | C26: =C25+1 -> 2031 | D26: =Assumptions!$B$35 -> 10 | E26: =Assumptions!$B$36 -> 0.4 | F26: =B26*(1-E26) -> 92212.829 | G26: =F26/D26 -> 9221.2829 | L26: =IF(AND(($C26-Assumptions!$B$4+1)<=L$4,L$4<=($C26-Assumptions!$B$4+$D26)),$G26,0) -> 0 | M26: =IF(AND(($C26-Assumptions!$B$4+1)<=M$4,M$4<=($C26-Assumptions!$B$4+$D26)),$G26,0) -> 9221.2829 | N26: =IF(AND(($C26-Assumptions!$B$4+1)<=N$4,N$4<=($C26-Assumptions!$B$4+$D26)),$G26,0) -> 9221.2829 | O26: =IF(AND(($C26-Assumptions!$B$4+1)<=O$4,O$4<=($C26-Assumptions!$B$4+$D26)),$G26,0) -> 9221.2829
A27: Barriers - Y7 additions | B27: 132436.7 | C27: =C26+1 -> 2032 | D27: =Assumptions!$B$35 -> 10 | E27: =Assumptions!$B$36 -> 0.4 | F27: =B27*(1-E27) -> 79462.02 | G27: =F27/D27 -> 7946.202 | L27: =IF(AND(($C27-Assumptions!$B$4+1)<=L$4,L$4<=($C27-Assumptions!$B$4+$D27)),$G27,0) -> 0 | M27: =IF(AND(($C27-Assumptions!$B$4+1)<=M$4,M$4<=($C27-Assumptions!$B$4+$D27)),$G27,0) -> 0 | N27: =IF(AND(($C27-Assumptions!$B$4+1)<=N$4,N$4<=($C27-Assumptions!$B$4+$D27)),$G27,0) -> 7946.202 | O27: =IF(AND(($C27-Assumptions!$B$4+1)<=O$4,O$4<=($C27-Assumptions!$B$4+$D27)),$G27,0) -> 7946.202
A28: Barriers - Y8 additions | B28: 108206.19 | C28: =C27+1 -> 2033 | D28: =Assumptions!$B$35 -> 10 | E28: =Assumptions!$B$36 -> 0.4 | F28: =B28*(1-E28) -> 64923.714 | G28: =F28/D28 -> 6492.3714 | L28: =IF(AND(($C28-Assumptions!$B$4+1)<=L$4,L$4<=($C28-Assumptions!$B$4+$D28)),$G28,0) -> 0 | M28: =IF(AND(($C28-Assumptions!$B$4+1)<=M$4,M$4<=($C28-Assumptions!$B$4+$D28)),$G28,0) -> 0 | N28: =IF(AND(($C28-Assumptions!$B$4+1)<=N$4,N$4<=($C28-Assumptions!$B$4+$D28)),$G28,0) -> 0 | O28: =IF(AND(($C28-Assumptions!$B$4+1)<=O$4,O$4<=($C28-Assumptions!$B$4+$D28)),$G28,0) -> 6492.3714
A29: Fencing - Y1 fleet | B29: {=TRANSPOSE('CapEx & Storage'!E21:L21)} -> 1184000 | C29: =Assumptions!$B$4 -> 2026 | D29: =Assumptions!$B$35 -> 10 | E29: =Assumptions!$B$36 -> 0.4 | F29: =B29*(1-E29) -> 710400 | G29: =F29/D29 -> 71040 | H29: =IF(AND(($C29-Assumptions!$B$4+1)<=H$4,H$4<=($C29-Assumptions!$B$4+$D29)),$G29,0) -> 71040 | I29: =IF(AND(($C29-Assumptions!$B$4+1)<=I$4,I$4<=($C29-Assumptions!$B$4+$D29)),$G29,0) -> 71040 | J29: =IF(AND(($C29-Assumptions!$B$4+1)<=J$4,J$4<=($C29-Assumptions!$B$4+$D29)),$G29,0) -> 71040 | K29: =IF(AND(($C29-Assumptions!$B$4+1)<=K$4,K$4<=($C29-Assumptions!$B$4+$D29)),$G29,0) -> 71040 | L29: =IF(AND(($C29-Assumptions!$B$4+1)<=L$4,L$4<=($C29-Assumptions!$B$4+$D29)),$G29,0) -> 71040 | M29: =IF(AND(($C29-Assumptions!$B$4+1)<=M$4,M$4<=($C29-Assumptions!$B$4+$D29)),$G29,0) -> 71040 | N29: =IF(AND(($C29-Assumptions!$B$4+1)<=N$4,N$4<=($C29-Assumptions!$B$4+$D29)),$G29,0) -> 71040 | O29: =IF(AND(($C29-Assumptions!$B$4+1)<=O$4,O$4<=($C29-Assumptions!$B$4+$D29)),$G29,0) -> 71040
A30: Fencing - Y2 additions | B30: 20400 | C30: =C29+1 -> 2027 | D30: =Assumptions!$B$35 -> 10 | E30: =Assumptions!$B$36 -> 0.4 | F30: =B30*(1-E30) -> 12240 | G30: =F30/D30 -> 1224 | H30: =IF(AND(($C30-Assumptions!$B$4+1)<=H$4,H$4<=($C30-Assumptions!$B$4+$D30)),$G30,0) -> 0 | I30: =IF(AND(($C30-Assumptions!$B$4+1)<=I$4,I$4<=($C30-Assumptions!$B$4+$D30)),$G30,0) -> 1224 | J30: =IF(AND(($C30-Assumptions!$B$4+1)<=J$4,J$4<=($C30-Assumptions!$B$4+$D30)),$G30,0) -> 1224 | K30: =IF(AND(($C30-Assumptions!$B$4+1)<=K$4,K$4<=($C30-Assumptions!$B$4+$D30)),$G30,0) -> 1224 | L30: =IF(AND(($C30-Assumptions!$B$4+1)<=L$4,L$4<=($C30-Assumptions!$B$4+$D30)),$G30,0) -> 1224 | M30: =IF(AND(($C30-Assumptions!$B$4+1)<=M$4,M$4<=($C30-Assumptions!$B$4+$D30)),$G30,0) -> 1224 | N30: =IF(AND(($C30-Assumptions!$B$4+1)<=N$4,N$4<=($C30-Assumptions!$B$4+$D30)),$G30,0) -> 1224 | O30: =IF(AND(($C30-Assumptions!$B$4+1)<=O$4,O$4<=($C30-Assumptions!$B$4+$D30)),$G30,0) -> 1224
A31: Fencing - Y3 additions | B31: 91555.2 | C31: =C30+1 -> 2028 | D31: =Assumptions!$B$35 -> 10 | E31: =Assumptions!$B$36 -> 0.4 | F31: =B31*(1-E31) -> 54933.12 | G31: =F31/D31 -> 5493.312 | H31: =IF(AND(($C31-Assumptions!$B$4+1)<=H$4,H$4<=($C31-Assumptions!$B$4+$D31)),$G31,0) -> 0 | I31: =IF(AND(($C31-Assumptions!$B$4+1)<=I$4,I$4<=($C31-Assumptions!$B$4+$D31)),$G31,0) -> 0 | J31: =IF(AND(($C31-Assumptions!$B$4+1)<=J$4,J$4<=($C31-Assumptions!$B$4+$D31)),$G31,0) -> 5493.312 | K31: =IF(AND(($C31-Assumptions!$B$4+1)<=K$4,K$4<=($C31-Assumptions!$B$4+$D31)),$G31,0) -> 5493.312 | L31: =IF(AND(($C31-Assumptions!$B$4+1)<=L$4,L$4<=($C31-Assumptions!$B$4+$D31)),$G31,0) -> 5493.312 | M31: =IF(AND(($C31-Assumptions!$B$4+1)<=M$4,M$4<=($C31-Assumptions!$B$4+$D31)),$G31,0) -> 5493.312 | N31: =IF(AND(($C31-Assumptions!$B$4+1)<=N$4,N$4<=($C31-Assumptions!$B$4+$D31)),$G31,0) -> 5493.312 | O31: =IF(AND(($C31-Assumptions!$B$4+1)<=O$4,O$4<=($C31-Assumptions!$B$4+$D31)),$G31,0) -> 5493.312
A32: Fencing - Y4 additions | B32: 89141.472 | C32: =C31+1 -> 2029 | D32: =Assumptions!$B$35 -> 10 | E32: =Assumptions!$B$36 -> 0.4 | F32: =B32*(1-E32) -> 53484.883 | G32: =F32/D32 -> 5348.4883 | H32: =IF(AND(($C32-Assumptions!$B$4+1)<=H$4,H$4<=($C32-Assumptions!$B$4+$D32)),$G32,0) -> 0 | I32: =IF(AND(($C32-Assumptions!$B$4+1)<=I$4,I$4<=($C32-Assumptions!$B$4+$D32)),$G32,0) -> 0 | J32: =IF(AND(($C32-Assumptions!$B$4+1)<=J$4,J$4<=($C32-Assumptions!$B$4+$D32)),$G32,0) -> 0 | K32: =IF(AND(($C32-Assumptions!$B$4+1)<=K$4,K$4<=($C32-Assumptions!$B$4+$D32)),$G32,0) -> 5348.4883 | L32: =IF(AND(($C32-Assumptions!$B$4+1)<=L$4,L$4<=($C32-Assumptions!$B$4+$D32)),$G32,0) -> 5348.4883 | M32: =IF(AND(($C32-Assumptions!$B$4+1)<=M$4,M$4<=($C32-Assumptions!$B$4+$D32)),$G32,0) -> 5348.4883 | N32: =IF(AND(($C32-Assumptions!$B$4+1)<=N$4,N$4<=($C32-Assumptions!$B$4+$D32)),$G32,0) -> 5348.4883 | O32: =IF(AND(($C32-Assumptions!$B$4+1)<=O$4,O$4<=($C32-Assumptions!$B$4+$D32)),$G32,0) -> 5348.4883
A33: Fencing - Y5 additions | B33: 64945.93 | C33: =C32+1 -> 2030 | D33: =Assumptions!$B$35 -> 10 | E33: =Assumptions!$B$36 -> 0.4 | F33: =B33*(1-E33) -> 38967.558 | G33: =F33/D33 -> 3896.7558 | H33: =IF(AND(($C33-Assumptions!$B$4+1)<=H$4,H$4<=($C33-Assumptions!$B$4+$D33)),$G33,0) -> 0 | I33: =IF(AND(($C33-Assumptions!$B$4+1)<=I$4,I$4<=($C33-Assumptions!$B$4+$D33)),$G33,0) -> 0 | J33: =IF(AND(($C33-Assumptions!$B$4+1)<=J$4,J$4<=($C33-Assumptions!$B$4+$D33)),$G33,0) -> 0 | K33: =IF(AND(($C33-Assumptions!$B$4+1)<=K$4,K$4<=($C33-Assumptions!$B$4+$D33)),$G33,0) -> 0 | L33: =IF(AND(($C33-Assumptions!$B$4+1)<=L$4,L$4<=($C33-Assumptions!$B$4+$D33)),$G33,0) -> 3896.7558 | M33: =IF(AND(($C33-Assumptions!$B$4+1)<=M$4,M$4<=($C33-Assumptions!$B$4+$D33)),$G33,0) -> 3896.7558 | N33: =IF(AND(($C33-Assumptions!$B$4+1)<=N$4,N$4<=($C33-Assumptions!$B$4+$D33)),$G33,0) -> 3896.7558 | O33: =IF(AND(($C33-Assumptions!$B$4+1)<=O$4,O$4<=($C33-Assumptions!$B$4+$D33)),$G33,0) -> 3896.7558
A34: Fencing - Y6 additions | B34: 128073.37 | C34: =C33+1 -> 2031 | D34: =Assumptions!$B$35 -> 10 | E34: =Assumptions!$B$36 -> 0.4 | F34: =B34*(1-E34) -> 76844.024 | G34: =F34/D34 -> 7684.4024 | L34: =IF(AND(($C34-Assumptions!$B$4+1)<=L$4,L$4<=($C34-Assumptions!$B$4+$D34)),$G34,0) -> 0 | M34: =IF(AND(($C34-Assumptions!$B$4+1)<=M$4,M$4<=($C34-Assumptions!$B$4+$D34)),$G34,0) -> 7684.4024 | N34: =IF(AND(($C34-Assumptions!$B$4+1)<=N$4,N$4<=($C34-Assumptions!$B$4+$D34)),$G34,0) -> 7684.4024 | O34: =IF(AND(($C34-Assumptions!$B$4+1)<=O$4,O$4<=($C34-Assumptions!$B$4+$D34)),$G34,0) -> 7684.4024
A35: Fencing - Y7 additions | B35: 207213.89 | C35: =C34+1 -> 2032 | D35: =Assumptions!$B$35 -> 10 | E35: =Assumptions!$B$36 -> 0.4 | F35: =B35*(1-E35) -> 124328.33 | G35: =F35/D35 -> 12432.833 | L35: =IF(AND(($C35-Assumptions!$B$4+1)<=L$4,L$4<=($C35-Assumptions!$B$4+$D35)),$G35,0) -> 0 | M35: =IF(AND(($C35-Assumptions!$B$4+1)<=M$4,M$4<=($C35-Assumptions!$B$4+$D35)),$G35,0) -> 0 | N35: =IF(AND(($C35-Assumptions!$B$4+1)<=N$4,N$4<=($C35-Assumptions!$B$4+$D35)),$G35,0) -> 12432.833 | O35: =IF(AND(($C35-Assumptions!$B$4+1)<=O$4,O$4<=($C35-Assumptions!$B$4+$D35)),$G35,0) -> 12432.833
A36: Fencing - Y8 additions | B36: 68921.14 | C36: =C35+1 -> 2033 | D36: =Assumptions!$B$35 -> 10 | E36: =Assumptions!$B$36 -> 0.4 | F36: =B36*(1-E36) -> 41352.684 | G36: =F36/D36 -> 4135.2684 | L36: =IF(AND(($C36-Assumptions!$B$4+1)<=L$4,L$4<=($C36-Assumptions!$B$4+$D36)),$G36,0) -> 0 | M36: =IF(AND(($C36-Assumptions!$B$4+1)<=M$4,M$4<=($C36-Assumptions!$B$4+$D36)),$G36,0) -> 0 | N36: =IF(AND(($C36-Assumptions!$B$4+1)<=N$4,N$4<=($C36-Assumptions!$B$4+$D36)),$G36,0) -> 0 | O36: =IF(AND(($C36-Assumptions!$B$4+1)<=O$4,O$4<=($C36-Assumptions!$B$4+$D36)),$G36,0) -> 4135.2684
A37: Flooring - Y1 fleet | B37: {=TRANSPOSE('CapEx & Storage'!E22:L22)} -> 370000 | C37: =Assumptions!$B$4 -> 2026 | D37: =Assumptions!$B$39 -> 10 | E37: =Assumptions!$B$40 -> 0.1 | F37: =B37*(1-E37) -> 333000 | G37: =F37/D37 -> 33300 | H37: =IF(AND(($C37-Assumptions!$B$4+1)<=H$4,H$4<=($C37-Assumptions!$B$4+$D37)),$G37,0) -> 33300 | I37: =IF(AND(($C37-Assumptions!$B$4+1)<=I$4,I$4<=($C37-Assumptions!$B$4+$D37)),$G37,0) -> 33300 | J37: =IF(AND(($C37-Assumptions!$B$4+1)<=J$4,J$4<=($C37-Assumptions!$B$4+$D37)),$G37,0) -> 33300 | K37: =IF(AND(($C37-Assumptions!$B$4+1)<=K$4,K$4<=($C37-Assumptions!$B$4+$D37)),$G37,0) -> 33300 | L37: =IF(AND(($C37-Assumptions!$B$4+1)<=L$4,L$4<=($C37-Assumptions!$B$4+$D37)),$G37,0) -> 33300 | M37: =IF(AND(($C37-Assumptions!$B$4+1)<=M$4,M$4<=($C37-Assumptions!$B$4+$D37)),$G37,0) -> 33300 | N37: =IF(AND(($C37-Assumptions!$B$4+1)<=N$4,N$4<=($C37-Assumptions!$B$4+$D37)),$G37,0) -> 33300 | O37: =IF(AND(($C37-Assumptions!$B$4+1)<=O$4,O$4<=($C37-Assumptions!$B$4+$D37)),$G37,0) -> 33300
A38: Flooring - Y2 additions | B38: 0 | C38: =C37+1 -> 2027 | D38: =Assumptions!$B$39 -> 10 | E38: =Assumptions!$B$40 -> 0.1 | F38: =B38*(1-E38) -> 0 | G38: =F38/D38 -> 0 | H38: =IF(AND(($C38-Assumptions!$B$4+1)<=H$4,H$4<=($C38-Assumptions!$B$4+$D38)),$G38,0) -> 0 | I38: =IF(AND(($C38-Assumptions!$B$4+1)<=I$4,I$4<=($C38-Assumptions!$B$4+$D38)),$G38,0) -> 0 | J38: =IF(AND(($C38-Assumptions!$B$4+1)<=J$4,J$4<=($C38-Assumptions!$B$4+$D38)),$G38,0) -> 0 | K38: =IF(AND(($C38-Assumptions!$B$4+1)<=K$4,K$4<=($C38-Assumptions!$B$4+$D38)),$G38,0) -> 0 | L38: =IF(AND(($C38-Assumptions!$B$4+1)<=L$4,L$4<=($C38-Assumptions!$B$4+$D38)),$G38,0) -> 0 | M38: =IF(AND(($C38-Assumptions!$B$4+1)<=M$4,M$4<=($C38-Assumptions!$B$4+$D38)),$G38,0) -> 0 | N38: =IF(AND(($C38-Assumptions!$B$4+1)<=N$4,N$4<=($C38-Assumptions!$B$4+$D38)),$G38,0) -> 0 | O38: =IF(AND(($C38-Assumptions!$B$4+1)<=O$4,O$4<=($C38-Assumptions!$B$4+$D38)),$G38,0) -> 0
A39: Flooring - Y3 additions | B39: 52020 | C39: =C38+1 -> 2028 | D39: =Assumptions!$B$39 -> 10 | E39: =Assumptions!$B$40 -> 0.1 | F39: =B39*(1-E39) -> 46818 | G39: =F39/D39 -> 4681.8 | H39: =IF(AND(($C39-Assumptions!$B$4+1)<=H$4,H$4<=($C39-Assumptions!$B$4+$D39)),$G39,0) -> 0 | I39: =IF(AND(($C39-Assumptions!$B$4+1)<=I$4,I$4<=($C39-Assumptions!$B$4+$D39)),$G39,0) -> 0 | J39: =IF(AND(($C39-Assumptions!$B$4+1)<=J$4,J$4<=($C39-Assumptions!$B$4+$D39)),$G39,0) -> 4681.8 | K39: =IF(AND(($C39-Assumptions!$B$4+1)<=K$4,K$4<=($C39-Assumptions!$B$4+$D39)),$G39,0) -> 4681.8 | L39: =IF(AND(($C39-Assumptions!$B$4+1)<=L$4,L$4<=($C39-Assumptions!$B$4+$D39)),$G39,0) -> 4681.8 | M39: =IF(AND(($C39-Assumptions!$B$4+1)<=M$4,M$4<=($C39-Assumptions!$B$4+$D39)),$G39,0) -> 4681.8 | N39: =IF(AND(($C39-Assumptions!$B$4+1)<=N$4,N$4<=($C39-Assumptions!$B$4+$D39)),$G39,0) -> 4681.8 | O39: =IF(AND(($C39-Assumptions!$B$4+1)<=O$4,O$4<=($C39-Assumptions!$B$4+$D39)),$G39,0) -> 4681.8
A40: Flooring - Y4 additions | B40: 21224.16 | C40: =C39+1 -> 2029 | D40: =Assumptions!$B$39 -> 10 | E40: =Assumptions!$B$40 -> 0.1 | F40: =B40*(1-E40) -> 19101.744 | G40: =F40/D40 -> 1910.1744 | H40: =IF(AND(($C40-Assumptions!$B$4+1)<=H$4,H$4<=($C40-Assumptions!$B$4+$D40)),$G40,0) -> 0 | I40: =IF(AND(($C40-Assumptions!$B$4+1)<=I$4,I$4<=($C40-Assumptions!$B$4+$D40)),$G40,0) -> 0 | J40: =IF(AND(($C40-Assumptions!$B$4+1)<=J$4,J$4<=($C40-Assumptions!$B$4+$D40)),$G40,0) -> 0 | K40: =IF(AND(($C40-Assumptions!$B$4+1)<=K$4,K$4<=($C40-Assumptions!$B$4+$D40)),$G40,0) -> 1910.1744 | L40: =IF(AND(($C40-Assumptions!$B$4+1)<=L$4,L$4<=($C40-Assumptions!$B$4+$D40)),$G40,0) -> 1910.1744 | M40: =IF(AND(($C40-Assumptions!$B$4+1)<=M$4,M$4<=($C40-Assumptions!$B$4+$D40)),$G40,0) -> 1910.1744 | N40: =IF(AND(($C40-Assumptions!$B$4+1)<=N$4,N$4<=($C40-Assumptions!$B$4+$D40)),$G40,0) -> 1910.1744 | O40: =IF(AND(($C40-Assumptions!$B$4+1)<=O$4,O$4<=($C40-Assumptions!$B$4+$D40)),$G40,0) -> 1910.1744
A41: Flooring - Y5 additions | B41: 20566.211 | C41: =C40+1 -> 2030 | D41: =Assumptions!$B$39 -> 10 | E41: =Assumptions!$B$40 -> 0.1 | F41: =B41*(1-E41) -> 18509.59 | G41: =F41/D41 -> 1850.959 | H41: =IF(AND(($C41-Assumptions!$B$4+1)<=H$4,H$4<=($C41-Assumptions!$B$4+$D41)),$G41,0) -> 0 | I41: =IF(AND(($C41-Assumptions!$B$4+1)<=I$4,I$4<=($C41-Assumptions!$B$4+$D41)),$G41,0) -> 0 | J41: =IF(AND(($C41-Assumptions!$B$4+1)<=J$4,J$4<=($C41-Assumptions!$B$4+$D41)),$G41,0) -> 0 | K41: =IF(AND(($C41-Assumptions!$B$4+1)<=K$4,K$4<=($C41-Assumptions!$B$4+$D41)),$G41,0) -> 0 | L41: =IF(AND(($C41-Assumptions!$B$4+1)<=L$4,L$4<=($C41-Assumptions!$B$4+$D41)),$G41,0) -> 1850.959 | M41: =IF(AND(($C41-Assumptions!$B$4+1)<=M$4,M$4<=($C41-Assumptions!$B$4+$D41)),$G41,0) -> 1850.959 | N41: =IF(AND(($C41-Assumptions!$B$4+1)<=N$4,N$4<=($C41-Assumptions!$B$4+$D41)),$G41,0) -> 1850.959 | O41: =IF(AND(($C41-Assumptions!$B$4+1)<=O$4,O$4<=($C41-Assumptions!$B$4+$D41)),$G41,0) -> 1850.959
A42: Flooring - Y6 additions | B42: 23185.697 | C42: =C41+1 -> 2031 | D42: =Assumptions!$B$39 -> 10 | E42: =Assumptions!$B$40 -> 0.1 | F42: =B42*(1-E42) -> 20867.127 | G42: =F42/D42 -> 2086.7127 | H42: =IF(AND(($C42-Assumptions!$B$4+1)<=H$4,H$4<=($C42-Assumptions!$B$4+$D42)),$G42,0) -> 0 | I42: =IF(AND(($C42-Assumptions!$B$4+1)<=I$4,I$4<=($C42-Assumptions!$B$4+$D42)),$G42,0) -> 0 | J42: =IF(AND(($C42-Assumptions!$B$4+1)<=J$4,J$4<=($C42-Assumptions!$B$4+$D42)),$G42,0) -> 0 | K42: =IF(AND(($C42-Assumptions!$B$4+1)<=K$4,K$4<=($C42-Assumptions!$B$4+$D42)),$G42,0) -> 0 | L42: =IF(AND(($C42-Assumptions!$B$4+1)<=L$4,L$4<=($C42-Assumptions!$B$4+$D42)),$G42,0) -> 0 | M42: =IF(AND(($C42-Assumptions!$B$4+1)<=M$4,M$4<=($C42-Assumptions!$B$4+$D42)),$G42,0) -> 2086.7127 | N42: =IF(AND(($C42-Assumptions!$B$4+1)<=N$4,N$4<=($C42-Assumptions!$B$4+$D42)),$G42,0) -> 2086.7127 | O42: =IF(AND(($C42-Assumptions!$B$4+1)<=O$4,O$4<=($C42-Assumptions!$B$4+$D42)),$G42,0) -> 2086.7127
A43: Flooring - Y7 additions | B43: 45046.497 | C43: =C42+1 -> 2032 | D43: =Assumptions!$B$39 -> 10 | E43: =Assumptions!$B$40 -> 0.1 | F43: =B43*(1-E43) -> 40541.847 | G43: =F43/D43 -> 4054.1847 | H43: =IF(AND(($C43-Assumptions!$B$4+1)<=H$4,H$4<=($C43-Assumptions!$B$4+$D43)),$G43,0) -> 0 | I43: =IF(AND(($C43-Assumptions!$B$4+1)<=I$4,I$4<=($C43-Assumptions!$B$4+$D43)),$G43,0) -> 0 | J43: =IF(AND(($C43-Assumptions!$B$4+1)<=J$4,J$4<=($C43-Assumptions!$B$4+$D43)),$G43,0) -> 0 | K43: =IF(AND(($C43-Assumptions!$B$4+1)<=K$4,K$4<=($C43-Assumptions!$B$4+$D43)),$G43,0) -> 0 | L43: =IF(AND(($C43-Assumptions!$B$4+1)<=L$4,L$4<=($C43-Assumptions!$B$4+$D43)),$G43,0) -> 0 | M43: =IF(AND(($C43-Assumptions!$B$4+1)<=M$4,M$4<=($C43-Assumptions!$B$4+$D43)),$G43,0) -> 0 | N43: =IF(AND(($C43-Assumptions!$B$4+1)<=N$4,N$4<=($C43-Assumptions!$B$4+$D43)),$G43,0) -> 4054.1847 | O43: =IF(AND(($C43-Assumptions!$B$4+1)<=O$4,O$4<=($C43-Assumptions!$B$4+$D43)),$G43,0) -> 4054.1847
A44: Flooring - Y8 additions | B44: 22973.713 | C44: =C43+1 -> 2033 | D44: =Assumptions!$B$39 -> 10 | E44: =Assumptions!$B$40 -> 0.1 | F44: =B44*(1-E44) -> 20676.342 | G44: =F44/D44 -> 2067.6342 | H44: =IF(AND(($C44-Assumptions!$B$4+1)<=H$4,H$4<=($C44-Assumptions!$B$4+$D44)),$G44,0) -> 0 | I44: =IF(AND(($C44-Assumptions!$B$4+1)<=I$4,I$4<=($C44-Assumptions!$B$4+$D44)),$G44,0) -> 0 | J44: =IF(AND(($C44-Assumptions!$B$4+1)<=J$4,J$4<=($C44-Assumptions!$B$4+$D44)),$G44,0) -> 0 | K44: =IF(AND(($C44-Assumptions!$B$4+1)<=K$4,K$4<=($C44-Assumptions!$B$4+$D44)),$G44,0) -> 0 | L44: =IF(AND(($C44-Assumptions!$B$4+1)<=L$4,L$4<=($C44-Assumptions!$B$4+$D44)),$G44,0) -> 0 | M44: =IF(AND(($C44-Assumptions!$B$4+1)<=M$4,M$4<=($C44-Assumptions!$B$4+$D44)),$G44,0) -> 0 | N44: =IF(AND(($C44-Assumptions!$B$4+1)<=N$4,N$4<=($C44-Assumptions!$B$4+$D44)),$G44,0) -> 0 | O44: =IF(AND(($C44-Assumptions!$B$4+1)<=O$4,O$4<=($C44-Assumptions!$B$4+$D44)),$G44,0) -> 2067.6342
A46: TOTAL ANNUAL DEPRECIATION (AED) | H46: =SUM(H5:H41) -> 884350 | I46: =SUM(I5:I41) -> 969697.48 | J46: =SUM(J5:J41) -> 1062884 | K46: =SUM(K5:K41) -> 1174414.9 | L46: =SUM(L5:L41) -> 1278547 | M46: =SUM(M5:M41) -> 1307818.4 | N46: =SUM(N5:N41) -> 1340810.4 | O46: =SUM(O5:O41) -> 1364303.4
A48: NET BOOK VALUE (end of year)
A49: Cumulative gross CapEx | H49: =SUM(B5,B13,B21,B29,B37) -> 9942100 | I49: =SUM(B5:B6,B13:B14,B21:B22,B29:B30,B37:B38) -> 10841434 | J49: =SUM(B5:B7,B13:B15,B21:B23,B29:B31,B37:B39) -> 11882042 | K49: =SUM(B5:B8,B13:B16,B21:B24,B29:B32,B37:B40) -> 13112301 | L49: =SUM(B5:B9,B13:B17,B21:B25,B29:B33,B37:B41) -> 14200361 | M49: =SUM(B5:B10,B13:B18,B21:B26,B29:B34,B37:B42) -> 14681961 | N49: =SUM(B5:B11,B13:B19,B21:B27,B29:B35,B37:B43) -> 15246844 | O49: =SUM(_xlfn.ANCHORARRAY(B5),_xlfn.ANCHORARRAY(B13),_xlfn.ANCHORARRAY(B21),_xlfn.ANCHORARRAY(B29),_xlfn.ANCHORARRAY(B37)) -> 15630735
A50: Accumulated depreciation | H50: =SUM($H$46:H46) -> 884350 | I50: =SUM($H$46:I46) -> 1854047.5 | J50: =SUM($H$46:J46) -> 2916931.5 | K50: =SUM($H$46:K46) -> 4091346.4 | L50: =SUM($H$46:L46) -> 5369893.4 | M50: =SUM($H$46:M46) -> 6677711.8 | N50: =SUM($H$46:N46) -> 8018522.2 | O50: =SUM($H$46:O46) -> 9382825.6
A51: NET BOOK VALUE (AED) | H51: =H49-H50 -> 9057750 | I51: =I49-I50 -> 8987386.5 | J51: =J49-J50 -> 8965110.6 | K51: =K49-K50 -> 9020954.1 | L51: =L49-L50 -> 8830467.9 | M51: =M49-M50 -> 8004249.6 | N51: =N49-N50 -> 7228322.2 | O51: =O49-O50 -> 6247909.6

Sheet Revenue Projection
A1: DEMAND PROJECTIONS - EVENT-BASED REVENUE DRIVERS
A2: Revenue = expected asset-days deployed × asset-day rate | Growth applied as % p.a. from Year 2.
C3: 1 | D3: 2 | E3: 3 | F3: 4 | G3: 5 | H3: 6 | I3: 7 | J3: 8
B4: Driver / Source | C4: Year 1 | D4: Year 2 | E4: Year 3 | F4: Year 4 | G4: Year 5 | H4: Year 6 | I4: Year 7 | J4: Year 8 | K4: 8-Yr Total
A5: PROJECTED EVENTS
A6: Number of target events | B6: Event pipeline / Targetable events | C6: =Assumptions!B9 -> 12 | D6: =ROUND(C6*(1+Assumptions!$B$15),0) -> 13 | E6: =ROUND(D6*(1+Assumptions!$B$15),0) -> 14 | F6: =ROUND(E6*(1+Assumptions!$B$15),0) -> 15 | G6: =ROUND(F6*(1+Assumptions!$B$15),0) -> 17 | H6: =ROUND(G6*(1+Assumptions!$B$15),0) -> 19 | I6: =ROUND(H6*(1+Assumptions!$B$15),0) -> 21 | J6: =ROUND(I6*(1+Assumptions!$B$15),0) -> 23
A7: Signed events (mean) | C7: =_xlfn.XLOOKUP(C$3,Simulation!$A$2:$A$41,Simulation!$J$2:$J$41,,0,1) -> 5.9987183 | D7: =_xlfn.XLOOKUP(D$3,Simulation!$A$2:$A$41,Simulation!$J$2:$J$41,,0,1) -> 6.4988317 | E7: =_xlfn.XLOOKUP(E$3,Simulation!$A$2:$A$41,Simulation!$J$2:$J$41,,0,1) -> 7.0027966 | F7: =_xlfn.XLOOKUP(F$3,Simulation!$A$2:$A$41,Simulation!$J$2:$J$41,,0,1) -> 7.4983177 | G7: =_xlfn.XLOOKUP(G$3,Simulation!$A$2:$A$41,Simulation!$J$2:$J$41,,0,1) -> 8.5018215 | H7: =_xlfn.XLOOKUP(H$3,Simulation!$A$2:$A$41,Simulation!$J$2:$J$41,,0,1) -> 9.5001287 | I7: =_xlfn.XLOOKUP(I$3,Simulation!$A$2:$A$41,Simulation!$J$2:$J$41,,0,1) -> 10.496984 | J7: =_xlfn.XLOOKUP(J$3,Simulation!$A$2:$A$41,Simulation!$J$2:$J$41,,0,1) -> 11.500706
A8: Signed events (median) | C8: =_xlfn.XLOOKUP(C$3,Simulation!$A$2:$A$41,Simulation!$K$2:$K$41,,0,1) -> 6 | D8: =_xlfn.XLOOKUP(D$3,Simulation!$A$2:$A$41,Simulation!$K$2:$K$41,,0,1) -> 6 | E8: =_xlfn.XLOOKUP(E$3,Simulation!$A$2:$A$41,Simulation!$K$2:$K$41,,0,1) -> 7 | F8: =_xlfn.XLOOKUP(F$3,Simulation!$A$2:$A$41,Simulation!$K$2:$K$41,,0,1) -> 7 | G8: =_xlfn.XLOOKUP(G$3,Simulation!$A$2:$A$41,Simulation!$K$2:$K$41,,0,1) -> 9 | H8: =_xlfn.XLOOKUP(H$3,Simulation!$A$2:$A$41,Simulation!$K$2:$K$41,,0,1) -> 9 | I8: =_xlfn.XLOOKUP(I$3,Simulation!$A$2:$A$41,Simulation!$K$2:$K$41,,0,1) -> 10 | J8: =_xlfn.XLOOKUP(J$3,Simulation!$A$2:$A$41,Simulation!$K$2:$K$41,,0,1) -> 11.5
A10: CABIN
A11: Fleet (end of year) | C11: ='CapEx & Storage'!E45 -> 73 | D11: ='CapEx & Storage'!F45 -> 80 | E11: ='CapEx & Storage'!G45 -> 88 | F11: ='CapEx & Storage'!H45 -> 97 | G11: ='CapEx & Storage'!I45 -> 107 | H11: ='CapEx & Storage'!J45 -> 107 | I11: ='CapEx & Storage'!K45 -> 107 | J11: ='CapEx & Storage'!L45 -> 107
A12: Expected cabin-days deployed | C12: {=INDEX(Simulation!$I$2:$I$41,MATCH(1,(Simulation!$C$2:$C$41="Cabins")*(Simulation!$A$2:$A$41=C$3),0))} -> 2778 | D12: {=INDEX(Simulation!$I$2:$I$41,MATCH(1,(Simulation!$C$2:$C$41="Cabins")*(Simulation!$A$2:$A$41=D$3),0))} -> 2941 | E12: {=INDEX(Simulation!$I$2:$I$41,MATCH(1,(Simulation!$C$2:$C$41="Cabins")*(Simulation!$A$2:$A$41=E$3),0))} -> 3105 | F12: {=INDEX(Simulation!$I$2:$I$41,MATCH(1,(Simulation!$C$2:$C$41="Cabins")*(Simulation!$A$2:$A$41=F$3),0))} -> 3267 | G12: {=INDEX(Simulation!$I$2:$I$41,MATCH(1,(Simulation!$C$2:$C$41="Cabins")*(Simulation!$A$2:$A$41=G$3),0))} -> 3592 | H12: {=INDEX(Simulation!$I$2:$I$41,MATCH(1,(Simulation!$C$2:$C$41="Cabins")*(Simulation!$A$2:$A$41=H$3),0))} -> 3915 | I12: {=INDEX(Simulation!$I$2:$I$41,MATCH(1,(Simulation!$C$2:$C$41="Cabins")*(Simulation!$A$2:$A$41=I$3),0))} -> 4241 | J12: {=INDEX(Simulation!$I$2:$I$41,MATCH(1,(Simulation!$C$2:$C$41="Cabins")*(Simulation!$A$2:$A$41=J$3),0))} -> 4567
A13: Revenue per cabin-days deployed | C13: =Assumptions!$B$18 -> 350 | D13: =Assumptions!$B$18 -> 350 | E13: =Assumptions!$B$18 -> 350 | F13: =Assumptions!$B$18 -> 350 | G13: =Assumptions!$B$18 -> 350 | H13: =Assumptions!$B$18 -> 350 | I13: =Assumptions!$B$18 -> 350 | J13: =Assumptions!$B$18 -> 350
A14: Time utilization | B14: asset-days used ÷ asset-days available | C14: =C12/(SUM('CapEx & Storage'!$E$12:E12)*360) -> 0.096458333 | D14: =D12/(SUM('CapEx & Storage'!$E$12:F12)*360) -> 0.098427041 | E14: =E12/(SUM('CapEx & Storage'!$E$12:G12)*360) -> 0.095833333 | F14: =F12/(SUM('CapEx & Storage'!$E$12:H12)*360) -> 0.093556701 | G14: =G12/(SUM('CapEx & Storage'!$E$12:I12)*360) -> 0.099777778 | H14: =H12/(SUM('CapEx & Storage'!$E$12:J12)*360) -> 0.099770642 | I14: =I12/(SUM('CapEx & Storage'!$E$12:K12)*360) -> 0.098171296 | J14: =J12/(SUM('CapEx & Storage'!$E$12:L12)*360) -> 0.099890639
A15: Cabin rental revenue | B15: Exp. cabin-days deployed x revenue per cabin per day | C15: =C12*C13 -> 972300 | D15: =D12*D13 -> 1029350 | E15: =E12*E13 -> 1086750 | F15: =F12*F13 -> 1143450 | G15: =G12*G13 -> 1257200 | H15: =H12*H13 -> 1370250 | I15: =I12*I13 -> 1484350 | J15: =J12*J13 -> 1598450 | K15: =SUM(C15:J15) -> 9942100
A16: BUGGIES
A17: Fleet (end of year) | C17: ='CapEx & Storage'!E6 -> 26 | D17: =C17+'CapEx & Storage'!F6 -> 54 | E17: =D17+'CapEx & Storage'!G6 -> 84 | F17: =E17+'CapEx & Storage'!H6 -> 118 | G17: =F17+'CapEx & Storage'!I6 -> 152 | H17: =G17+'CapEx & Storage'!J6 -> 190 | I17: =H17+'CapEx & Storage'!K6 -> 232 | J17: =I17+'CapEx & Storage'!L6 -> 278
A18: Expected buggy-days deployed | C18: {=INDEX(Simulation!$I$2:$I$41,MATCH(1,(Simulation!$C$2:$C$41="Buggies")*(Simulation!$A$2:$A$41=C$3),0))} -> 1570 | D18: {=INDEX(Simulation!$I$2:$I$41,MATCH(1,(Simulation!$C$2:$C$41="Buggies")*(Simulation!$A$2:$A$41=D$3),0))} -> 1660 | E18: {=INDEX(Simulation!$I$2:$I$41,MATCH(1,(Simulation!$C$2:$C$41="Buggies")*(Simulation!$A$2:$A$41=E$3),0))} -> 1732 | F18: {=INDEX(Simulation!$I$2:$I$41,MATCH(1,(Simulation!$C$2:$C$41="Buggies")*(Simulation!$A$2:$A$41=F$3),0))} -> 1822 | G18: {=INDEX(Simulation!$I$2:$I$41,MATCH(1,(Simulation!$C$2:$C$41="Buggies")*(Simulation!$A$2:$A$41=G$3),0))} -> 1960 | H18: {=INDEX(Simulation!$I$2:$I$41,MATCH(1,(Simulation!$C$2:$C$41="Buggies")*(Simulation!$A$2:$A$41=H$3),0))} -> 2116 | I18: {=INDEX(Simulation!$I$2:$I$41,MATCH(1,(Simulation!$C$2:$C$41="Buggies")*(Simulation!$A$2:$A$41=I$3),0))} -> 2266 | J18: {=INDEX(Simulation!$I$2:$I$41,MATCH(1,(Simulation!$C$2:$C$41="Buggies")*(Simulation!$A$2:$A$41=J$3),0))} -> 2416
A19: Revenue per buggy-days deployed | C19: =Assumptions!$B$19 -> 700 | D19: =Assumptions!$B$19 -> 700 | E19: =Assumptions!$B$19 -> 700 | F19: =Assumptions!$B$19 -> 700 | G19: =Assumptions!$B$19 -> 700 | H19: =Assumptions!$B$19 -> 700 | I19: =Assumptions!$B$19 -> 700 | J19: =Assumptions!$B$19 -> 700
A20: Time utilization | B20: asset-days used ÷ asset-days available | C20: =C18/(SUM('CapEx & Storage'!$E$13:E13)*360) -> 0.16773504 | D20: =D18/(SUM('CapEx & Storage'!$E$13:F13)*360) -> 0.16468254 | E20: =E18/(SUM('CapEx & Storage'!$E$13:G13)*360) -> 0.16037037 | F20: =F18/(SUM('CapEx & Storage'!$E$13:H13)*360) -> 0.14885621 | G20: =G18/(SUM('CapEx & Storage'!$E$13:I13)*360) -> 0.16013072 | H20: =H18/(SUM('CapEx & Storage'!$E$13:J13)*360) -> 0.15467836 | I20: =I18/(SUM('CapEx & Storage'!$E$13:K13)*360) -> 0.14986772 | J20: =J18/(SUM('CapEx & Storage'!$E$13:L13)*360) -> 0.14589372
A21: Buggies rental revenue | B21: Exp. buggy-days deployed x revenue per buggy per day | C21: =C19*C18 -> 1099000 | D21: =D19*D18 -> 1162000 | E21: =E19*E18 -> 1212400 | F21: =F19*F18 -> 1275400 | G21: =G19*G18 -> 1372000 | H21: =H19*H18 -> 1481200 | I21: =I19*I18 -> 1586200 | J21: =J19*J18 -> 1691200 | K21: =SUM(C21:J21) -> 10879400
A22: BARRIERS
A23: Fleet (end of year) | C23: ='CapEx & Storage'!E7 -> 2300 | D23: =C23+'CapEx & Storage'!F7 -> 4708 | E23: =D23+'CapEx & Storage'!G7 -> 7452 | F23: =E23+'CapEx & Storage'!H7 -> 10402 | G23: =F23+'CapEx & Storage'!I7 -> 13496 | H23: =G23+'CapEx & Storage'!J7 -> 17054 | I23: =H23+'CapEx & Storage'!K7 -> 21004 | J23: =I23+'CapEx & Storage'!L7 -> 25268
A24: Expected barrier-days deployed | B24: monthly slab billing | C24: {=INDEX(Simulation!$I$2:$I$41,MATCH(1,(Simulation!$C$2:$C$41="Barriers")*(Simulation!$A$2:$A$41=C$3),0))} -> 124560 | D24: {=INDEX(Simulation!$I$2:$I$41,MATCH(1,(Simulation!$C$2:$C$41="Barriers")*(Simulation!$A$2:$A$41=D$3),0))} -> 132060 | E24: {=INDEX(Simulation!$I$2:$I$41,MATCH(1,(Simulation!$C$2:$C$41="Barriers")*(Simulation!$A$2:$A$41=E$3),0))} -> 140280 | F24: {=INDEX(Simulation!$I$2:$I$41,MATCH(1,(Simulation!$C$2:$C$41="Barriers")*(Simulation!$A$2:$A$41=F$3),0))} -> 147060 | G24: {=INDEX(Simulation!$I$2:$I$41,MATCH(1,(Simulation!$C$2:$C$41="Barriers")*(Simulation!$A$2:$A$41=G$3),0))} -> 162780 | H24: {=INDEX(Simulation!$I$2:$I$41,MATCH(1,(Simulation!$C$2:$C$41="Barriers")*(Simulation!$A$2:$A$41=H$3),0))} -> 177420 | I24: {=INDEX(Simulation!$I$2:$I$41,MATCH(1,(Simulation!$C$2:$C$41="Barriers")*(Simulation!$A$2:$A$41=I$3),0))} -> 192420 | J24: {=INDEX(Simulation!$I$2:$I$41,MATCH(1,(Simulation!$C$2:$C$41="Barriers")*(Simulation!$A$2:$A$41=J$3),0))} -> 207780
A25: Revenue per barrier-days deployed | C25: =Assumptions!$B$20 -> 0.4 | D25: =Assumptions!$B$20 -> 0.4 | E25: =Assumptions!$B$20 -> 0.4 | F25: =Assumptions!$B$20 -> 0.4 | G25: =Assumptions!$B$20 -> 0.4 | H25: =Assumptions!$B$20 -> 0.4 | I25: =Assumptions!$B$20 -> 0.4 | J25: =Assumptions!$B$20 -> 0.4
A26: Time utilization | B26: asset-days used ÷ asset-days available | C26: =C24/(SUM('CapEx & Storage'!$E$14:E14)*360) -> 0.15043478 | D26: =D24/(SUM('CapEx & Storage'!$E$14:F14)*360) -> 0.15233942 | E26: =E24/(SUM('CapEx & Storage'!$E$14:G14)*360) -> 0.1420068 | F26: =F24/(SUM('CapEx & Storage'!$E$14:H14)*360) -> 0.13847458 | G26: =G24/(SUM('CapEx & Storage'!$E$14:I14)*360) -> 0.14614307 | H26: =H24/(SUM('CapEx & Storage'!$E$14:J14)*360) -> 0.13851415 | I26: =I24/(SUM('CapEx & Storage'!$E$14:K14)*360) -> 0.13531646 | J26: =J24/(SUM('CapEx & Storage'!$E$14:L14)*360) -> 0.13535804
A27: Barriers rental revenue | B27: Exp. barrier-days deployed x revenue per barrier per day | C27: =C25*C24 -> 49824 | D27: =D25*D24 -> 52824 | E27: =E25*E24 -> 56112 | F27: =F25*F24 -> 58824 | G27: =G25*G24 -> 65112 | H27: =H25*H24 -> 70968 | I27: =I25*I24 -> 76968 | J27: =J25*J24 -> 83112 | K27: =SUM(C27:J27) -> 513744
A28: FENCING
A29: Fleet (end of year) | C29: ='CapEx & Storage'!E8 -> 2960 | D29: =C29+'CapEx & Storage'!F8 -> 5970 | E29: =D29+'CapEx & Storage'!G8 -> 9200 | F29: =E29+'CapEx & Storage'!H8 -> 12640 | G29: =F29+'CapEx & Storage'!I8 -> 16230 | H29: =G29+'CapEx & Storage'!J8 -> 20110 | I29: =H29+'CapEx & Storage'!K8 -> 24450 | J29: =I29+'CapEx & Storage'!L8 -> 28940
A30: Expected fencing-days deployed | B30: monthly slab billing | C30: {=INDEX(Simulation!$I$2:$I$41,MATCH(1,(Simulation!$C$2:$C$41="Fencing")*(Simulation!$A$2:$A$41=C$3),0))} -> 108600 | D30: {=INDEX(Simulation!$I$2:$I$41,MATCH(1,(Simulation!$C$2:$C$41="Fencing")*(Simulation!$A$2:$A$41=D$3),0))} -> 114000 | E30: {=INDEX(Simulation!$I$2:$I$41,MATCH(1,(Simulation!$C$2:$C$41="Fencing")*(Simulation!$A$2:$A$41=E$3),0))} -> 119760 | F30: {=INDEX(Simulation!$I$2:$I$41,MATCH(1,(Simulation!$C$2:$C$41="Fencing")*(Simulation!$A$2:$A$41=F$3),0))} -> 125760 | G30: {=INDEX(Simulation!$I$2:$I$41,MATCH(1,(Simulation!$C$2:$C$41="Fencing")*(Simulation!$A$2:$A$41=G$3),0))} -> 138000 | H30: {=INDEX(Simulation!$I$2:$I$41,MATCH(1,(Simulation!$C$2:$C$41="Fencing")*(Simulation!$A$2:$A$41=H$3),0))} -> 149760 | I30: {=INDEX(Simulation!$I$2:$I$41,MATCH(1,(Simulation!$C$2:$C$41="Fencing")*(Simulation!$A$2:$A$41=I$3),0))} -> 161760 | J30: {=INDEX(Simulation!$I$2:$I$41,MATCH(1,(Simulation!$C$2:$C$41="Fencing")*(Simulation!$A$2:$A$41=J$3),0))} -> 173760
A31: Revenue per fencing-days deployed | C31: =Assumptions!$B$21 -> 1.8333333 | D31: =Assumptions!$B$21 -> 1.8333333 | E31: =Assumptions!$B$21 -> 1.8333333 | F31: =Assumptions!$B$21 -> 1.8333333 | G31: =Assumptions!$B$21 -> 1.8333333 | H31: =Assumptions!$B$21 -> 1.8333333 | I31: =Assumptions!$B$21 -> 1.8333333 | J31: =Assumptions!$B$21 -> 1.8333333
A32: Time utilization | B32: asset-days used ÷ asset-days available | C32: =C30/(SUM('CapEx & Storage'!$E$15:E15)*360) -> 0.10191441 | D32: =D30/(SUM('CapEx & Storage'!$E$15:F15)*360) -> 0.10520487 | E32: =E30/(SUM('CapEx & Storage'!$E$15:G15)*360) -> 0.10299278 | F32: =F30/(SUM('CapEx & Storage'!$E$15:H15)*360) -> 0.10155039 | G32: =G30/(SUM('CapEx & Storage'!$E$15:I15)*360) -> 0.10677809 | H32: =H30/(SUM('CapEx & Storage'!$E$15:J15)*360) -> 0.10721649 | I32: =I30/(SUM('CapEx & Storage'!$E$15:K15)*360) -> 0.10353303 | J32: =J30/(SUM('CapEx & Storage'!$E$15:L15)*360) -> 0.10749814
A33: Fencing rental revenue | B33: Exp. fencing-days deployed x revenue per fencing per day | C33: =C31*C30 -> 199100 | D33: =D31*D30 -> 209000 | E33: =E31*E30 -> 219560 | F33: =F31*F30 -> 230560 | G33: =G31*G30 -> 253000 | H33: =H31*H30 -> 274560 | I33: =I31*I30 -> 296560 | J33: =J31*J30 -> 318560 | K33: =SUM(C33:J33) -> 2000900
A34: FLOORING
A35: Fleet (end of year) | C35: ='CapEx & Storage'!E9 -> 740 | D35: =C35+'CapEx & Storage'!F9 -> 1480 | E35: =D35+'CapEx & Storage'!G9 -> 2320 | F35: =E35+'CapEx & Storage'!H9 -> 3200 | G35: =F35+'CapEx & Storage'!I9 -> 4118 | H35: =G35+'CapEx & Storage'!J9 -> 5078 | I35: =H35+'CapEx & Storage'!K9 -> 6118 | J35: =I35+'CapEx & Storage'!L9 -> 7198
A36: Expected flooring-days deployed | B36: monthly slab billing | C36: {=INDEX(Simulation!$I$2:$I$41,MATCH(1,(Simulation!$C$2:$C$41="Flooring")*(Simulation!$A$2:$A$41=C$3),0))} -> 36540 | D36: {=INDEX(Simulation!$I$2:$I$41,MATCH(1,(Simulation!$C$2:$C$41="Flooring")*(Simulation!$A$2:$A$41=D$3),0))} -> 39540 | E36: {=INDEX(Simulation!$I$2:$I$41,MATCH(1,(Simulation!$C$2:$C$41="Flooring")*(Simulation!$A$2:$A$41=E$3),0))} -> 42540 | F36: {=INDEX(Simulation!$I$2:$I$41,MATCH(1,(Simulation!$C$2:$C$41="Flooring")*(Simulation!$A$2:$A$41=F$3),0))} -> 50400 | G36: {=INDEX(Simulation!$I$2:$I$41,MATCH(1,(Simulation!$C$2:$C$41="Flooring")*(Simulation!$A$2:$A$41=G$3),0))} -> 48540 | H36: {=INDEX(Simulation!$I$2:$I$41,MATCH(1,(Simulation!$C$2:$C$41="Flooring")*(Simulation!$A$2:$A$41=H$3),0))} -> 54540 | I36: {=INDEX(Simulation!$I$2:$I$41,MATCH(1,(Simulation!$C$2:$C$41="Flooring")*(Simulation!$A$2:$A$41=I$3),0))} -> 57000 | J36: {=INDEX(Simulation!$I$2:$I$41,MATCH(1,(Simulation!$C$2:$C$41="Flooring")*(Simulation!$A$2:$A$41=J$3),0))} -> 60000
A37: Revenue per flooring-days deployed | C37: =Assumptions!$B$22 -> 30 | D37: =Assumptions!$B$22 -> 30 | E37: =Assumptions!$B$22 -> 30 | F37: =Assumptions!$B$22 -> 30 | G37: =Assumptions!$B$22 -> 30 | H37: =Assumptions!$B$22 -> 30 | I37: =Assumptions!$B$22 -> 30 | J37: =Assumptions!$B$22 -> 30
A38: Time utilization | B38: asset-days used ÷ asset-days available | C38: =C36/(SUM('CapEx & Storage'!$E$16:E16)*360) -> 0.13716216 | D38: =D36/(SUM('CapEx & Storage'!$E$16:F16)*360) -> 0.14842342 | E38: =E36/(SUM('CapEx & Storage'!$E$16:G16)*360) -> 0.1406746 | F38: =F36/(SUM('CapEx & Storage'!$E$16:H16)*360) -> 0.15909091 | G38: =G36/(SUM('CapEx & Storage'!$E$16:I16)*360) -> 0.14687727 | H38: =H36/(SUM('CapEx & Storage'!$E$16:J16)*360) -> 0.1578125 | I38: =I36/(SUM('CapEx & Storage'!$E$16:K16)*360) -> 0.15224359 | J38: =J36/(SUM('CapEx & Storage'!$E$16:L16)*360) -> 0.15432099
A39: Flooring rental revenue | B39: Exp. flooring-days deployed x revenue per flooring per day | C39: =C37*C36 -> 1096200 | D39: =D37*D36 -> 1186200 | E39: =E37*E36 -> 1276200 | F39: =F37*F36 -> 1512000 | G39: =G37*G36 -> 1456200 | H39: =H37*H36 -> 1636200 | I39: =I37*I36 -> 1710000 | J39: =J37*J36 -> 1800000 | K39: =SUM(C39:J39) -> 11673000
A40: TOTAL REVENUE | C40: =SUM(C15,C21,C27,C33,C39) -> 3416424 | D40: =SUM(D15,D21,D27,D33,D39) -> 3639374 | E40: =SUM(E15,E21,E27,E33,E39) -> 3851022 | F40: =SUM(F15,F21,F27,F33,F39) -> 4220234 | G40: =SUM(G15,G21,G27,G33,G39) -> 4403512 | H40: =SUM(H15,H21,H27,H33,H39) -> 4833178 | I40: =SUM(I15,I21,I27,I33,I39) -> 5154078 | J40: =SUM(J15,J21,J27,J33,J39) -> 5491322 | K40: =SUM(K15,K21,K27,K33,K39) -> 35009144

Sheet P&L Projection
A1: P&L & CASH FLOW PROJECTION (5-YEAR)
B2: Driver / Source | C2: Year 1 | D2: Year 2 | E2: Year 3 | F2: Year 4 | G2: Year 5 | H2: Year 6 | I2: Year 7 | J2: Year 8 | K2: 8-Yr Total
A3: FLEET SUMMARY (CUMULATIVE)
A4: Cabin fleet | B4: From CapEx sheet | C4: ='CapEx & Storage'!E12 -> 80 | D4: =C4+'CapEx & Storage'!F12 -> 83 | E4: =D4+'CapEx & Storage'!G12 -> 90 | F4: =E4+'CapEx & Storage'!H12 -> 97 | G4: =F4+'CapEx & Storage'!I12 -> 100 | H4: =G4+'CapEx & Storage'!J12 -> 109 | I4: =H4+'CapEx & Storage'!K12 -> 120 | J4: =I4+'CapEx & Storage'!L12 -> 127 | K4: —
A5: Buggie fleet | B5: From CapEx sheet | C5: ='CapEx & Storage'!E13 -> 26 | D5: =C5+'CapEx & Storage'!F13 -> 28 | E5: =D5+'CapEx & Storage'!G13 -> 30 | F5: =E5+'CapEx & Storage'!H13 -> 34 | G5: =F5+'CapEx & Storage'!I13 -> 34 | H5: =G5+'CapEx & Storage'!J13 -> 38 | I5: =H5+'CapEx & Storage'!K13 -> 42 | J5: =I5+'CapEx & Storage'!L13 -> 46 | K5: —
A6: Barrier fleet | B6: From CapEx sheet | C6: ='CapEx & Storage'!E14 -> 2300 | D6: =C6+'CapEx & Storage'!F14 -> 2408 | E6: =D6+'CapEx & Storage'!G14 -> 2744 | F6: =E6+'CapEx & Storage'!H14 -> 2950 | G6: =F6+'CapEx & Storage'!I14 -> 3094 | H6: =G6+'CapEx & Storage'!J14 -> 3558 | I6: =H6+'CapEx & Storage'!K14 -> 3950 | J6: =I6+'CapEx & Storage'!L14 -> 4264 | K6: —
A7: Fencing fleet | B7: From CapEx sheet | C7: ='CapEx & Storage'!E15 -> 2960 | D7: =C7+'CapEx & Storage'!F15 -> 3010 | E7: =D7+'CapEx & Storage'!G15 -> 3230 | F7: =E7+'CapEx & Storage'!H15 -> 3440 | G7: =F7+'CapEx & Storage'!I15 -> 3590 | H7: =G7+'CapEx & Storage'!J15 -> 3880 | I7: =H7+'CapEx & Storage'!K15 -> 4340 | J7: =I7+'CapEx & Storage'!L15 -> 4490 | K7: —
A8: Flooring fleet | B8: From CapEx sheet | C8: ='CapEx & Storage'!E16 -> 740 | D8: =C8+'CapEx & Storage'!F16 -> 740 | E8: =D8+'CapEx & Storage'!G16 -> 840 | F8: =E8+'CapEx & Storage'!H16 -> 880 | G8: =F8+'CapEx & Storage'!I16 -> 918 | H8: =G8+'CapEx & Storage'!J16 -> 960 | I8: =H8+'CapEx & Storage'!K16 -> 1040 | J8: =I8+'CapEx & Storage'!L16 -> 1080 | K8: —
A10: INCOME STATEMENT | C10: Year 1 | D10: Year 2 | E10: Year 3 | F10: Year 4 | G10: Year 5 | H10: Year 6 | I10: Year 7 | J10: Year 8 | K10: 8-Yr Total
A11: REVENUE
A12: Cabin rental revenue | B12: From Revenue Projection | C12: ='Revenue Projection'!C15 -> 972300 | D12: ='Revenue Projection'!D15 -> 1029350 | E12: ='Revenue Projection'!E15 -> 1086750 | F12: ='Revenue Projection'!F15 -> 1143450 | G12: ='Revenue Projection'!G15 -> 1257200 | H12: ='Revenue Projection'!H15 -> 1370250 | I12: ='Revenue Projection'!I15 -> 1484350 | J12: ='Revenue Projection'!J15 -> 1598450 | K12: =SUM(C12:J12) -> 9942100
A13: Buggie rental revenue | B13: From Revenue Projection | C13: ='Revenue Projection'!C21 -> 1099000 | D13: ='Revenue Projection'!D21 -> 1162000 | E13: ='Revenue Projection'!E21 -> 1212400 | F13: ='Revenue Projection'!F21 -> 1275400 | G13: ='Revenue Projection'!G21 -> 1372000 | H13: ='Revenue Projection'!H21 -> 1481200 | I13: ='Revenue Projection'!I21 -> 1586200 | J13: ='Revenue Projection'!J21 -> 1691200 | K13: =SUM(C13:J13) -> 10879400
A14: Barrier rental revenue | B14: From Revenue Projection | C14: ='Revenue Projection'!C27 -> 49824 | D14: ='Revenue Projection'!D27 -> 52824 | E14: ='Revenue Projection'!E27 -> 56112 | F14: ='Revenue Projection'!F27 -> 58824 | G14: ='Revenue Projection'!G27 -> 65112 | H14: ='Revenue Projection'!H27 -> 70968 | I14: ='Revenue Projection'!I27 -> 76968 | J14: ='Revenue Projection'!J27 -> 83112 | K14: =SUM(C14:J14) -> 513744
A15: Fencing rental revenue | B15: From Revenue Projection | C15: ='Revenue Projection'!C33 -> 199100 | D15: ='Revenue Projection'!D33 -> 209000 | E15: ='Revenue Projection'!E33 -> 219560 | F15: ='Revenue Projection'!F33 -> 230560 | G15: ='Revenue Projection'!G33 -> 253000 | H15: ='Revenue Projection'!H33 -> 274560 | I15: ='Revenue Projection'!I33 -> 296560 | J15: ='Revenue Projection'!J33 -> 318560 | K15: =SUM(C15:J15) -> 2000900
A16: Flooring rental revenue | B16: From Revenue Projection | C16: ='Revenue Projection'!C39 -> 1096200 | D16: ='Revenue Projection'!D39 -> 1186200 | E16: ='Revenue Projection'!E39 -> 1276200 | F16: ='Revenue Projection'!F39 -> 1512000 | G16: ='Revenue Projection'!G39 -> 1456200 | H16: ='Revenue Projection'!H39 -> 1636200 | I16: ='Revenue Projection'!I39 -> 1710000 | J16: ='Revenue Projection'!J39 -> 1800000 | K16: =SUM(C16:J16) -> 11673000
A17: TOTAL REVENUE | C17: =SUM(C12:C16) -> 3416424 | D17: =SUM(D12:D16) -> 3639374 | E17: =SUM(E12:E16) -> 3851022 | F17: =SUM(F12:F16) -> 4220234 | G17: =SUM(G12:G16) -> 4403512 | H17: =SUM(H12:H16) -> 4833178 | I17: =SUM(I12:I16) -> 5154078 | J17: =SUM(J12:J16) -> 5491322 | K17: =SUM(K12:K16) -> 35009144
A19: COST OF REVENUE
A20: Depreciation | B20: From Depreciation Schedule | C20: ='Depreciation Schedule'!H46 -> 884350 | D20: ='Depreciation Schedule'!I46 -> 969697.48 | E20: ='Depreciation Schedule'!J46 -> 1062884 | F20: ='Depreciation Schedule'!K46 -> 1174414.9 | G20: ='Depreciation Schedule'!L46 -> 1278547 | H20: ='Depreciation Schedule'!M46 -> 1307818.4 | I20: ='Depreciation Schedule'!N46 -> 1340810.4 | J20: ='Depreciation Schedule'!O46 -> 1364303.4 | K20: =SUM(C20:J20) -> 9382825.6
A21: Cabin asset maintenance | B21: 2.5% × cumulative cabin CapEx | C21: =SUM('CapEx & Storage'!$E$18:E18)*Assumptions!$B$28 -> 166452.5 | D21: =SUM('CapEx & Storage'!$E$18:F18)*Assumptions!$B$28 -> 185559.65 | E21: =SUM('CapEx & Storage'!$E$18:G18)*Assumptions!$B$28 -> 203282.86 | F21: =SUM('CapEx & Storage'!$E$18:H18)*Assumptions!$B$28 -> 225395.79 | G21: =SUM('CapEx & Storage'!$E$18:I18)*Assumptions!$B$28 -> 249290.48 | H21: =SUM('CapEx & Storage'!$E$18:J18)*Assumptions!$B$28 -> 249290.48 | I21: =SUM('CapEx & Storage'!$E$18:K18)*Assumptions!$B$28 -> 249290.48 | J21: =SUM('CapEx & Storage'!$E$18:L18)*Assumptions!$B$28 -> 249290.48 | K21: =SUM(C21:J21) -> 1777852.7
A22: Buggie maintenance | B22: 2.5% × cumulative buggie CapEx | C22: =SUM('CapEx & Storage'!$E$19:E19)*Assumptions!$B$32 -> 26000 | D22: =SUM('CapEx & Storage'!$E$19:F19)*Assumptions!$B$32 -> 28040 | E22: =SUM('CapEx & Storage'!$E$19:G19)*Assumptions!$B$32 -> 30120.8 | F22: =SUM('CapEx & Storage'!$E$19:H19)*Assumptions!$B$32 -> 34365.632 | G22: =SUM('CapEx & Storage'!$E$19:I19)*Assumptions!$B$32 -> 34365.632 | H22: =SUM('CapEx & Storage'!$E$19:J19)*Assumptions!$B$32 -> 38781.955 | I22: =SUM('CapEx & Storage'!$E$19:K19)*Assumptions!$B$32 -> 43286.605 | J22: =SUM('CapEx & Storage'!$E$19:L19)*Assumptions!$B$32 -> 47881.348 | K22: =SUM(C22:J22) -> 282841.97
A23: Barrier & fencing maintenance | B23: 0.5% × cumulative barrier & fencing CapEx | C23: =SUM('CapEx & Storage'!$E$20:E21)*Assumptions!$B$37 -> 9370 | D23: =SUM('CapEx & Storage'!$E$20:F21)*Assumptions!$B$37 -> 9637.24 | E23: =SUM('CapEx & Storage'!$E$20:G21)*Assumptions!$B$37 -> 10619.378 | F23: =SUM('CapEx & Storage'!$E$20:H21)*Assumptions!$B$37 -> 11392.998 | G23: =SUM('CapEx & Storage'!$E$20:I21)*Assumptions!$B$37 -> 11951.533 | H23: =SUM('CapEx & Storage'!$E$20:J21)*Assumptions!$B$37 -> 13360.34 | I23: =SUM('CapEx & Storage'!$E$20:K21)*Assumptions!$B$37 -> 15058.593 | J23: =SUM('CapEx & Storage'!$E$20:L21)*Assumptions!$B$37 -> 15944.23 | K23: =SUM(C23:J23) -> 97334.313
A24: Flooring maintenance | B24: 0.5% × cumulative flooring CapEx | C24: =SUM('CapEx & Storage'!$E$22:E22)*Assumptions!$B$41 -> 1850 | D24: =SUM('CapEx & Storage'!$E$22:F22)*Assumptions!$B$41 -> 1850 | E24: =SUM('CapEx & Storage'!$E$22:G22)*Assumptions!$B$41 -> 2110.1 | F24: =SUM('CapEx & Storage'!$E$22:H22)*Assumptions!$B$41 -> 2216.2208 | G24: =SUM('CapEx & Storage'!$E$22:I22)*Assumptions!$B$41 -> 2319.0519 | H24: =SUM('CapEx & Storage'!$E$22:J22)*Assumptions!$B$41 -> 2434.9803 | I24: =SUM('CapEx & Storage'!$E$22:K22)*Assumptions!$B$41 -> 2660.2128 | J24: =SUM('CapEx & Storage'!$E$22:L22)*Assumptions!$B$41 -> 2775.0814 | K24: =SUM(C24:J24) -> 18215.647
A25: COST OF REVENUE | C25: =SUM(C20:C24) -> 1088022.5 | D25: =SUM(D20:D24) -> 1194784.4 | E25: =SUM(E20:E24) -> 1309017.2 | F25: =SUM(F20:F24) -> 1447785.5 | G25: =SUM(G20:G24) -> 1576473.7 | H25: =SUM(H20:H24) -> 1611686.1 | I25: =SUM(I20:I24) -> 1651106.3 | J25: =SUM(J20:J24) -> 1680194.5 | K25: =SUM(K20:K24) -> 11559070
A26: GROSS PROFIT | C26: =C17-C25 -> 2328401.5 | D26: =D17-D25 -> 2444589.6 | E26: =E17-E25 -> 2542004.8 | F26: =F17-F25 -> 2772448.5 | G26: =G17-G25 -> 2827038.3 | H26: =H17-H25 -> 3221491.9 | I26: =I17-I25 -> 3502971.7 | J26: =J17-J25 -> 3811127.5 | K26: =K17-K25 -> 23450074
A27: Gross margin % | C27: =IF(C17<>0,C26/C17,0) -> 0.68153177 | D27: =IF(D17<>0,D26/D17,0) -> 0.67170608 | E27: =IF(E17<>0,E26/E17,0) -> 0.66008577 | F27: =IF(F17<>0,F26/F17,0) -> 0.65694189 | G27: =IF(G17<>0,G26/G17,0) -> 0.64199628 | H27: =IF(H17<>0,H26/H17,0) -> 0.66653698 | I27: =IF(I17<>0,I26/I17,0) -> 0.6796505 | J27: =IF(J17<>0,J26/J17,0) -> 0.69402732 | K27: =IF(K17<>0,K26/K17,0) -> 0.66982711
A29: OPERATING EXPENSES
A30: Yard rent (Storage) | B30: From CapEx & Inventory schedule | C30: ='CapEx & Storage'!E63 -> 315888.47 | D30: ='CapEx & Storage'!F63 -> 372409.76 | E30: ='CapEx & Storage'!G63 -> 436325.86 | F30: ='CapEx & Storage'!H63 -> 506269.74 | G30: ='CapEx & Storage'!I63 -> 579647.32 | H30: ='CapEx & Storage'!J63 -> 649859.76 | I30: ='CapEx & Storage'!K63 -> 728545.56 | J30: ='CapEx & Storage'!L63 -> 816324.71 | K30: =SUM(C30:J30) -> 4405271.2
A31: Staff costs | B31: From Human Resources schedule | C31: ='Human Resources'!D32 -> 492000 | D31: ='Human Resources'!E32 -> 534000 | E31: ='Human Resources'!F32 -> 685680 | F31: ='Human Resources'!G32 -> 741018 | G31: ='Human Resources'!H32 -> 917916.9 | H31: ='Human Resources'!I32 -> 1050549.6 | I31: ='Human Resources'!J32 -> 1259749.1 | J31: ='Human Resources'!K32 -> 1353561.8 | K31: =SUM(C31:J31) -> 7034475.4
A32: Office rent | B32: From Human Resources schedule | C32: ='Human Resources'!D38 -> 120000 | D32: ='Human Resources'!E38 -> 126000 | E32: ='Human Resources'!F38 -> 132300 | F32: ='Human Resources'!G38 -> 138915 | G32: ='Human Resources'!H38 -> 145860.75 | H32: ='Human Resources'!I38 -> 183784.55 | I32: ='Human Resources'!J38 -> 192973.77 | J32: ='Human Resources'!K38 -> 202622.46 | K32: =SUM(C32:J32) -> 1242456.5
A33: Marketing | B33: From Assumptions | C33: =Assumptions!$B$48*12 -> 120000 | D33: =Assumptions!$B$48*12 -> 120000 | E33: =Assumptions!$B$48*12 -> 120000 | F33: =Assumptions!$B$48*12 -> 120000 | G33: =Assumptions!$B$48*12 -> 120000 | H33: =Assumptions!$B$48*12 -> 120000 | I33: =Assumptions!$B$48*12 -> 120000 | J33: =Assumptions!$B$48*12 -> 120000 | K33: =SUM(C33:J33) -> 960000
A34: DEWA + utilities | B34: From Assumptions | C34: =Assumptions!B49*12 -> 18000 | D34: =C34*(1+Assumptions!$B$52) -> 18900 | E34: =D34*(1+Assumptions!$B$52) -> 19845 | F34: =E34*(1+Assumptions!$B$52) -> 20837.25 | G34: =F34*(1+Assumptions!$B$52) -> 21879.112 | H34: =G34*(1+Assumptions!$B$52) -> 22973.068 | I34: =H34*(1+Assumptions!$B$52) -> 24121.722 | J34: =I34*(1+Assumptions!$B$52) -> 25327.808 | K34: =SUM(C34:J34) -> 171883.96
A35: Insurance | B35: From Assumptions | C35: =Assumptions!B50 -> 22000 | D35: =C35*(1+Assumptions!$B$52) -> 23100 | E35: =D35*(1+Assumptions!$B$52) -> 24255 | F35: =E35*(1+Assumptions!$B$52) -> 25467.75 | G35: =F35*(1+Assumptions!$B$52) -> 26741.138 | H35: =G35*(1+Assumptions!$B$52) -> 28078.194 | I35: =H35*(1+Assumptions!$B$52) -> 29482.104 | J35: =I35*(1+Assumptions!$B$52) -> 30956.209 | K35: =SUM(C35:J35) -> 210080.4
A36: Misc / contingency | B36: From Assumptions | C36: =Assumptions!B51 -> 50000 | D36: =C36*(1+Assumptions!$B$52) -> 52500 | E36: =D36*(1+Assumptions!$B$52) -> 55125 | F36: =E36*(1+Assumptions!$B$52) -> 57881.25 | G36: =F36*(1+Assumptions!$B$52) -> 60775.312 | H36: =G36*(1+Assumptions!$B$52) -> 63814.078 | I36: =H36*(1+Assumptions!$B$52) -> 67004.782 | J36: =I36*(1+Assumptions!$B$52) -> 70355.021 | K36: =SUM(C36:J36) -> 477455.44
A37: TOTAL OPERATING EXPENSES | C37: =SUM(C30:C36) -> 1137888.5 | D37: =SUM(D30:D36) -> 1246909.8 | E37: =SUM(E30:E36) -> 1473530.9 | F37: =SUM(F30:F36) -> 1610389 | G37: =SUM(G30:G36) -> 1872820.5 | H37: =SUM(H30:H36) -> 2119059.2 | I37: =SUM(I30:I36) -> 2421877.1 | J37: =SUM(J30:J36) -> 2619148 | K37: =SUM(K30:K36) -> 14501623
A38: EBITDA | B38: Gross Profit − OPEX excl. depreciation | C38: =C26-C37+C20 -> 2074863 | D38: =D26-D37+D20 -> 2167377.4 | E38: =E26-E37+E20 -> 2131358 | F38: =F26-F37+F20 -> 2336474.4 | G38: =G26-G37+G20 -> 2232764.8 | H38: =H26-H37+H20 -> 2410251 | I38: =I26-I37+I20 -> 2421905 | J38: =J26-J37+J20 -> 2556282.9 | K38: =K26-K37+K20 -> 18331276
A39: EBITDA margin % | C39: =IF(C17<>0,C38/C17,0) -> 0.60732012 | D39: =IF(D17<>0,D38/D17,0) -> 0.59553576 | E39: =IF(E17<>0,E38/E17,0) -> 0.55345256 | F39: =IF(F17<>0,F38/F17,0) -> 0.55363621 | G39: =IF(G17<>0,G38/G17,0) -> 0.50704183 | H39: =IF(H17<>0,H38/H17,0) -> 0.49868865 | I39: =IF(I17<>0,I38/I17,0) -> 0.46990073 | J39: =IF(J17<>0,J38/J17,0) -> 0.46551321 | K39: =IF(K17<>0,K38/K17,0) -> 0.52361396
A40: EBIT (after depreciation) | C40: =C26-C37 -> 1190513 | D40: =D26-D37 -> 1197679.9 | E40: =E26-E37 -> 1068474 | F40: =F26-F37 -> 1162059.5 | G40: =G26-G37 -> 954217.77 | H40: =H26-H37 -> 1102432.6 | I40: =I26-I37 -> 1081094.6 | J40: =J26-J37 -> 1191979.5 | K40: =K26-K37 -> 8948450.9
A41: EBIT margin % | C41: =IF(C17<>0,C40/C17,0) -> 0.34846759 | D41: =IF(D17<>0,D40/D17,0) -> 0.32908953 | E41: =IF(E17<>0,E40/E17,0) -> 0.27745206 | F41: =IF(F17<>0,F40/F17,0) -> 0.27535428 | G41: =IF(G17<>0,G40/G17,0) -> 0.21669471 | H41: =IF(H17<>0,H40/H17,0) -> 0.22809683 | I41: =IF(I17<>0,I40/I17,0) -> 0.20975519 | J41: =IF(J17<>0,J40/J17,0) -> 0.21706604 | K41: =IF(K17<>0,K40/K17,0) -> 0.25560325
A43: INTEREST EXPENSES & TAXES
A44: Interest Expenses | B44: N/A | C44: 0 | D44: 0 | E44: 0 | F44: 0 | G44: 0 | H44: 0 | I44: 0 | J44: 0 | K44: =SUM(C44:J44) -> 0
A45: UAE federal corporate tax | B45: 9% on taxable profit in excess of AED 375k | C45: =MAX((C40-C44-375000)*9%,0) -> 73396.173 | D45: =MAX((D40-D44-375000)*9%,0) -> 74041.188 | E45: =MAX((E40-E44-375000)*9%,0) -> 62412.658 | F45: =MAX((F40-F44-375000)*9%,0) -> 70835.355 | G45: =MAX((G40-G44-375000)*9%,0) -> 52129.6 | H45: =MAX((H40-H44-375000)*9%,0) -> 65468.934 | I45: =MAX((I40-I44-375000)*9%,0) -> 63548.513 | J45: =MAX((J40-J44-375000)*9%,0) -> 73528.158 | K45: =SUM(C45:J45) -> 535360.58
A46: NET PROFIT | C46: =C40-C44-C45 -> 1117116.9 | D46: =D40-D44-D45 -> 1123638.7 | E46: =E40-E44-E45 -> 1006061.3 | F46: =F40-F44-F45 -> 1091224.1 | G46: =G40-G44-G45 -> 902088.17 | H46: =H40-H44-H45 -> 1036963.7 | I46: =I40-I44-I45 -> 1017546.1 | J46: =J40-J44-J45 -> 1118451.4 | K46: =K40-K44-K45 -> 8413090.3
A49: CASH FLOW | C49: Year 1 | D49: Year 2 | E49: Year 3 | F49: Year 4 | G49: Year 5 | H49: Year 6 | I49: Year 7 | J49: Year 8 | K49: 8-Yr Total
A50: OPERATING CASH FLOWS
A51: (+) Revenue | C51: =C17 -> 3416424 | D51: =D17 -> 3639374 | E51: =E17 -> 3851022 | F51: =F17 -> 4220234 | G51: =G17 -> 4403512 | H51: =H17 -> 4833178 | I51: =I17 -> 5154078 | J51: =J17 -> 5491322 | K51: =SUM(C51:J51) -> 35009144
A52: (-) Cost of revenue | C52: =-C25 -> -1088022.5 | D52: =-D25 -> -1194784.4 | E52: =-E25 -> -1309017.2 | F52: =-F25 -> -1447785.5 | G52: =-G25 -> -1576473.7 | H52: =-H25 -> -1611686.1 | I52: =-I25 -> -1651106.3 | J52: =-J25 -> -1680194.5 | K52: =SUM(C52:J52) -> -11559070
A53: (-) Operating expenses | C53: =-C37 -> -1137888.5 | D53: =-D37 -> -1246909.8 | E53: =-E37 -> -1473530.9 | F53: =-F37 -> -1610389 | G53: =-G37 -> -1872820.5 | H53: =-H37 -> -2119059.2 | I53: =-I37 -> -2421877.1 | J53: =-J37 -> -2619148 | K53: =SUM(C53:J53) -> -14501623
A54: (-) Taxes | C54: =-C45 -> -73396.173 | D54: =-D45 -> -74041.188 | E54: =-E45 -> -62412.658 | F54: =-F45 -> -70835.355 | G54: =-G45 -> -52129.6 | H54: =-H45 -> -65468.934 | I54: =-I45 -> -63548.513 | J54: =-J45 -> -73528.158 | K54: =SUM(C54:J54) -> -535360.58
A55: (+) Non-cash expenses | C55: =C20 -> 884350 | D55: =D20 -> 969697.48 | E55: =E20 -> 1062884 | F55: =F20 -> 1174414.9 | G55: =G20 -> 1278547 | H55: =H20 -> 1307818.4 | I55: =I20 -> 1340810.4 | J55: =J20 -> 1364303.4 | K55: =SUM(C55:J55) -> 9382825.6
A56: Net cash from operations | C56: =SUM(C51:C55) -> 2001466.9 | D56: =SUM(D51:D55) -> 2093336.2 | E56: =SUM(E51:E55) -> 2068945.3 | F56: =SUM(F51:F55) -> 2265639 | G56: =SUM(G51:G55) -> 2180635.2 | H56: =SUM(H51:H55) -> 2344782.1 | I56: =SUM(I51:I55) -> 2358356.5 | J56: =SUM(J51:J55) -> 2482754.7 | K56: =SUM(C56:J56) -> 17795916
A57: INVESTING CASH FLOWS
A58: (-) Cabin purchase expenditure | C58: =-'CapEx & Storage'!E18 -> -6658100 | D58: =-'CapEx & Storage'!F18 -> -764286 | E58: =-'CapEx & Storage'!G18 -> -708928.56 | F58: =-'CapEx & Storage'!H18 -> -884516.87 | G58: =-'CapEx & Storage'!I18 -> -955787.6 | H58: =-'CapEx & Storage'!J18 -> 0 | I58: =-'CapEx & Storage'!K18 -> 0 | J58: =-'CapEx & Storage'!L18 -> 0 | K58: =SUM(C58:J58) -> -9971619
A59: (-) Buggie purchase expenditure | C59: =-'CapEx & Storage'!E19 -> -1040000 | D59: =-'CapEx & Storage'!F19 -> -81600 | E59: =-'CapEx & Storage'!G19 -> -83232 | F59: =-'CapEx & Storage'!H19 -> -169793.28 | G59: =-'CapEx & Storage'!I19 -> 0 | H59: =-'CapEx & Storage'!J19 -> -176652.93 | I59: =-'CapEx & Storage'!K19 -> -180185.99 | J59: =-'CapEx & Storage'!L19 -> -183789.71 | K59: =SUM(C59:J59) -> -1915253.9
A60: (-) Barrier purchase expenditure | C60: =-'CapEx & Storage'!E20 -> -690000 | D60: =-'CapEx & Storage'!F20 -> -33048 | E60: =-'CapEx & Storage'!G20 -> -104872.32 | F60: =-'CapEx & Storage'!H20 -> -65582.654 | G60: =-'CapEx & Storage'!I20 -> -46761.069 | H60: =-'CapEx & Storage'!J20 -> -153688.05 | I60: =-'CapEx & Storage'!K20 -> -132436.7 | J60: =-'CapEx & Storage'!L20 -> -108206.19 | K60: =SUM(C60:J60) -> -1334595
A61: (-) Fencing purchase expenditure | C61: =-'CapEx & Storage'!E21 -> -1184000 | D61: =-'CapEx & Storage'!F21 -> -20400 | E61: =-'CapEx & Storage'!G21 -> -91555.2 | F61: =-'CapEx & Storage'!H21 -> -89141.472 | G61: =-'CapEx & Storage'!I21 -> -64945.93 | H61: =-'CapEx & Storage'!J21 -> -128073.37 | I61: =-'CapEx & Storage'!K21 -> -207213.89 | J61: =-'CapEx & Storage'!L21 -> -68921.14 | K61: =SUM(C61:J61) -> -1854251
A62: (-) Flooring purchase expenditure | C62: =-'CapEx & Storage'!E22 -> -370000 | D62: =-'CapEx & Storage'!F22 -> 0 | E62: =-'CapEx & Storage'!G22 -> -52020 | F62: =-'CapEx & Storage'!H22 -> -21224.16 | G62: =-'CapEx & Storage'!I22 -> -20566.211 | H62: =-'CapEx & Storage'!J22 -> -23185.697 | I62: =-'CapEx & Storage'!K22 -> -45046.497 | J62: =-'CapEx & Storage'!L22 -> -22973.713 | K62: =SUM(C62:J62) -> -555016.28
A63: Net cash from investing | C63: =SUM(C58:C62) -> -9942100 | D63: =SUM(D58:D62) -> -899334 | E63: =SUM(E58:E62) -> -1040608.1 | F63: =SUM(F58:F62) -> -1230258.4 | G63: =SUM(G58:G62) -> -1088060.8 | H63: =SUM(H58:H62) -> -481600.05 | I63: =SUM(I58:I62) -> -564883.07 | J63: =SUM(J58:J62) -> -383890.75 | K63: =SUM(C63:J63) -> -15630735
A64: FINANCING CASH FLOWS
A65: (+) Equity capital raised | C65: 4470950
A66: (+) Debt capital raised | C66: 5000000
A67: (-) Debt capital paid back | D67: -1000000 | E67: -1000000 | F67: -1000000 | G67: -1000000 | H67: -1000000
A68: Net cash from investing | C68: =SUM(C65:C67) -> 9470950 | D68: =SUM(D65:D67) -> -1000000 | E68: =SUM(E65:E67) -> -1000000 | F68: =SUM(F65:F67) -> -1000000 | G68: =SUM(G65:G67) -> -1000000 | H68: =SUM(H65:H67) -> -1000000 | I68: =SUM(I65:I67) -> 0 | J68: =SUM(J65:J67) -> 0 | K68: =SUM(C68:G68) -> 5470950
A70: Net change in cash | C70: =C68+C63+C56 -> 1530316.9 | D70: =D68+D63+D56 -> 194002.16 | E70: =E68+E63+E56 -> 28337.265 | F70: =F68+F63+F56 -> 35380.581 | G70: =G68+G63+G56 -> 92574.371 | H70: =H68+H63+H56 -> 863182.02 | I70: =I68+I63+I56 -> 1793473.5 | J70: =J68+J63+J56 -> 2098864 | K70: =K56+K63 -> 2165180.7
A71: Starting balance | C71: 0 | D71: =C72 -> 1530316.9 | E71: =D72 -> 1724319 | F71: =E72 -> 1752656.3 | G71: =F72 -> 1788036.9 | H71: =G72 -> 1880611.2 | I71: =H72 -> 2743793.3 | J71: =I72 -> 4537266.7
A72: Closing balance | C72: =C71+C70 -> 1530316.9 | D72: =D71+D70 -> 1724319 | E72: =E71+E70 -> 1752656.3 | F72: =F71+F70 -> 1788036.9 | G72: =G71+G70 -> 1880611.2 | H72: =H71+H70 -> 2743793.3 | I72: =I71+I70 -> 4537266.7 | J72: =J71+J70 -> 6636130.7

Sheet Simulation
A1: Year | B1: New Events | C1: Asset | D1: 0.5 | E1: 0.75 | F1: 0.85 | G1: 0.95 | H1: Asset Days (Mean) | I1: Asset Days (Median) | J1: Signed (Mean) | K1: Signed (Median)
A2: 1 | B2: 0 | C2: Cabins | D2: 56 | E2: 72 | F2: 80 | G2: 91 | H2: 2779 | I2: 2778 | J2: 5.9987183 | K2: 6
A3: 1 | B3: 0 | C3: Buggies | D3: 26 | E3: 34 | F3: 36 | G3: 42 | H3: 1590 | I3: 1570 | J3: 5.9987183 | K3: 6
A4: 1 | B4: 0 | C4: Barriers | D4: 1894 | E4: 2275 | F4: 2300 | G4: 2594 | H4: 125084 | I4: 124560 | J4: 5.9987183 | K4: 6
A5: 1 | B5: 0 | C5: Fencing | D5: 1910 | E5: 2490 | F5: 2960 | G5: 3590 | H5: 107926 | I5: 108600 | J5: 5.9987183 | K5: 6
A6: 1 | B6: 0 | C6: Flooring | D6: 480 | E6: 680 | F6: 740 | G6: 880 | H6: 43459 | I6: 36540 | J6: 5.9987183 | K6: 6
A7: 2 | B7: 1 | C7: Cabins | D7: 58 | E7: 75 | F7: 83 | G7: 97 | H7: 2941 | I7: 2941 | J7: 6.4988317 | K7: 6
A8: 2 | B8: 1 | C8: Buggies | D8: 28 | E8: 34 | F8: 38 | G8: 44 | H8: 1664 | I8: 1660 | J8: 6.4988317 | K8: 6
A9: 2 | B9: 1 | C9: Barriers | D9: 1950 | E9: 2275 | F9: 2408 | G9: 2800 | H9: 132611 | I9: 132060 | J9: 6.4988317 | K9: 6
A10: 2 | B10: 1 | C10: Fencing | D10: 1940 | E10: 2680 | F10: 3010 | G10: 3590 | H10: 113906 | I10: 114000 | J10: 6.4988317 | K10: 6
A11: 2 | B11: 1 | C11: Flooring | D11: 540 | E11: 680 | F11: 740 | G11: 918 | H11: 44961 | I11: 39540 | J11: 6.4988317 | K11: 6
A12: 3 | B12: 1 | C12: Cabins | D12: 65 | E12: 81 | F12: 90 | G12: 104 | H12: 3104 | I12: 3105 | J12: 7.0027966 | K12: 7
A13: 3 | B13: 1 | C13: Buggies | D13: 30 | E13: 38 | F13: 40 | G13: 46 | H13: 1738 | I13: 1732 | J13: 7.0027966 | K13: 7
... A41: 8 | B41: 2 | C41: Flooring | D41: 858 | E41: 1018 | F41: 1080 | G41: 1240 | H41: 59986 | I41: 60000 | J41: 11.500706 | K41: 11.5
